Workbook
Name _bdm.FastTrackBookmark.1_11_2024_10_14_49_AM.edm: #REF!
Name _bdm.FastTrackBookmark.1_14_2019_9_35_13_AM.edm: #REF!
Name _bdm.FastTrackBookmark.1_14_2019_9_35_13_AM.edm: #REF!
Name _bdm.FastTrackBookmark.1_14_2019_9_35_13_AM.edm: #REF!
Name _bdm.FastTrackBookmark.11_1_2023_1_59_16_PM.edm: Sand!$X$143
Name A_ALL_AESI: #REF!
Name A_ALL_AESI: AESI_Annotation_Sheet!$A$1:$AT$315
Name A_ALL_KEYWORDS_TYPE_ScalarContributed_EQTY_200022132: AESI_Annotation_Sheet!$248:$248,AESI_Annotation_Sheet!$251:$261,AESI_Annotation_Sheet!$302:$302,AESI_Annotation_Sheet!$306:$308,AESI_Annotation_Sheet!$313:$315
Name A_ALL_KEYWORDS_TYPE_ScalarContributed_EQTY_200022132: AESI_Annotation_Sheet!$248:$248,AESI_Annotation_Sheet!$302:$302,AESI_Annotation_Sheet!$306:$308,AESI_Annotation_Sheet!$313:$315,AESI_Annotation_Sheet!$251:$261
Name A_ALL_KEYWORDS_TYPE_ScalarContributed_ISSR_208021701: AESI_Annotation_Sheet!$9:$9,AESI_Annotation_Sheet!$39:$39
Name A_ALL_KEYWORDS_TYPE_ScalarReference_EQTY_200022132: AESI_Annotation_Sheet!$241:$246
Name A_ALL_KEYWORDS_TYPE_ScalarReference_ISSR_208021701: AESI_Annotation_Sheet!$6:$7
Name A_ALL_PERIODS_AESI: AESI_Annotation_Sheet!$F$1:$AT$1
Name A_ALL_SECTION_KEYWORDS_EQTY_200000592_13K: #REF!
Name A_ALL_SECTION_KEYWORDS_EQTY_200000592_13K: #REF!
Name A_ALL_SECTION_KEYWORDS_EQTY_200022132_1314: AESI_Annotation_Sheet!$C$304
Name A_ALL_SECTION_KEYWORDS_EQTY_200022132_1319: AESI_Annotation_Sheet!$C$306:$C$309
Name A_ALL_SECTION_KEYWORDS_EQTY_200022132_131E: AESI_Annotation_Sheet!$C$311
Name A_ALL_SECTION_KEYWORDS_EQTY_200022132_131O: AESI_Annotation_Sheet!$C$313:$C$315
Name A_ALL_SECTION_KEYWORDS_EQTY_200022132_13A: AESI_Annotation_Sheet!$C$248:$C$261
Name A_ALL_SECTION_KEYWORDS_EQTY_200022132_13A: AESI_Annotation_Sheet!$C$248:$C$261
Name A_ALL_SECTION_KEYWORDS_EQTY_200022132_13K: AESI_Annotation_Sheet!$C$263:$C$277
Name A_ALL_SECTION_KEYWORDS_EQTY_200022132_13U: AESI_Annotation_Sheet!$C$279:$C$294
Name A_ALL_SECTION_KEYWORDS_EQTY_200022132_13V: AESI_Annotation_Sheet!$C$296
Name A_ALL_SECTION_KEYWORDS_EQTY_200022132_13W: AESI_Annotation_Sheet!$C$298:$C$302
Name A_ALL_SECTION_KEYWORDS_EQTY_200022132_Reference_Data: AESI_Annotation_Sheet!$C$241:$C$246
Name A_ALL_SECTION_KEYWORDS_ISSR_208000084_136J: #REF!,#REF!
Name A_ALL_SECTION_KEYWORDS_ISSR_208000084_136J: #REF!,#REF!
Name A_ALL_SECTION_KEYWORDS_ISSR_208021701_1314: AESI_Annotation_Sheet!$C$41:$C$70
Name A_ALL_SECTION_KEYWORDS_ISSR_208021701_13168: AESI_Annotation_Sheet!$C$132:$C$193
Name A_ALL_SECTION_KEYWORDS_ISSR_208021701_1316S: AESI_Annotation_Sheet!$C$195:$C$200
Name A_ALL_SECTION_KEYWORDS_ISSR_208021701_1316T: AESI_Annotation_Sheet!$C$202:$C$211
Name A_ALL_SECTION_KEYWORDS_ISSR_208021701_1316U: AESI_Annotation_Sheet!$C$213:$C$227
Name A_ALL_SECTION_KEYWORDS_ISSR_208021701_1319: AESI_Annotation_Sheet!$C$72:$C$90
Name A_ALL_SECTION_KEYWORDS_ISSR_208021701_131E: AESI_Annotation_Sheet!$C$92:$C$108
Name A_ALL_SECTION_KEYWORDS_ISSR_208021701_131J: AESI_Annotation_Sheet!$C$110:$C$122
Name A_ALL_SECTION_KEYWORDS_ISSR_208021701_131O: AESI_Annotation_Sheet!$C$124
Name A_ALL_SECTION_KEYWORDS_ISSR_208021701_131O: AESI_Annotation_Sheet!$C$124,AESI_Annotation_Sheet!$C$126
Name A_ALL_SECTION_KEYWORDS_ISSR_208021701_131P: AESI_Annotation_Sheet!$C$128:$C$130
Name A_ALL_SECTION_KEYWORDS_ISSR_208021701_136E: AESI_Annotation_Sheet!$C$229:$C$238
Name A_ALL_SECTION_KEYWORDS_ISSR_208021701_13A: AESI_Annotation_Sheet!$C$9
Name A_ALL_SECTION_KEYWORDS_ISSR_208021701_13U: AESI_Annotation_Sheet!$C$11:$C$30
Name A_ALL_SECTION_KEYWORDS_ISSR_208021701_13V: AESI_Annotation_Sheet!$C$32:$C$39
Name A_ALL_SECTION_KEYWORDS_ISSR_208021701_Reference_Data: AESI_Annotation_Sheet!$C$6:$C$7
Name A_ALL_SLB: #REF!
Name A_ALL_SLB: #REF!
Name A_CURRENCY_EQTY_200022132_PRI: AESI_Annotation_Sheet!$E$245
Name A_CURRENCY_EQTY_200022132_PUB: AESI_Annotation_Sheet!$E$244
Name A_CURRENCY_EQTY_200022132_REP: AESI_Annotation_Sheet!$E$246
Name A_CURRENCY_ISSR_208021701_REP: AESI_Annotation_Sheet!$E$7
Name A_ENTITY_DATA_EQTY_200022132: AESI_Annotation_Sheet!$E$240:$AT$315
Name A_ENTITY_DATA_ISSR_208021701: AESI_Annotation_Sheet!$E$5:$AT$238
Name A_KEYWORD_EQTY_200022132_AMER_CONVICTION: AESI_Annotation_Sheet!$250:$250
Name A_KEYWORD_EQTY_200022132_AMER_LIST: AESI_Annotation_Sheet!$248:$248
Name A_KEYWORD_EQTY_200022132_BETA_ANALYST: AESI_Annotation_Sheet!$313:$313
Name A_KEYWORD_EQTY_200022132_BVPS: AESI_Annotation_Sheet!$304:$304
Name A_KEYWORD_EQTY_200022132_BVPS_PUB: AESI_Annotation_Sheet!$263:$263
Name A_KEYWORD_EQTY_200022132_CEEE_NDEBT: AESI_Annotation_Sheet!$272:$272
Name A_KEYWORD_EQTY_200022132_CF_NI_PRE_PREF: AESI_Annotation_Sheet!$311:$311
Name A_KEYWORD_EQTY_200022132_COMMON_DIV_PAID: AESI_Annotation_Sheet!$290:$290

Sheet __FDSCACHE__
B1: This sheet contains FactSet XML data for use with this workbook's =FDS codes. Modifying the worksheet's contents may damage the workbook's =FDS functionality.

Sheet Summary
A2: x | B2: Atlas Energy Solutions
B3: Summary Sheet
B4: (US$ Millions)
C6: 2020 | D6: 2021 | E6: 2022 | F6: 2023 | G6: 2024 | H6: 2025 | I6: 2026 | J6: 2027 | K6: 2028
B8: Revenue
B9: Sand Revenue | C9: {=INDEX('Income Statement'!$DE$9:$EB$9,MATCH(Summary!C$6,'Income Statement'!$DE$5:$EB$5,0))} -> 79.869601 | D9: {=INDEX('Income Statement'!$DE$9:$EB$9,MATCH(Summary!D$6,'Income Statement'!$DE$5:$EB$5,0))} -> 142.5198 | E9: {=INDEX('Income Statement'!$DE$9:$EB$9,MATCH(Summary!E$6,'Income Statement'!$DE$5:$EB$5,0))} -> 408.32798 | F9: {=INDEX('Income Statement'!$DE$9:$EB$9,MATCH(Summary!F$6,'Income Statement'!$DE$5:$EB$5,0))} -> 468.119 | G9: {=INDEX('Income Statement'!$DE$9:$EB$9,MATCH(Summary!G$6,'Income Statement'!$DE$5:$EB$5,0))} -> 515.434 | H9: {=INDEX('Income Statement'!$DE$9:$EB$9,MATCH(Summary!H$6,'Income Statement'!$DE$5:$EB$5,0))} -> 629.80808 | I9: {=INDEX('Income Statement'!$DE$9:$EB$9,MATCH(Summary!I$6,'Income Statement'!$DE$5:$EB$5,0))} -> 687.46864 | J9: {=INDEX('Income Statement'!$DE$9:$EC$9,MATCH(Summary!J$6,'Income Statement'!$DE$5:$EC$5,0))} -> 727.51171 | K9: {=INDEX('Income Statement'!$DE$9:$EC$9,MATCH(Summary!K$6,'Income Statement'!$DE$5:$EC$5,0))} -> 748.24488
B10: Logistics Revenue | C10: {=INDEX('Income Statement'!$DE$10:$EC$10,MATCH(Summary!C$6,'Income Statement'!$DE$5:$EC$5,0))} -> 31.902027 | D10: {=INDEX('Income Statement'!$DE$10:$EC$10,MATCH(Summary!D$6,'Income Statement'!$DE$5:$EC$5,0))} -> 29.885861 | E10: {=INDEX('Income Statement'!$DE$10:$EC$10,MATCH(Summary!E$6,'Income Statement'!$DE$5:$EC$5,0))} -> 74.265797 | F10: {=INDEX('Income Statement'!$DE$10:$EC$10,MATCH(Summary!F$6,'Income Statement'!$DE$5:$EC$5,0))} -> 145.841 | G10: {=INDEX('Income Statement'!$DE$10:$EC$10,MATCH(Summary!G$6,'Income Statement'!$DE$5:$EC$5,0))} -> 542.0102 | H10: {=INDEX('Income Statement'!$DE$10:$EC$10,MATCH(Summary!H$6,'Income Statement'!$DE$5:$EC$5,0))} -> 663.71998 | I10: {=INDEX('Income Statement'!$DE$10:$EC$10,MATCH(Summary!I$6,'Income Statement'!$DE$5:$EC$5,0))} -> 670.09294 | J10: {=INDEX('Income Statement'!$DE$10:$EC$10,MATCH(Summary!J$6,'Income Statement'!$DE$5:$EC$5,0))} -> 681.56055 | K10: {=INDEX('Income Statement'!$DE$10:$EC$10,MATCH(Summary!K$6,'Income Statement'!$DE$5:$EC$5,0))} -> 682.754
B11: Total Revenue | C11: =INDEX('Income Statement'!$DE11:$EB11,MATCH(Summary!C$6,'Income Statement'!$DE$5:$EB$5,0)) -> 111.77163 | D11: {=INDEX('Income Statement'!$DE11:$EB11,MATCH(Summary!D$6,'Income Statement'!$DE$5:$EB$5,0))} -> 172.40566 | E11: {=INDEX('Income Statement'!$DE11:$EB11,MATCH(Summary!E$6,'Income Statement'!$DE$5:$EB$5,0))} -> 482.59377 | F11: {=INDEX('Income Statement'!$DE11:$EB11,MATCH(Summary!F$6,'Income Statement'!$DE$5:$EB$5,0))} -> 613.96 | G11: {=INDEX('Income Statement'!$DE11:$EB11,MATCH(Summary!G$6,'Income Statement'!$DE$5:$EB$5,0))} -> 1057.4442 | H11: {=INDEX('Income Statement'!$DE11:$EB11,MATCH(Summary!H$6,'Income Statement'!$DE$5:$EB$5,0))} -> 1293.5281 | I11: {=INDEX('Income Statement'!$DE11:$EB11,MATCH(Summary!I$6,'Income Statement'!$DE$5:$EB$5,0))} -> 1357.5616 | J11: {=INDEX('Income Statement'!$DE11:$EC11,MATCH(Summary!J$6,'Income Statement'!$DE$5:$EC$5,0))} -> 1409.0723 | K11: {=INDEX('Income Statement'!$DE11:$EC11,MATCH(Summary!K$6,'Income Statement'!$DE$5:$EC$5,0))} -> 1430.9989
B13: Operating Income
B14: Sand | C14: {=INDEX(Sand!$BF$22:$BP$22,MATCH(Summary!C$6,Sand!$BF$5:$BP$5,0))} -> 18.263283 | D14: {=INDEX(Sand!$BF$22:$BP$22,MATCH(Summary!D$6,Sand!$BF$5:$BP$5,0))} -> 71.900625 | E14: {=INDEX(Sand!$BF$22:$BP$22,MATCH(Summary!E$6,Sand!$BF$5:$BP$5,0))} -> 254.44963 | F14: {=INDEX(Sand!$BF$22:$BP$22,MATCH(Summary!F$6,Sand!$BF$5:$BP$5,0))} -> 295.2622 | G14: {=INDEX(Sand!$BF$22:$BP$22,MATCH(Summary!G$6,Sand!$BF$5:$BP$5,0))} -> 144.59576 | H14: {=INDEX(Sand!$BF$22:$BP$22,MATCH(Summary!H$6,Sand!$BF$5:$BP$5,0))} -> 238.41644 | I14: {=INDEX(Sand!$BF$22:$BP$22,MATCH(Summary!I$6,Sand!$BF$5:$BP$5,0))} -> 304.80678 | J14: {=INDEX(Sand!$BF$22:$BP$22,MATCH(Summary!J$6,Sand!$BF$5:$BP$5,0))} -> 344.60675 | K14: {=INDEX(Sand!$BF$22:$BP$22,MATCH(Summary!K$6,Sand!$BF$5:$BP$5,0))} -> 363.2038
B15: Logistics | C15: {=INDEX(Logistics!$BF$18:$BP$18,MATCH(Summary!C$6,Logistics!$BF$5:$BP$5,0))} -> 0.08921977 | D15: {=INDEX(Logistics!$BF$18:$BP$18,MATCH(Summary!D$6,Logistics!$BF$5:$BP$5,0))} -> 3.0858606 | E15: {=INDEX(Logistics!$BF$18:$BP$18,MATCH(Summary!E$6,Logistics!$BF$5:$BP$5,0))} -> 6.6616839 | F15: {=INDEX(Logistics!$BF$18:$BP$18,MATCH(Summary!F$6,Logistics!$BF$5:$BP$5,0))} -> 23.101957 | G15: {=INDEX(Logistics!$BF$18:$BP$18,MATCH(Summary!G$6,Logistics!$BF$5:$BP$5,0))} -> 83.290509 | H15: {=INDEX(Logistics!$BF$18:$BP$18,MATCH(Summary!H$6,Logistics!$BF$5:$BP$5,0))} -> 95.947124 | I15: {=INDEX(Logistics!$BF$18:$BP$18,MATCH(Summary!I$6,Logistics!$BF$5:$BP$5,0))} -> 95.684856 | J15: {=INDEX(Logistics!$BF$18:$BP$18,MATCH(Summary!J$6,Logistics!$BF$5:$BP$5,0))} -> 97.108254 | K15: {=INDEX(Logistics!$BF$18:$BP$18,MATCH(Summary!K$6,Logistics!$BF$5:$BP$5,0))} -> 97.246176
B16: Total Operating Income | C16: {=INDEX('Income Statement'!$DU31:$EC31,MATCH(Summary!C$6,'Income Statement'!$DU$5:$EC$5,0))} -> 1.3806168 | D16: {=INDEX('Income Statement'!$DU31:$EC31,MATCH(Summary!D$6,'Income Statement'!$DU$5:$EC$5,0))} -> 47.189592 | E16: {=INDEX('Income Statement'!$DU31:$EC31,MATCH(Summary!E$6,'Income Statement'!$DU$5:$EC$5,0))} -> 232.65733 | F16: {=INDEX('Income Statement'!$DU31:$EC31,MATCH(Summary!F$6,'Income Statement'!$DU$5:$EC$5,0))} -> 265.13 | G16: {=INDEX('Income Statement'!$DU31:$EC31,MATCH(Summary!G$6,'Income Statement'!$DU$5:$EC$5,0))} -> 116.10293 | H16: {=INDEX('Income Statement'!$DU31:$EC31,MATCH(Summary!H$6,'Income Statement'!$DU$5:$EC$5,0))} -> 229.56618 | I16: {=INDEX('Income Statement'!$DU31:$EC31,MATCH(Summary!I$6,'Income Statement'!$DU$5:$EC$5,0))} -> 295.69426 | J16: {=INDEX('Income Statement'!$DU31:$EC31,MATCH(Summary!J$6,'Income Statement'!$DU$5:$EC$5,0))} -> 336.91763 | K16: {=INDEX('Income Statement'!$DU31:$EC31,MATCH(Summary!K$6,'Income Statement'!$DU$5:$EC$5,0))} -> 355.65259
B18: Interest Expense | C18: {=INDEX('Income Statement'!$DU32:$EC32,MATCH(Summary!C$6,'Income Statement'!$DU$5:$EC$5,0))} -> -32.819165 | D18: {=INDEX('Income Statement'!$DU32:$EC32,MATCH(Summary!D$6,'Income Statement'!$DU$5:$EC$5,0))} -> -30.276282 | E18: {=INDEX('Income Statement'!$DU32:$EC32,MATCH(Summary!E$6,'Income Statement'!$DU$5:$EC$5,0))} -> -15.739831 | F18: {=INDEX('Income Statement'!$DU32:$EC32,MATCH(Summary!F$6,'Income Statement'!$DU$5:$EC$5,0))} -> -7.689 | G18: {=INDEX('Income Statement'!$DU32:$EC32,MATCH(Summary!G$6,'Income Statement'!$DU$5:$EC$5,0))} -> -37.822 | H18: {=INDEX('Income Statement'!$DU32:$EC32,MATCH(Summary!H$6,'Income Statement'!$DU$5:$EC$5,0))} -> -24.391786 | I18: {=INDEX('Income Statement'!$DU32:$EC32,MATCH(Summary!I$6,'Income Statement'!$DU$5:$EC$5,0))} -> -13.037606 | J18: {=INDEX('Income Statement'!$DU32:$EC32,MATCH(Summary!J$6,'Income Statement'!$DU$5:$EC$5,0))} -> -13.037606 | K18: {=INDEX('Income Statement'!$DU32:$EC32,MATCH(Summary!K$6,'Income Statement'!$DU$5:$EC$5,0))} -> -13.037606
B19: Other Income | C19: {=INDEX('Income Statement'!$DU33:$EC33,MATCH(Summary!C$6,'Income Statement'!$DU$5:$EC$5,0))} -> -3.8814379 | D19: {=INDEX('Income Statement'!$DU33:$EC33,MATCH(Summary!D$6,'Income Statement'!$DU$5:$EC$5,0))} -> 4.5908677 | E19: {=INDEX('Income Statement'!$DU33:$EC33,MATCH(Summary!E$6,'Income Statement'!$DU$5:$EC$5,0))} -> 0 | F19: {=INDEX('Income Statement'!$DU33:$EC33,MATCH(Summary!F$6,'Income Statement'!$DU$5:$EC$5,0))} -> 0.43 | G19: {=INDEX('Income Statement'!$DU33:$EC33,MATCH(Summary!G$6,'Income Statement'!$DU$5:$EC$5,0))} -> 0.45 | H19: {=INDEX('Income Statement'!$DU33:$EC33,MATCH(Summary!H$6,'Income Statement'!$DU$5:$EC$5,0))} -> 0 | I19: {=INDEX('Income Statement'!$DU33:$EC33,MATCH(Summary!I$6,'Income Statement'!$DU$5:$EC$5,0))} -> 0 | J19: {=INDEX('Income Statement'!$DU33:$EC33,MATCH(Summary!J$6,'Income Statement'!$DU$5:$EC$5,0))} -> 0 | K19: {=INDEX('Income Statement'!$DU33:$EC33,MATCH(Summary!K$6,'Income Statement'!$DU$5:$EC$5,0))} -> 0
B20: Pre-tax Income | C20: {=INDEX('Income Statement'!$DU34:$EC34,MATCH(Summary!C$6,'Income Statement'!$DU$5:$EC$5,0))} -> -35.319986 | D20: {=INDEX('Income Statement'!$DU34:$EC34,MATCH(Summary!D$6,'Income Statement'!$DU$5:$EC$5,0))} -> 21.504178 | E20: {=INDEX('Income Statement'!$DU34:$EC34,MATCH(Summary!E$6,'Income Statement'!$DU$5:$EC$5,0))} -> 216.9175 | F20: {=INDEX('Income Statement'!$DU34:$EC34,MATCH(Summary!F$6,'Income Statement'!$DU$5:$EC$5,0))} -> 257.871 | G20: {=INDEX('Income Statement'!$DU34:$EC34,MATCH(Summary!G$6,'Income Statement'!$DU$5:$EC$5,0))} -> 78.730925 | H20: {=INDEX('Income Statement'!$DU34:$EC34,MATCH(Summary!H$6,'Income Statement'!$DU$5:$EC$5,0))} -> 205.17439 | I20: {=INDEX('Income Statement'!$DU34:$EC34,MATCH(Summary!I$6,'Income Statement'!$DU$5:$EC$5,0))} -> 282.65665 | J20: {=INDEX('Income Statement'!$DU34:$EC34,MATCH(Summary!J$6,'Income Statement'!$DU$5:$EC$5,0))} -> 323.88002 | K20: {=INDEX('Income Statement'!$DU34:$EC34,MATCH(Summary!K$6,'Income Statement'!$DU$5:$EC$5,0))} -> 342.61499
B21: Taxes | C21: {=INDEX('Income Statement'!$DU36:$EC36,MATCH(Summary!C$6,'Income Statement'!$DU$5:$EC$5,0))} -> -0.3729235 | D21: {=INDEX('Income Statement'!$DU36:$EC36,MATCH(Summary!D$6,'Income Statement'!$DU$5:$EC$5,0))} -> -0.47040432 | E21: {=INDEX('Income Statement'!$DU36:$EC36,MATCH(Summary!E$6,'Income Statement'!$DU$5:$EC$5,0))} -> -2.0292631 | F21: {=INDEX('Income Statement'!$DU36:$EC36,MATCH(Summary!F$6,'Income Statement'!$DU$5:$EC$5,0))} -> -31.378 | G21: {=INDEX('Income Statement'!$DU36:$EC36,MATCH(Summary!G$6,'Income Statement'!$DU$5:$EC$5,0))} -> -15.770585 | H21: {=INDEX('Income Statement'!$DU36:$EC36,MATCH(Summary!H$6,'Income Statement'!$DU$5:$EC$5,0))} -> -43.086623 | I21: {=INDEX('Income Statement'!$DU36:$EC36,MATCH(Summary!I$6,'Income Statement'!$DU$5:$EC$5,0))} -> -59.357896 | J21: {=INDEX('Income Statement'!$DU36:$EC36,MATCH(Summary!J$6,'Income Statement'!$DU$5:$EC$5,0))} -> -68.014804 | K21: {=INDEX('Income Statement'!$DU36:$EC36,MATCH(Summary!K$6,'Income Statement'!$DU$5:$EC$5,0))} -> -71.949147
B22: Minority Interest | C22: {=INDEX('Income Statement'!$DU38:$EC38,MATCH(Summary!C$6,'Income Statement'!$DU$5:$EC$5,0))} -> 0 | D22: {=INDEX('Income Statement'!$DU38:$EC38,MATCH(Summary!D$6,'Income Statement'!$DU$5:$EC$5,0))} -> 0 | E22: {=INDEX('Income Statement'!$DU38:$EC38,MATCH(Summary!E$6,'Income Statement'!$DU$5:$EC$5,0))} -> 0 | F22: {=INDEX('Income Statement'!$DU38:$EC38,MATCH(Summary!F$6,'Income Statement'!$DU$5:$EC$5,0))} -> 0 | G22: {=INDEX('Income Statement'!$DU38:$EC38,MATCH(Summary!G$6,'Income Statement'!$DU$5:$EC$5,0))} -> 0 | H22: {=INDEX('Income Statement'!$DU38:$EC38,MATCH(Summary!H$6,'Income Statement'!$DU$5:$EC$5,0))} -> 0 | I22: {=INDEX('Income Statement'!$DU38:$EC38,MATCH(Summary!I$6,'Income Statement'!$DU$5:$EC$5,0))} -> 0 | J22: {=INDEX('Income Statement'!$DU38:$EC38,MATCH(Summary!J$6,'Income Statement'!$DU$5:$EC$5,0))} -> 0 | K22: {=INDEX('Income Statement'!$DU38:$EC38,MATCH(Summary!K$6,'Income Statement'!$DU$5:$EC$5,0))} -> 0
B23: Net Income | C23: {=INDEX('Income Statement'!$DU39:$EC39,MATCH(Summary!C$6,'Income Statement'!$DU$5:$EC$5,0))} -> -35.692909 | D23: {=INDEX('Income Statement'!$DU39:$EC39,MATCH(Summary!D$6,'Income Statement'!$DU$5:$EC$5,0))} -> 21.033774 | E23: {=INDEX('Income Statement'!$DU39:$EC39,MATCH(Summary!E$6,'Income Statement'!$DU$5:$EC$5,0))} -> 214.88823 | F23: {=INDEX('Income Statement'!$DU39:$EC39,MATCH(Summary!F$6,'Income Statement'!$DU$5:$EC$5,0))} -> 226.493 | G23: {=INDEX('Income Statement'!$DU39:$EC39,MATCH(Summary!G$6,'Income Statement'!$DU$5:$EC$5,0))} -> 62.96034 | H23: {=INDEX('Income Statement'!$DU39:$EC39,MATCH(Summary!H$6,'Income Statement'!$DU$5:$EC$5,0))} -> 162.08777 | I23: {=INDEX('Income Statement'!$DU39:$EC39,MATCH(Summary!I$6,'Income Statement'!$DU$5:$EC$5,0))} -> 223.29875 | J23: {=INDEX('Income Statement'!$DU39:$EC39,MATCH(Summary!J$6,'Income Statement'!$DU$5:$EC$5,0))} -> 255.86522 | K23: {=INDEX('Income Statement'!$DU39:$EC39,MATCH(Summary!K$6,'Income Statement'!$DU$5:$EC$5,0))} -> 270.66584
B25: Diluted Shares Outstanding | C25: {=INDEX('Income Statement'!$DE59:$EB59,MATCH(Summary!C$6,'Income Statement'!$DE$5:$EB$5,0))} -> 0 | D25: {=INDEX('Income Statement'!$DE59:$EB59,MATCH(Summary!D$6,'Income Statement'!$DE$5:$EB$5,0))} -> 0 | E25: {=INDEX('Income Statement'!$DE59:$EB59,MATCH(Summary!E$6,'Income Statement'!$DE$5:$EB$5,0))} -> 0 | F25: {=INDEX('Income Statement'!$DE59:$EB59,MATCH(Summary!F$6,'Income Statement'!$DE$5:$EB$5,0))} -> 100.242 | G25: {=INDEX('Income Statement'!$DE59:$EB59,MATCH(Summary!G$6,'Income Statement'!$DE$5:$EB$5,0))} -> 111.078 | H25: {=INDEX('Income Statement'!$DE59:$EB59,MATCH(Summary!H$6,'Income Statement'!$DE$5:$EB$5,0))} -> 111.078 | I25: {=INDEX('Income Statement'!$DE59:$EB59,MATCH(Summary!I$6,'Income Statement'!$DE$5:$EB$5,0))} -> 111.078 | J25: {=INDEX('Income Statement'!$DE59:$EC59,MATCH(Summary!J$6,'Income Statement'!$DE$5:$EC$5,0))} -> 111.078 | K25: {=INDEX('Income Statement'!$DE59:$EC59,MATCH(Summary!K$6,'Income Statement'!$DE$5:$EC$5,0))} -> 111.078
B26: Adjusted EPS | C26: {=INDEX('Income Statement'!$DE43:$EB43,MATCH(Summary!C$6,'Income Statement'!$DE$5:$EB$5,0))} -> #DIV/0! | D26: {=INDEX('Income Statement'!$DE43:$EB43,MATCH(Summary!D$6,'Income Statement'!$DE$5:$EB$5,0))} -> #DIV/0! | E26: {=INDEX('Income Statement'!$DE43:$EB43,MATCH(Summary!E$6,'Income Statement'!$DE$5:$EB$5,0))} -> #DIV/0! | F26: {=INDEX('Income Statement'!$DE43:$EB43,MATCH(Summary!F$6,'Income Statement'!$DE$5:$EB$5,0))} -> 2.2594621 | G26: {=INDEX('Income Statement'!$DE43:$EB43,MATCH(Summary!G$6,'Income Statement'!$DE$5:$EB$5,0))} -> 0.56681197 | H26: {=INDEX('Income Statement'!$DE43:$EB43,MATCH(Summary!H$6,'Income Statement'!$DE$5:$EB$5,0))} -> 1.4592248 | I26: {=INDEX('Income Statement'!$DE43:$EB43,MATCH(Summary!I$6,'Income Statement'!$DE$5:$EB$5,0))} -> 2.0102878 | J26: {=INDEX('Income Statement'!$DE43:$EC43,MATCH(Summary!J$6,'Income Statement'!$DE$5:$EC$5,0))} -> 2.3034734 | K26: {=INDEX('Income Statement'!$DE43:$EC43,MATCH(Summary!K$6,'Income Statement'!$DE$5:$EC$5,0))} -> 2.4367187
B28: Adjusted EBITDA
B29: Sand | C29: {=INDEX('Income Statement'!$DU81:$EC81,MATCH(Summary!C$6,'Income Statement'!$DU$5:$EC$5,0))} -> 0 | D29: {=INDEX('Income Statement'!$DU81:$EC81,MATCH(Summary!D$6,'Income Statement'!$DU$5:$EC$5,0))} -> 0 | E29: {=INDEX('Income Statement'!$DU81:$EC81,MATCH(Summary!E$6,'Income Statement'!$DU$5:$EC$5,0))} -> 0 | F29: {=INDEX('Income Statement'!$DU81:$EC81,MATCH(Summary!F$6,'Income Statement'!$DU$5:$EC$5,0))} -> 0 | G29: {=INDEX('Income Statement'!$DU81:$EC81,MATCH(Summary!G$6,'Income Statement'!$DU$5:$EC$5,0))} -> 0 | H29: {=INDEX('Income Statement'!$DU81:$EC81,MATCH(Summary!H$6,'Income Statement'!$DU$5:$EC$5,0))} -> 0 | I29: {=INDEX('Income Statement'!$DU81:$EC81,MATCH(Summary!I$6,'Income Statement'!$DU$5:$EC$5,0))} -> 0 | J29: {=INDEX('Income Statement'!$DU81:$EC81,MATCH(Summary!J$6,'Income Statement'!$DU$5:$EC$5,0))} -> 0 | K29: {=INDEX('Income Statement'!$DU81:$EC81,MATCH(Summary!K$6,'Income Statement'!$DU$5:$EC$5,0))} -> 0
B30: Logistics | C30: {=INDEX('Income Statement'!$DU82:$EC82,MATCH(Summary!C$6,'Income Statement'!$DU$5:$EC$5,0))} -> 0 | D30: {=INDEX('Income Statement'!$DU82:$EC82,MATCH(Summary!D$6,'Income Statement'!$DU$5:$EC$5,0))} -> 0 | E30: {=INDEX('Income Statement'!$DU82:$EC82,MATCH(Summary!E$6,'Income Statement'!$DU$5:$EC$5,0))} -> 0 | F30: {=INDEX('Income Statement'!$DU82:$EC82,MATCH(Summary!F$6,'Income Statement'!$DU$5:$EC$5,0))} -> 0 | G30: {=INDEX('Income Statement'!$DU82:$EC82,MATCH(Summary!G$6,'Income Statement'!$DU$5:$EC$5,0))} -> 0 | H30: {=INDEX('Income Statement'!$DU82:$EC82,MATCH(Summary!H$6,'Income Statement'!$DU$5:$EC$5,0))} -> 0 | I30: {=INDEX('Income Statement'!$DU82:$EC82,MATCH(Summary!I$6,'Income Statement'!$DU$5:$EC$5,0))} -> 0 | J30: {=INDEX('Income Statement'!$DU82:$EC82,MATCH(Summary!J$6,'Income Statement'!$DU$5:$EC$5,0))} -> 0 | K30: {=INDEX('Income Statement'!$DU82:$EC82,MATCH(Summary!K$6,'Income Statement'!$DU$5:$EC$5,0))} -> 0
B31: Total Adjusted EBITDA | C31: {=INDEX('Income Statement'!$DE45:$EB45,MATCH(Summary!C$6,'Income Statement'!$DE$5:$EB$5,0))} -> 22.897311 | D31: {=INDEX('Income Statement'!$DE45:$EB45,MATCH(Summary!D$6,'Income Statement'!$DE$5:$EB$5,0))} -> 71.730486 | E31: {=INDEX('Income Statement'!$DE45:$EB45,MATCH(Summary!E$6,'Income Statement'!$DE$5:$EB$5,0))} -> 261.11132 | F31: {=INDEX('Income Statement'!$DE45:$EB45,MATCH(Summary!F$6,'Income Statement'!$DE$5:$EB$5,0))} -> 304.928 | G31: {=INDEX('Income Statement'!$DE45:$EB45,MATCH(Summary!G$6,'Income Statement'!$DE$5:$EB$5,0))} -> 227.75727 | H31: {=INDEX('Income Statement'!$DE45:$EB45,MATCH(Summary!H$6,'Income Statement'!$DE$5:$EB$5,0))} -> 334.36356 | I31: {=INDEX('Income Statement'!$DE45:$EB45,MATCH(Summary!I$6,'Income Statement'!$DE$5:$EB$5,0))} -> 400.49164 | J31: {=INDEX('Income Statement'!$DE45:$EB45,MATCH(Summary!J$6,'Income Statement'!$DE$5:$EB$5,0))} -> 441.71501 | K31: {=INDEX('Income Statement'!$DE45:$EC45,MATCH(Summary!K$6,'Income Statement'!$DE$5:$EC$5,0))} -> 460.44997
B32: Check
B34: Adjusted EBITDA Margin
B35: Sand | C35: =C29/C9 -> 0 | D35: =D29/D9 -> 0 | E35: =E29/E9 -> 0 | F35: =F29/F9 -> 0 | G35: =G29/G9 -> 0 | H35: =H29/H9 -> 0 | I35: =I29/I9 -> 0 | J35: =J29/J9 -> 0 | K35: =K29/K9 -> 0
B36: Logistics | C36: =C30/C10 -> 0 | D36: =D30/D10 -> 0 | E36: =E30/E10 -> 0 | F36: =F30/F10 -> 0 | G36: =G30/G10 -> 0 | H36: =H30/H10 -> 0 | I36: =I30/I10 -> 0 | J36: =J30/J10 -> 0 | K36: =K30/K10 -> 0
B37: Total Adjusted EBITDA Margin | C37: =C31/C11 -> 0.20485799 | D37: =D31/D11 -> 0.41605644 | E37: =E31/E11 -> 0.5410582 | F37: =F31/F11 -> 0.49665776 | G37: =G31/G11 -> 0.21538467 | H37: =H31/H11 -> 0.25848961 | I37: =I31/I11 -> 0.29500808 | J37: =J31/J11 -> 0.31347931 | K37: =K31/K11 -> 0.32176823
B39: Free Cash Flow | C39: {=INDEX('Cash Flow'!$DE58:$EB58,MATCH(Summary!C$6,'Cash Flow'!$DE$5:$EB$5,0))} -> 2.954 | D39: {=INDEX('Cash Flow'!$DE58:$EB58,MATCH(Summary!D$6,'Cash Flow'!$DE$5:$EB$5,0))} -> 24.074616 | E39: {=INDEX('Cash Flow'!$DE58:$EB58,MATCH(Summary!E$6,'Cash Flow'!$DE$5:$EB$5,0))} -> 116.24989 | F39: {=INDEX('Cash Flow'!$DE58:$EB58,MATCH(Summary!F$6,'Cash Flow'!$DE$5:$EB$5,0))} -> -66.455 | G39: {=INDEX('Cash Flow'!$DE58:$EB58,MATCH(Summary!G$6,'Cash Flow'!$DE$5:$EB$5,0))} -> -103.57034 | H39: {=INDEX('Cash Flow'!$DE58:$EB58,MATCH(Summary!H$6,'Cash Flow'!$DE$5:$EB$5,0))} -> 248.46755 | I39: {=INDEX('Cash Flow'!$DE58:$EB58,MATCH(Summary!I$6,'Cash Flow'!$DE$5:$EB$5,0))} -> 317.11052 | J39: {=INDEX('Cash Flow'!$DE58:$EB58,MATCH(Summary!J$6,'Cash Flow'!$DE$5:$EB$5,0))} -> 351.14786 | K39: {=INDEX('Cash Flow'!$DE58:$EC58,MATCH(Summary!K$6,'Cash Flow'!$DE$5:$EC$5,0))} -> -154.56676
B40: FCF/EBITDA conversion | C40: =C39/C31 -> 0.12901078 | D40: =D39/D31 -> 0.33562599 | E40: =E39/E31 -> 0.44521201 | F40: =F39/F31 -> -0.21793669 | G40: =G39/G31 -> -0.45474 | H40: =H39/H31 -> 0.74310595 | I40: =I39/I31 -> 0.79180311 | J40: =J39/J31 -> 0.79496474 | K40: =K39/K31 -> -0.33568632
B41: FCF/Revenue Conversion | C41: =C39/C11 -> 0.026428889 | D41: =D39/D11 -> 0.13963936 | E41: =E39/E11 -> 0.24088561 | F41: =F39/F11 -> -0.10823995 | G41: =G39/G11 -> -0.097944024 | H41: =H39/H11 -> 0.19208517 | I41: =I39/I11 -> 0.23358832 | J41: =J39/J11 -> 0.249205 | K41: =K39/K11 -> -0.10801319
B43: Net Debt | C43: {=INDEX('Balance Sheet'!$DE$57:$EB$57,MATCH(Summary!C$6,'Balance Sheet'!$DE$5:$EB$5,0))} -> 137.03977 | D43: {=INDEX('Balance Sheet'!$DE$57:$EB$57,MATCH(Summary!D$6,'Balance Sheet'!$DE$5:$EB$5,0))} -> 137.13801 | E43: {=INDEX('Balance Sheet'!$DE$57:$EB$57,MATCH(Summary!E$6,'Balance Sheet'!$DE$5:$EB$5,0))} -> 65.163794 | F43: {=INDEX('Balance Sheet'!$DE$57:$EB$57,MATCH(Summary!F$6,'Balance Sheet'!$DE$5:$EB$5,0))} -> -37.354 | G43: {=INDEX('Balance Sheet'!$DE$57:$EB$57,MATCH(Summary!G$6,'Balance Sheet'!$DE$5:$EB$5,0))} -> 414.90906 | H43: {=INDEX('Balance Sheet'!$DE$57:$EB$57,MATCH(Summary!H$6,'Balance Sheet'!$DE$5:$EB$5,0))} -> 278.40813 | I43: {=INDEX('Balance Sheet'!$DE$57:$EB$57,MATCH(Summary!I$6,'Balance Sheet'!$DE$5:$EB$5,0))} -> 78.862564 | J43: {=INDEX('Balance Sheet'!$DE$57:$EB$57,MATCH(Summary!J$6,'Balance Sheet'!$DE$5:$EB$5,0))} -> -148.84209 | K43: {=INDEX('Balance Sheet'!$DE$57:$EC$57,MATCH(Summary!K$6,'Balance Sheet'!$DE$5:$EC$5,0))} -> 135.34003
B44: Net Debt/EBITDA | C44: =C43/C31 -> 5.9849724 | D44: =D43/D31 -> 1.9118511 | E44: =E43/E31 -> 0.24956327 | F44: =F43/F31 -> -0.12250105 | G44: =G43/G31 -> 1.821716 | H44: =H43/H31 -> 0.83265094 | I44: =I43/I31 -> 0.19691438 | J44: =J43/J31 -> -0.33696408 | K44: =K43/K31 -> 0.29392994
B46: Total assets | C46: {=INDEX('Balance Sheet'!$25:$25,MATCH(Summary!C$6,'Balance Sheet'!$7:$7,0))} -> 521.74237 | D46: {=INDEX('Balance Sheet'!$25:$25,MATCH(Summary!D$6,'Balance Sheet'!$7:$7,0))} -> 543.75479 | E46: {=INDEX('Balance Sheet'!$25:$25,MATCH(Summary!E$6,'Balance Sheet'!$7:$7,0))} -> 750.99959 | F46: {=INDEX('Balance Sheet'!$25:$25,MATCH(Summary!F$6,'Balance Sheet'!$7:$7,0))} -> 1261.686 | G46: {=INDEX('Balance Sheet'!$25:$25,MATCH(Summary!G$6,'Balance Sheet'!$7:$7,0))} -> 1955.2133 | H46: {=INDEX('Balance Sheet'!$25:$25,MATCH(Summary!H$6,'Balance Sheet'!$7:$7,0))} -> 2122.2441 | I46: {=INDEX('Balance Sheet'!$25:$25,MATCH(Summary!I$6,'Balance Sheet'!$7:$7,0))} -> 2348.4629 | J46: {=INDEX('Balance Sheet'!$25:$25,MATCH(Summary!J$6,'Balance Sheet'!$7:$7,0))} -> 2528.2005 | K46: {=INDEX('Balance Sheet'!$25:$25,MATCH(Summary!K$6,'Balance Sheet'!$7:$7,0))} -> 2142.5371
B47: Current liabilities | C47: {=INDEX('Balance Sheet'!$34:$34,MATCH(Summary!C$6,'Balance Sheet'!$7:$7,0))} -> 10.952645 | D47: {=INDEX('Balance Sheet'!$34:$34,MATCH(Summary!D$6,'Balance Sheet'!$7:$7,0))} -> 23.547045 | E47: {=INDEX('Balance Sheet'!$34:$34,MATCH(Summary!E$6,'Balance Sheet'!$7:$7,0))} -> 68.284107 | F47: {=INDEX('Balance Sheet'!$34:$34,MATCH(Summary!F$6,'Balance Sheet'!$7:$7,0))} -> 92.592 | G47: {=INDEX('Balance Sheet'!$34:$34,MATCH(Summary!G$6,'Balance Sheet'!$7:$7,0))} -> 250.84664 | H47: {=INDEX('Balance Sheet'!$34:$34,MATCH(Summary!H$6,'Balance Sheet'!$7:$7,0))} -> 374.60037 | I47: {=INDEX('Balance Sheet'!$34:$34,MATCH(Summary!I$6,'Balance Sheet'!$7:$7,0))} -> 501.92933 | J47: {=INDEX('Balance Sheet'!$34:$34,MATCH(Summary!J$6,'Balance Sheet'!$7:$7,0))} -> 556.08893 | K47: {=INDEX('Balance Sheet'!$34:$34,MATCH(Summary!K$6,'Balance Sheet'!$7:$7,0))} -> 36.219
B48: ROCE | C48: =C16/(C46-C47) -> 0.0027029063 | D48: =D16/(D46-D47) -> 0.090712975 | E48: =E16/(E46-E47) -> 0.34078226 | F48: =F16/(F46-F47) -> 0.22678245 | G48: =G16/(G46-G47) -> 0.068120863 | H48: =H16/(H46-H47) -> 0.13135754 | I48: =I16/(I46-I47) -> 0.16013478 | J48: =J16/(J46-J47) -> 0.17084106 | K48: =K16/(K46-K47) -> 0.16885037
B49: Total debt | C49: {=INDEX('Balance Sheet'!$37:$37,MATCH(Summary!C$6,'Balance Sheet'!$7:$7,0))} -> 173.11224 | D49: {=INDEX('Balance Sheet'!$37:$37,MATCH(Summary!D$6,'Balance Sheet'!$7:$7,0))} -> 177.53899 | E49: {=INDEX('Balance Sheet'!$37:$37,MATCH(Summary!E$6,'Balance Sheet'!$7:$7,0))} -> 147.17383 | F49: {=INDEX('Balance Sheet'!$37:$37,MATCH(Summary!F$6,'Balance Sheet'!$7:$7,0))} -> 172.82 | G49: {=INDEX('Balance Sheet'!$37:$37,MATCH(Summary!G$6,'Balance Sheet'!$7:$7,0))} -> 431.043 | H49: =+Valuation!D12 -> 22 | I49: {=INDEX('Balance Sheet'!$37:$37,MATCH(Summary!I$6,'Balance Sheet'!$7:$7,0))} -> 367.043 | J49: {=INDEX('Balance Sheet'!$37:$37,MATCH(Summary!J$6,'Balance Sheet'!$7:$7,0))} -> 335.043 | K49: {=INDEX('Balance Sheet'!$37:$37,MATCH(Summary!K$6,'Balance Sheet'!$7:$7,0))} -> 303.043
B50: Equity | C50: {=INDEX('Balance Sheet'!$49:$49,MATCH(Summary!C$6,'Balance Sheet'!$7:$7,0))} -> 331.69405 | D50: {=INDEX('Balance Sheet'!$49:$49,MATCH(Summary!D$6,'Balance Sheet'!$7:$7,0))} -> 339.36464 | E50: {=INDEX('Balance Sheet'!$49:$49,MATCH(Summary!E$6,'Balance Sheet'!$7:$7,0))} -> 511.15966 | F50: {=INDEX('Balance Sheet'!$49:$49,MATCH(Summary!F$6,'Balance Sheet'!$7:$7,0))} -> 867.824 | G50: {=INDEX('Balance Sheet'!$49:$49,MATCH(Summary!G$6,'Balance Sheet'!$7:$7,0))} -> 1043.2296 | H50: {=INDEX('Balance Sheet'!$49:$49,MATCH(Summary!H$6,'Balance Sheet'!$7:$7,0))} -> 1118.5068 | I50: {=INDEX('Balance Sheet'!$49:$49,MATCH(Summary!I$6,'Balance Sheet'!$7:$7,0))} -> 1249.3966 | J50: {=INDEX('Balance Sheet'!$49:$49,MATCH(Summary!J$6,'Balance Sheet'!$7:$7,0))} -> 1406.9746 | K50: {=INDEX('Balance Sheet'!$49:$49,MATCH(Summary!K$6,'Balance Sheet'!$7:$7,0))} -> 1573.1811
B51: Tax rate | C51: {=INDEX('Income Statement'!$37:$37,MATCH(Summary!C$6,'Income Statement'!$7:$7,0))} -> -0.010558427 | D51: {=INDEX('Income Statement'!$37:$37,MATCH(Summary!D$6,'Income Statement'!$7:$7,0))} -> 0.02187502 | E51: {=INDEX('Income Statement'!$37:$37,MATCH(Summary!E$6,'Income Statement'!$7:$7,0))} -> 0.0093549995 | F51: {=INDEX('Income Statement'!$37:$37,MATCH(Summary!F$6,'Income Statement'!$7:$7,0))} -> 0.121681 | G51: {=INDEX('Income Statement'!$37:$37,MATCH(Summary!G$6,'Income Statement'!$7:$7,0))} -> 0.20030992 | H51: {=INDEX('Income Statement'!$37:$37,MATCH(Summary!H$6,'Income Statement'!$7:$7,0))} -> 0.21 | I51: {=INDEX('Income Statement'!$37:$37,MATCH(Summary!I$6,'Income Statement'!$7:$7,0))} -> 0.21 | J51: {=INDEX('Income Statement'!$37:$37,MATCH(Summary!J$6,'Income Statement'!$7:$7,0))} -> 0.21 | K51: {=INDEX('Income Statement'!$37:$37,MATCH(Summary!K$6,'Income Statement'!$7:$7,0))} -> 0.21
B52: ROIC | C52: =C16*(1-C51)/(C49+C50) -> 0.0027638204 | D52: =D16*(1-D51)/(D49+D50) -> 0.089295792 | E52: =E16*(1-E51)/(E49+E50) -> 0.35009736 | F52: =F16*(1-F51)/(F49+F50) -> 0.22377366 | G52: =G16*(1-G51)/(G49+G50) -> 0.06297774 | H52: =H16*(1-H51)/(H49+H50) -> 0.15901465 | I52: =I16*(1-I51)/(I49+I50) -> 0.14451419 | J52: =J16*(1-J51)/(J49+J50) -> 0.15279118 | K52: =K16*(1-K51)/(K49+K50) -> 0.14975053
B54: Atlas Energy Solutions Revenue | X54: Terminal Growth Input
C55: 2022 | D55: =C55+1 -> 2023 | E55: =D55+1 -> 2024 | F55: =E55+1 -> 2025 | G55: =F55+1 -> 2026 | H55: =G55+1 -> 2027 | I55: =H55+1 -> 2028 | J55: =I55+1 -> 2029 | K55: =J55+1 -> 2030 | ... V55: =U55+1 -> 2041
B56: Digital and Integration | C56: {=INDEX('Income Statement'!$DE$9:$EB$9,MATCH(Summary!C$55,'Income Statement'!$DE$5:$EB$5,0))} -> 408.32798 | D56: {=INDEX('Income Statement'!$DE$9:$EB$9,MATCH(Summary!D$55,'Income Statement'!$DE$5:$EB$5,0))} -> 468.119 | E56: {=INDEX('Income Statement'!$DE$9:$EB$9,MATCH(Summary!E$55,'Income Statement'!$DE$5:$EB$5,0))} -> 515.434 | F56: {=INDEX('Income Statement'!$DE$9:$EB$9,MATCH(Summary!F$55,'Income Statement'!$DE$5:$EB$5,0))} -> 629.80808 | G56: {=INDEX('Income Statement'!$DE$9:$EB$9,MATCH(Summary!G$55,'Income Statement'!$DE$5:$EB$5,0))} -> 687.46864 | H56: {=INDEX('Income Statement'!$DE$9:$EB$9,MATCH(Summary!H$55,'Income Statement'!$DE$5:$EB$5,0))} -> 727.51171 | I56: {=INDEX('Income Statement'!$DE$9:$EC$9,MATCH(Summary!I$55,'Income Statement'!$DE$5:$EC$5,0))} -> 748.24488 | J56: =I56*(1+$X56) -> 751.9861 | K56: =J56*(1+$X56) -> 755.74603 | L56: =K56*(1+$X56) -> 759.52476 | M56: =L56*(1+$X56) -> 763.32238 | N56: =M56*(1+$X56) -> 767.139 | O56: =N56*(1+$X56) -> 770.97469 | P56: =O56*(1+$X56) -> 774.82956 | Q56: =P56*(1+$X56) -> 778.70371 | ... V56: =U56*(1+$X56) -> 798.36696 | X56: 0.005
B57: Reservoir Performance | C57: {=INDEX('Income Statement'!$DE$10:$EB$10,MATCH(Summary!C$55,'Income Statement'!$DE$5:$EB$5,0))} -> 74.265797 | D57: {=INDEX('Income Statement'!$DE$10:$EB$10,MATCH(Summary!D$55,'Income Statement'!$DE$5:$EB$5,0))} -> 145.841 | E57: {=INDEX('Income Statement'!$DE$10:$EB$10,MATCH(Summary!E$55,'Income Statement'!$DE$5:$EB$5,0))} -> 542.0102 | F57: {=INDEX('Income Statement'!$DE$10:$EB$10,MATCH(Summary!F$55,'Income Statement'!$DE$5:$EB$5,0))} -> 663.71998 | G57: {=INDEX('Income Statement'!$DE$10:$EB$10,MATCH(Summary!G$55,'Income Statement'!$DE$5:$EB$5,0))} -> 670.09294 | H57: {=INDEX('Income Statement'!$DE$10:$EB$10,MATCH(Summary!H$55,'Income Statement'!$DE$5:$EB$5,0))} -> 681.56055 | I57: {=INDEX('Income Statement'!$DE$10:$EC$10,MATCH(Summary!I$55,'Income Statement'!$DE$5:$EC$5,0))} -> 682.754 | J57: =I57*(1+$X57) -> 686.16777 | K57: =J57*(1+$X57) -> 689.5986 | L57: =K57*(1+$X57) -> 693.0466 | M57: =L57*(1+$X57) -> 696.51183 | N57: =M57*(1+$X57) -> 699.99439 | O57: =N57*(1+$X57) -> 703.49436 | P57: =O57*(1+$X57) -> 707.01183 | Q57: =P57*(1+$X57) -> 710.54689 | ... V57: =U57*(1+$X57) -> 728.48909 | X57: 0.005
B58: Total Revenue | C58: =SUM(C56:C57) -> 482.59377 | D58: =SUM(D56:D57) -> 613.96 | E58: =SUM(E56:E57) -> 1057.4442 | F58: =SUM(F56:F57) -> 1293.5281 | G58: =SUM(G56:G57) -> 1357.5616 | H58: =SUM(H56:H57) -> 1409.0723 | I58: =SUM(I56:I57) -> 1430.9989 | J58: =SUM(J56:J57) -> 1438.1539 | ... V58: =SUM(V56:V57) -> 1526.856
B60: EBITDA Margin | C60: =C62/C58 -> 0.5410582 | D60: =D62/D58 -> 0.49665776 | E60: =E62/E58 -> 0.21538467 | F60: =F62/F58 -> 0.25848961 | G60: =G62/G58 -> 0.29500808 | H60: =G60*(1+$X60) -> 0.29648312 | I60: =H60*(1+$X60) -> 0.29796554 | J60: =I60*(1+$X60) -> 0.29945536 | K60: =J60*(1+$X60) -> 0.30095264 | L60: =K60*(1+$X60) -> 0.30245741 | M60: =L60*(1+$X60) -> 0.30396969 | N60: =M60*(1+$X60) -> 0.30548954 | O60: =N60*(1+$X60) -> 0.30701699 | ... V60: =U60*(1+$X60) -> 0.31792512 | X60: 0.005
B62: EBITDA | C62: {=INDEX('Income Statement'!$DE$45:$EB$45,MATCH(Summary!C$55,'Income Statement'!$DE$5:$EB$5,0))} -> 261.11132 | D62: {=INDEX('Income Statement'!$DE$45:$EB$45,MATCH(Summary!D$55,'Income Statement'!$DE$5:$EB$5,0))} -> 304.928 | E62: {=INDEX('Income Statement'!$DE$45:$EB$45,MATCH(Summary!E$55,'Income Statement'!$DE$5:$EB$5,0))} -> 227.75727 | F62: {=INDEX('Income Statement'!$DE$45:$EB$45,MATCH(Summary!F$55,'Income Statement'!$DE$5:$EB$5,0))} -> 334.36356 | G62: {=INDEX('Income Statement'!$DE$45:$EB$45,MATCH(Summary!G$55,'Income Statement'!$DE$5:$EB$5,0))} -> 400.49164 | H62: =H58*H60 -> 417.76614 | I62: =I58*I60 -> 426.38835 | J62: =J58*J60 -> 430.66289 | K62: =K58*K60 -> 434.98029 | L62: =L58*L60 -> 439.34096 | M62: =M58*M60 -> 443.74536 | N62: =N58*N60 -> 448.1939 | O62: =O58*O60 -> 452.68705 | ... V62: =V58*V60 -> 485.42589
B63: Interest | C63: {=INDEX('Income Statement'!$DE$32:$EB$32,MATCH(Summary!C$55,'Income Statement'!$DE$5:$EB$5,0))+INDEX('Income Statement'!$DE$32:$EB$32,MATCH(Summary!C$55,'Income Statement'!$DE$5:$EB$5,0))} -> -31.479661 | D63: {=INDEX('Income Statement'!$DE$32:$EB$32,MATCH(Summary!D$55,'Income Statement'!$DE$5:$EB$5,0))+INDEX('Income Statement'!$DE$32:$EB$32,MATCH(Summary!D$55,'Income Statement'!$DE$5:$EB$5,0))} -> -15.378 | E63: {=INDEX('Income Statement'!$DE$32:$EB$32,MATCH(Summary!E$55,'Income Statement'!$DE$5:$EB$5,0))+INDEX('Income Statement'!$DE$32:$EB$32,MATCH(Summary!E$55,'Income Statement'!$DE$5:$EB$5,0))} -> -75.644 | F63: {=INDEX('Income Statement'!$DE$32:$EB$32,MATCH(Summary!F$55,'Income Statement'!$DE$5:$EB$5,0))+INDEX('Income Statement'!$DE$32:$EB$32,MATCH(Summary!F$55,'Income Statement'!$DE$5:$EB$5,0))} -> -48.783571 | G63: {=INDEX('Income Statement'!$DE$32:$EB$32,MATCH(Summary!G$55,'Income Statement'!$DE$5:$EB$5,0))+INDEX('Income Statement'!$DE$32:$EB$32,MATCH(Summary!G$55,'Income Statement'!$DE$5:$EB$5,0))} -> -26.075213 | H63: =G63*(1+$X63) -> -26.335965 | I63: =H63*(1+$X63) -> -26.599325 | J63: =I63*(1+$X63) -> -26.865318 | K63: =J63*(1+$X63) -> -27.133971 | L63: =K63*(1+$X63) -> -27.405311 | M63: =L63*(1+$X63) -> -27.679364 | N63: =M63*(1+$X63) -> -27.956157 | O63: =N63*(1+$X63) -> -28.235719 | ... V63: =U63*(1+$X63) -> -30.272513 | X63: 0.01
B64: Taxes | C64: {=INDEX('Income Statement'!$DE$36:$EB$36,MATCH(Summary!C$55,'Income Statement'!$DE$5:$EB$5,0))} -> -2.0292631 | D64: {=INDEX('Income Statement'!$DE$36:$EB$36,MATCH(Summary!D$55,'Income Statement'!$DE$5:$EB$5,0))} -> -31.378 | E64: {=INDEX('Income Statement'!$DE$36:$EB$36,MATCH(Summary!E$55,'Income Statement'!$DE$5:$EB$5,0))} -> -15.770585 | F64: {=INDEX('Income Statement'!$DE$36:$EB$36,MATCH(Summary!F$55,'Income Statement'!$DE$5:$EB$5,0))} -> -43.086623 | G64: {=INDEX('Income Statement'!$DE$36:$EB$36,MATCH(Summary!G$55,'Income Statement'!$DE$5:$EB$5,0))} -> -59.357896 | H64: =G64*(1+$X64) -> -59.951475 | I64: =H64*(1+$X64) -> -60.55099 | J64: =I64*(1+$X64) -> -61.1565 | K64: =J64*(1+$X64) -> -61.768065 | L64: =K64*(1+$X64) -> -62.385746 | M64: =L64*(1+$X64) -> -63.009603 | N64: =M64*(1+$X64) -> -63.639699 | O64: =N64*(1+$X64) -> -64.276096 | ... V64: =U64*(1+$X64) -> -68.912675 | X64: 0.01
B65: Working Capital | C65: {=INDEX('Cash Flow'!$DE$24:$EB$24,MATCH(Summary!C$55,'Cash Flow'!$DE$5:$EB$5,0))} -> -43.568843 | D65: {=INDEX('Cash Flow'!$DE$24:$EB$24,MATCH(Summary!D$55,'Cash Flow'!$DE$5:$EB$5,0))} -> -6.947 | E65: {=INDEX('Cash Flow'!$DE$24:$EB$24,MATCH(Summary!E$55,'Cash Flow'!$DE$5:$EB$5,0))} -> 41.412224 | F65: {=INDEX('Cash Flow'!$DE$24:$EB$24,MATCH(Summary!F$55,'Cash Flow'!$DE$5:$EB$5,0))} -> 149.63398 | G65: {=INDEX('Cash Flow'!$DE$24:$EB$24,MATCH(Summary!G$55,'Cash Flow'!$DE$5:$EB$5,0))} -> 60.720214 | H65: =G65*(1+$X65) -> 61.327416 | I65: =H65*(1+$X65) -> 61.94069 | J65: =I65*(1+$X65) -> 62.560097 | K65: =J65*(1+$X65) -> 63.185698 | L65: =K65*(1+$X65) -> 63.817555 | M65: =L65*(1+$X65) -> 64.45573 | N65: =M65*(1+$X65) -> 65.100288 | O65: =N65*(1+$X65) -> 65.75129 | ... V65: =U65*(1+$X65) -> 70.494283 | X65: 0.01
B66: Other | C66: =C67-SUM(C62:C65) -> 21.808313 | D66: =D67-SUM(D62:D65) -> 47.806 | E66: =E67-SUM(E62:E65) -> 75.808 | F66: =F67-SUM(F62:F65) -> 49.547786 | G66: =G67-SUM(G62:G65) -> 38.193606 | H66: =G66*(1+$X66) -> 38.575542 | I66: =H66*(1+$X66) -> 38.961298 | J66: =I66*(1+$X66) -> 39.350911 | K66: =J66*(1+$X66) -> 39.74442 | L66: =K66*(1+$X66) -> 40.141864 | M66: =L66*(1+$X66) -> 40.543283 | N66: =M66*(1+$X66) -> 40.948716 | O66: =N66*(1+$X66) -> 41.358203 | ... V66: =U66*(1+$X66) -> 44.341591 | X66: 0.01
B67: CFO | C67: {=INDEX('Cash Flow'!$DE$25:$EB$25,MATCH(Summary!C$55,'Cash Flow'!$DE$5:$EB$5,0))} -> 205.84186 | D67: {=INDEX('Cash Flow'!$DE$25:$EB$25,MATCH(Summary!D$55,'Cash Flow'!$DE$5:$EB$5,0))} -> 299.031 | E67: {=INDEX('Cash Flow'!$DE$25:$EB$25,MATCH(Summary!E$55,'Cash Flow'!$DE$5:$EB$5,0))} -> 253.56291 | F67: {=INDEX('Cash Flow'!$DE$25:$EB$25,MATCH(Summary!F$55,'Cash Flow'!$DE$5:$EB$5,0))} -> 441.67513 | G67: {=INDEX('Cash Flow'!$DE$25:$EB$25,MATCH(Summary!G$55,'Cash Flow'!$DE$5:$EB$5,0))} -> 413.97235 | H67: =SUM(H62:H66) -> 431.38166 | I67: =SUM(I62:I66) -> 440.14002 | J67: =SUM(J62:J66) -> 444.55208 | K67: =SUM(K62:K66) -> 449.00837 | L67: =SUM(L62:L66) -> 453.50933 | M67: =SUM(M62:M66) -> 458.0554 | N67: =SUM(N62:N66) -> 462.64705 | O67: =SUM(O62:O66) -> 467.28473 | ... V67: =SUM(V62:V66) -> 501.07657
B69: Capital Spending | C69: =+SUMIF('Cash Flow'!$DU$5:$EC$5,Summary!C55,'Cash Flow'!$DU$28:$EC$28) -> -89.591968 | D69: =+SUMIF('Cash Flow'!$DU$5:$EC$5,Summary!D55,'Cash Flow'!$DU$28:$EC$28) -> -365.486 | E69: =+SUMIF('Cash Flow'!$DU$5:$EC$5,Summary!E55,'Cash Flow'!$DU$28:$EC$28) -> -357.13325 | F69: =+SUMIF('Cash Flow'!$DU$5:$EC$5,Summary!F55,'Cash Flow'!$DU$28:$EC$28) -> -193.20758 | G69: =+SUMIF('Cash Flow'!$DU$5:$EC$5,Summary!G55,'Cash Flow'!$DU$28:$EC$28) -> -96.861822 | H69: =+SUMIF('Cash Flow'!$DU$5:$EC$5,Summary!H55,'Cash Flow'!$DU$28:$EC$28) -> -75.975 | I69: =+SUMIF('Cash Flow'!$DU$5:$EC$5,Summary!I55,'Cash Flow'!$DU$28:$EC$28) -> -75.975 | J69: =+SUMIF('Cash Flow'!$DU$5:$EC$5,Summary!J55,'Cash Flow'!$DU$28:$EC$28) -> 0 | ... V69: =+SUMIF('Cash Flow'!$DU$5:$EC$5,Summary!V55,'Cash Flow'!$DU$28:$EC$28) -> 0 | X69: 0.07
B71: Free Cash Flow | C71: =C67+C69 -> 116.24989 | D71: =D67+D69 -> -66.455 | E71: =E67+E69 -> -103.57034 | F71: =F67+F69 -> 248.46755 | G71: =G67+G69 -> 317.11052 | H71: =H67+H69 -> 355.40666 | I71: =I67+I69 -> 364.16502 | J71: =J67+J69 -> 444.55208 | ... V71: =V67+V69 -> 501.07657
B73: FCF/Revenue Conversion | C73: =C71/C58 -> 0.24088561 | D73: =D71/D58 -> -0.10823995 | E73: =E71/E58 -> -0.097944024 | F73: =F71/F58 -> 0.19208517 | G73: =G71/G58 -> 0.23358832 | H73: =H71/H58 -> 0.25222742 | I73: =I71/I58 -> 0.25448309 | J73: =J71/J58 -> 0.30911302 | ... V73: =V71/V58 -> 0.32817539 | X73: =AVERAGE(C71:V71)/AVERAGE(C58:V58) -> 0.27389715
B75: CAPM | C75: 0.07
B76: Risk Free Rate | C76: 0.02 | D76: *MAJOR BANK 2022 forecast
B77: Beta | C77: 0.99 | D77: *FactSet unlevered beta
B78: Market Risk Premium | C78: 0.046 | D78: *Kostin Nov 16, 2021 for 2022 outlook
B79: Capm based COE | C79: =C76+(C77*C78) -> 0.06554
B80: NPV Equity | C80: {=+NPV(C75,D71:V71)} -> 3394.0045
B81: Share Count | C81: {=INDEX('Income Statement'!$DE$59:$EB$59,MATCH(Summary!D$55,'Income Statement'!$DE$5:$EB$5,0))} -> 100.242
B82: Price Target | C82: =C80/C81 -> 33.858109
B84: Net Debt | C84: {=INDEX('Balance Sheet'!$DE$57:$EB$57,MATCH(Summary!C$55,'Balance Sheet'!$DE$5:$EB$5,0))} -> 65.163794
B85: Minority Interest | C85: {=INDEX('Balance Sheet'!$DE$47:$EB$47,MATCH(Summary!C$55,'Balance Sheet'!$DE$5:$EB$5,0))} -> 0
B86: EV | C86: =SUM(C80,C84:C85) -> 3459.1683
B87: Terminal value as % of EV | C87: {=(+NPV(C75,C71:U71)-+NPV(C75,C71:H71))/C86} -> 0.73213991
X88: Average
B89: DCF Implied FCF Yield | C89: =C71/$C$80 -> 0.034251544 | D89: =D71/$C$80 -> -0.019580115 | E89: =E71/$C$80 -> -0.030515675 | F89: =F71/$C$80 -> 0.073207784 | G89: =G71/$C$80 -> 0.093432558 | H89: =H71/$C$80 -> 0.10471602 | I89: =I71/$C$80 -> 0.10729656 | J89: =J71/$C$80 -> 0.13098158 | ... V89: =V71/$C$80 -> 0.1476358 | X89: =+AVERAGE(C89:V89) -> 0.10859213
B90: DCF Implied EV/EBITDA | C90: =$C$86/C62 -> 13.247868 | D90: =$C$86/D62 -> 11.344213 | E90: =$C$86/E62 -> 15.18796 | F90: =$C$86/F62 -> 10.34553 | G90: =$C$86/G62 -> 8.6373048 | H90: =$C$86/H62 -> 8.2801548 | I90: =$C$86/I62 -> 8.1127178 | J90: =$C$86/J62 -> 8.032195 | ... V90: =$C$86/V62 -> 7.1260483 | X90: =+AVERAGE(C90:V90) -> 8.6788322
B93: Current Market Cap | C93: =C81*C120 -> 2425.8564
B94: =B84 -> Net Debt | C94: =C84 -> 65.163794
B95: =B85 -> Minority Interest | C95: =C85 -> 0
B96: EV | C96: =SUM(C93:C95) -> 2491.0202
X97: Average
B98: Current Price Implied FCF Yield | C98: =C71/$C$93 -> 0.047921177 | D98: =D71/$C$93 -> -0.027394449 | E98: =E71/$C$93 -> -0.042694341 | F98: =F71/$C$93 -> 0.10242467 | G98: =G71/$C$93 -> 0.13072106 | H98: =H71/$C$93 -> 0.14650771 | I98: =I71/$C$93 -> 0.15011813 | J98: =J71/$C$93 -> 0.18325573 | ... V98: =V71/$C$93 -> 0.20655657 | X98: =+AVERAGE(C98:V98) -> 0.15193075
B99: Current Price Implied EV/EBITDA | C99: =$C$96/C62 -> 9.5400698 | D99: =$C$96/D62 -> 8.1692078 | E99: =$C$96/E62 -> 10.937171 | F99: =$C$96/F62 -> 7.4500349 | G99: =$C$96/G62 -> 6.2199057 | H99: =$C$96/H62 -> 5.9627144 | I99: =$C$96/I62 -> 5.8421395 | J99: =$C$96/J62 -> 5.7841533 | ... V99: =$C$96/V62 -> 5.1316179 | X99: =+AVERAGE(C99:V99) -> 6.2498104
B102: Valuation Summary
B104: DCF Method (not part of val. methodology)
B105: Cost of Equity | C105: =+Valuation!H70 -> 0.165
B106: Valuation | C106: =+Valuation!H79 -> 24.20378
B108: Free Cash Flow Yield Method
B109: Through cycle free cash flow | C109: =+AVERAGE(Valuation!D21:H21) -> 370.74105
B110: Target free cash flow yield | C110: =+Valuation!H26 -> 0.15
B111: Valuation | C111: =+Valuation!H28 -> 22.251094
B113: EV/EBITDA Method
B114: Through cycle EV/EBITDA | C114: =+Valuation!H47 -> 502.01749
B115: Target EV/EBITDA | C115: =+Valuation!H50 -> 5.5
B116: Valuation | C116: =+Valuation!H59 -> 22.350853
B118: Average Implied Target Price | C118: =ROUND(AVERAGE(C116,C111),0.05) -> 22
B120: Current Price | C120: 24.2
B121: Implied Price Upside | C121: =C118/C120-1 -> -0.090909091
B123: Dividend | C123: {=INDEX('Income Statement'!$DE$61:$EB$61,MATCH(G6,'Income Statement'!$DE$5:$EB$5,0))} -> 0.93
B124: Implied Total Return | C124: =(C123+C118)/C120-1 -> -0.052479339

Sheet Valuation
B2: Atlas Energy Solutions
B3: Valuation
B4: (US$ Millions)
B6: Weighted Valution
B8: Methodology | C8: Weight | D8: Valuation
B9: Free Cash Flow Yield Method | C9: 0.5 | D9: =$H$28 -> 22.251094
B10: EV/EBITDA Method | C10: 0.5 | D10: =$H$59 -> 22.350853
B11: Discounted Cash Flow | C11: 0 | D11: =$H$79 -> 24.20378
B12: Weighted implied valuation | D12: =ROUND(AVERAGE(D9:D10),0.05) -> 22
B14: Current Price | D14: =+Summary!C120 -> 24.2
B15: Estimated return | D15: =D12/D14-1 -> -0.090909091
B16: Rating | D16: =IF(D15>0.15,"Buy",IF(D15<-0.15,"Sell","Neutral")) -> Neutral
B18: Free Cash Flow Yield Method
C20: 2025 | D20: =C20+1 -> 2026 | E20: =D20+1 -> 2027 | F20: =E20+1 -> 2028 | G20: =F20+1 -> 2029 | H20: =G20+1 -> 2030
B21: Free Cash Flow | C21: {=INDEX('Cash Flow'!$DF$58:$EF$58,MATCH(C$20,'Cash Flow'!$DF$7:$EF$7,0))} -> 248.46755 | D21: {=INDEX('Cash Flow'!$DF$58:$EF$58,MATCH(D$20,'Cash Flow'!$DF$7:$EF$7,0))} -> 317.11052 | E21: {=INDEX('Cash Flow'!$DF$58:$EF$58,MATCH(E$20,'Cash Flow'!$DF$7:$EF$7,0))} -> 351.14786 | F21: {=INDEX('Cash Flow'!$DF$58:$EF$58,MATCH(F$20,'Cash Flow'!$DF$7:$EF$7,0))} -> -154.56676 | G21: {=INDEX('Cash Flow'!$DF$58:$EF$58,MATCH(G$20,'Cash Flow'!$DF$7:$EF$7,0))} -> 933.87171 | H21: {=INDEX('Cash Flow'!$DF$58:$EM$58,MATCH(H$20,'Cash Flow'!$DF$7:$EM$7,0))} -> 406.14191
B22: Shares Outstanding | C22: {=INDEX('Income Statement'!$DU$59:$EF$59,MATCH(Valuation!C$20,'Income Statement'!$DU$7:$EF$7,0))} -> 111.078 | D22: {=INDEX('Income Statement'!$DU$59:$EF$59,MATCH(Valuation!D$20,'Income Statement'!$DU$7:$EF$7,0))} -> 111.078 | E22: {=INDEX('Income Statement'!$DU$59:$EF$59,MATCH(Valuation!E$20,'Income Statement'!$DU$7:$EF$7,0))} -> 111.078 | F22: {=INDEX('Income Statement'!$DU$59:$EF$59,MATCH(Valuation!F$20,'Income Statement'!$DU$7:$EF$7,0))} -> 111.078 | G22: {=INDEX('Income Statement'!$DU$59:$EF$59,MATCH(Valuation!G$20,'Income Statement'!$DU$7:$EF$7,0))} -> 111.078 | H22: {=INDEX('Income Statement'!$DU$59:$EM$59,MATCH(Valuation!H$20,'Income Statement'!$DU$7:$EM$7,0))} -> 111.078
B23: FCF/Share | C23: =C21/C22 -> 2.2368746 | D23: =D21/D22 -> 2.8548455 | E23: =E21/E22 -> 3.1612728 | F23: =F21/F22 -> -1.3915155 | G23: =G21/G22 -> 8.4073508 | H23: =H21/H22 -> 3.6563668
C24: =C23/$D$14 -> 0.092432833 | D24: =D23/$D$14 -> 0.11796882 | E24: =E23/$D$14 -> 0.13063111 | F24: =F23/$D$14 -> -0.05750064 | G24: =G23/$D$14 -> 0.34741119 | H24: =H23/$D$14 -> 0.15108954
B25: Historical FCF Yield
B26: Target FCF Yield | G26: 20 | H26: 0.15
B28: Implied Valuation | H28: =AVERAGE(D23:H23)/H26 -> 22.251094
B30: Current Price | H30: 24.2
B31: Estimated return | H31: =H28/H30-1 -> -0.080533317
B33: Enterprise Value to EBITDA Method
D34: 427 | E34: 604 | F34: 635
B35: Current Price Implied | C35: 2025 | D35: =D20 -> 2026 | E35: =E20 -> 2027 | F35: =F20 -> 2028 | G35: =G20 -> 2029 | H35: =H20 -> 2030 | J35: Target Price Implied | K35: =C35 -> 2025 | L35: =D35 -> 2026 | M35: =E35 -> 2027 | N35: =F35 -> 2028 | O35: =G35 -> 2029 | P35: =H35 -> 2030
B36: EBITDA | C36: {=INDEX('Income Statement'!$DU$47:$EF$47,MATCH(C$35,'Income Statement'!$DU$7:$EF$7,0))} -> 361.88657 | D36: {=INDEX('Income Statement'!$DU$47:$EF$47,MATCH(D$35,'Income Statement'!$DU$7:$EF$7,0))} -> 435.86073 | E36: {=INDEX('Income Statement'!$DU$47:$EF$47,MATCH(E$35,'Income Statement'!$DU$7:$EF$7,0))} -> 485.96772 | F36: {=INDEX('Income Statement'!$DU$47:$EF$47,MATCH(F$35,'Income Statement'!$DU$7:$EF$7,0))} -> 514.22921 | G36: {=INDEX('Income Statement'!$DU$47:$EF$47,MATCH(G$35,'Income Statement'!$DU$7:$EF$7,0))} -> 526.36271 | H36: {=INDEX('Income Statement'!$DU$47:$EM$47,MATCH(H$35,'Income Statement'!$DU$7:$EM$7,0))} -> 547.66709 | J36: =B36 -> EBITDA | K36: =C36 -> 361.88657 | L36: =D36 -> 435.86073 | M36: =E36 -> 485.96772 | N36: =F36 -> 514.22921 | O36: =G36 -> 526.36271 | P36: =H36 -> 547.66709
B37: Shares Outstanding | C37: {=INDEX('Income Statement'!$DU$59:$EF$59,MATCH(Valuation!C$35,'Income Statement'!$DU$7:$EF$7,0))} -> 111.078 | D37: {=INDEX('Income Statement'!$DU$59:$EF$59,MATCH(Valuation!D$35,'Income Statement'!$DU$7:$EF$7,0))} -> 111.078 | E37: {=INDEX('Income Statement'!$DU$59:$EF$59,MATCH(Valuation!E$35,'Income Statement'!$DU$7:$EF$7,0))} -> 111.078 | F37: {=INDEX('Income Statement'!$DU$59:$EF$59,MATCH(Valuation!F$35,'Income Statement'!$DU$7:$EF$7,0))} -> 111.078 | G37: {=INDEX('Income Statement'!$DU$59:$EF$59,MATCH(Valuation!G$35,'Income Statement'!$DU$7:$EF$7,0))} -> 111.078 | H37: {=INDEX('Income Statement'!$DU$59:$EM$59,MATCH(Valuation!H$35,'Income Statement'!$DU$7:$EM$7,0))} -> 111.078 | J37: =B37 -> Shares Outstanding | K37: =C37 -> 111.078 | L37: =D37 -> 111.078 | M37: =E37 -> 111.078 | N37: =F37 -> 111.078 | O37: =G37 -> 111.078 | P37: =H37 -> 111.078
B38: Current Price | C38: 18.33 | D38: =$H$30 -> 24.2 | E38: =$H$30 -> 24.2 | F38: =$H$30 -> 24.2 | G38: =$H$30 -> 24.2 | H38: =$H$30 -> 24.2 | J38: Target Price | K38: =$H$59 -> 22.350853 | L38: =$H$59 -> 22.350853 | M38: =$H$59 -> 22.350853 | N38: =$H$59 -> 22.350853 | O38: =$H$59 -> 22.350853 | P38: =$H$59 -> 22.350853
B39: Market Capitalization | C39: =C38*C37 -> 2036.0597 | D39: =D38*D37 -> 2688.0876 | E39: =E38*E37 -> 2688.0876 | F39: =F38*F37 -> 2688.0876 | G39: =G38*G37 -> 2688.0876 | H39: =H38*H37 -> 2688.0876 | J39: Implied Mkt Cap | K39: =K38*K37 -> 2482.6881 | L39: =L38*L37 -> 2482.6881 | M39: =M38*M37 -> 2482.6881 | N39: =N38*N37 -> 2482.6881 | O39: =O38*O37 -> 2482.6881 | P39: =P38*P37 -> 2482.6881
B40: Net Debt | C40: =172.82-210.174 -> -37.354 | D40: {=INDEX('Balance Sheet'!$DU$57:$EF$57,MATCH(Valuation!D$35,'Balance Sheet'!$DU$7:$EF$7,0))} -> 78.862564 | E40: {=INDEX('Balance Sheet'!$DU$57:$EF$57,MATCH(Valuation!E$35,'Balance Sheet'!$DU$7:$EF$7,0))} -> -148.84209 | F40: {=INDEX('Balance Sheet'!$DU$57:$EF$57,MATCH(Valuation!F$35,'Balance Sheet'!$DU$7:$EF$7,0))} -> 135.34003 | G40: {=INDEX('Balance Sheet'!$DU$57:$EF$57,MATCH(Valuation!G$35,'Balance Sheet'!$DU$7:$EF$7,0))} -> -662.43555 | H40: {=INDEX('Balance Sheet'!$DU$57:$EM$57,MATCH(Valuation!H$35,'Balance Sheet'!$DU$7:$EM$7,0))} -> -925.67652 | J40: =B40 -> Net Debt | K40: =C40 -> -37.354 | L40: =D40 -> 78.862564 | M40: =E40 -> -148.84209 | N40: =F40 -> 135.34003 | O40: =G40 -> -662.43555 | P40: =H40 -> -925.67652
B41: Preferred Equity | C41: 0 | D41: 0 | E41: 0 | F41: 0 | G41: 0 | H41: 0 | J41: =B41 -> Preferred Equity | K41: =C41 -> 0 | L41: =D41 -> 0 | M41: =E41 -> 0 | N41: =F41 -> 0 | O41: =G41 -> 0 | P41: =H41 -> 0
B42: Minority Interest | C42: 0 | D42: 0 | E42: 0 | F42: 0 | G42: 0 | H42: 0 | J42: =B42 -> Minority Interest | K42: =C42 -> 0 | L42: =D42 -> 0 | M42: =E42 -> 0 | N42: =F42 -> 0 | O42: =G42 -> 0 | P42: =H42 -> 0
B43: Enterprise Value | C43: =SUM(C39:C42) -> 1998.7057 | D43: =SUM(D39:D42) -> 2766.9502 | E43: =SUM(E39:E42) -> 2539.2455 | F43: =SUM(F39:F42) -> 2823.4276 | G43: =SUM(G39:G42) -> 2025.6521 | H43: =SUM(H39:H42) -> 1762.4111 | J43: =B43 -> Enterprise Value | K43: =SUM(K39:K42) -> 2445.3341 | L43: =SUM(L39:L42) -> 2561.5506 | M43: =SUM(M39:M42) -> 2333.846 | N43: =SUM(N39:N42) -> 2618.0281 | O43: =SUM(O39:O42) -> 1820.2525 | P43: =SUM(P39:P42) -> 1557.0115
B45: Implied EV/EBITDA | C45: =C43/C36 -> 5.5230171 | D45: =D43/D36 -> 6.3482438 | E45: =E43/E36 -> 5.225132 | F45: =F43/F36 -> 5.4906014 | G45: =G43/G36 -> 3.8483959 | H45: =H43/H36 -> 3.2180336 | J45: Implied EV/EBITDA | K45: =K43/K36 -> 6.7571838 | L45: =L43/L36 -> 5.8769934 | M45: =M43/M36 -> 4.8024712 | N45: =N43/N36 -> 5.0911696 | O45: =O43/O36 -> 3.4581715 | P45: =P43/P36 -> 2.8429891
B47: Through cycle EBITDA (2023-2026) | H47: =AVERAGE(D36:H36) -> 502.01749
B49: 2008-2014 average EV/EBITDA (Historical)
B50: Target through cycle EV/EBITDA | H50: 5.5
B52: Implied Enterprise Value | H52: =H50*H47 -> 2761.0962
B53: Net Debt | H53: {=INDEX('Balance Sheet'!$DU$57:$EB$57,MATCH(Valuation!C$35,'Balance Sheet'!$DU$7:$EB$7,0))} -> 278.40813
B54: Minority Interest | H54: 0
B55: Preferred Equity | H55: 0
B56: Equity Value | H56: =H52-SUM(H53:H55) -> 2482.6881
B57: Shares Outstanding | H57: {=INDEX('Income Statement'!$DU$59:$EB$59,MATCH(Valuation!C$35,'Income Statement'!$DU$7:$EB$7,0))} -> 111.078
B59: Implied Valuation | H59: =H56/H57 -> 22.350853
B61: Current Price | H61: =H30 -> 24.2
B62: Estimated return | H62: =H59/H61-1 -> -0.076411028
B65: Discounted Cash Flow Method
B67: Terminal Growth Rate Method
B69: 10 Yr Treasury | C69: 0.038 | D69: Beta | E69: 1.15 | F69: CAPM | H69: =C69+C70*E69 -> 0.107
B70: Equiy Risk Premium | C70: 0.06 | F70: Cost of Equity | H70: 0.165
C72: 1 | D72: =C72+1 -> 2 | E72: =D72+1 -> 3 | F72: =E72+1 -> 4 | G72: =F72+1 -> 5 | H72: =G72+1 -> 6
F73: Terminal Growth Rate | H73: -0.005
C74: 2024 | D74: =C74+1 -> 2025 | E74: =D74+1 -> 2026 | F74: =E74+1 -> 2027 | G74: =F74+1 -> 2028 | H74: =G74+1 -> 2029
B75: Free Cash Flow | C75: {=INDEX('Cash Flow'!$DF$58:$EF$58,MATCH(Valuation!C$74,'Cash Flow'!$DF$7:$EF$7,0))} -> -103.57034 | D75: {=INDEX('Cash Flow'!$DF$58:$EF$58,MATCH(Valuation!D$74,'Cash Flow'!$DF$7:$EF$7,0))} -> 248.46755 | E75: {=INDEX('Cash Flow'!$DF$58:$EF$58,MATCH(Valuation!E$74,'Cash Flow'!$DF$7:$EF$7,0))} -> 317.11052 | F75: {=INDEX('Cash Flow'!$DF$58:$EF$58,MATCH(Valuation!F$74,'Cash Flow'!$DF$7:$EF$7,0))} -> 351.14786 | G75: {=INDEX('Cash Flow'!$DF$58:$EF$58,MATCH(Valuation!G$74,'Cash Flow'!$DF$7:$EF$7,0))} -> -154.56676 | H75: {=INDEX('Cash Flow'!$DF$58:$EM$58,MATCH(Valuation!H$74,'Cash Flow'!$DF$7:$EM$7,0))} -> 933.87171
B76: Shares Outstanding | C76: {=INDEX('Income Statement'!$DU$59:$EF$59,MATCH(Valuation!C$74,'Income Statement'!$DU$7:$EF$7,0))} -> 111.078 | D76: {=INDEX('Income Statement'!$DU$59:$EF$59,MATCH(Valuation!D$74,'Income Statement'!$DU$7:$EF$7,0))} -> 111.078 | E76: {=INDEX('Income Statement'!$DU$59:$EF$59,MATCH(Valuation!E$74,'Income Statement'!$DU$7:$EF$7,0))} -> 111.078 | F76: {=INDEX('Income Statement'!$DU$59:$EF$59,MATCH(Valuation!F$74,'Income Statement'!$DU$7:$EF$7,0))} -> 111.078 | G76: {=INDEX('Income Statement'!$DU$59:$EF$59,MATCH(Valuation!G$74,'Income Statement'!$DU$7:$EF$7,0))} -> 111.078 | H76: {=INDEX('Income Statement'!$DU$59:$EM$59,MATCH(Valuation!H$74,'Income Statement'!$DU$7:$EM$7,0))} -> 111.078
B77: FCF/share | C77: =C75/C76 -> -0.93241092 | D77: =D75/D76 -> 2.2368746 | E77: =E75/E76 -> 2.8548455 | F77: =F75/F76 -> 3.1612728 | G77: =G75/G76 -> -1.3915155 | H77: =H75/H76 -> 8.4073508
B78: Discounted Value | C78: =C77/(1+$H$70)^C$72 -> -0.80035272 | D78: =D77/(1+$H$70)^D$72 -> 1.6481236 | E78: =E77/(1+$H$70)^E$72 -> 1.8055305 | F78: =F77/(1+$H$70)^F$72 -> 1.7161619 | G78: =G77/(1+$H$70)^G$72 -> -0.64842301 | H78: =H77/(1+$H$70)^H$72 -> 3.36282
B79: Implied Valuation | H79: =SUM(D78:G78)+H78*(1+$H$73)/(H70-H73) -> 24.20378
B81: Current Price | H81: =$H$30 -> 24.2
B82: Estimated return | H82: =H79/H81-1 -> 0.00015621633
B83: Rating
B85: Implied FCF yield | H85: =AVERAGE(C77:G77)/H79 -> 0.048992895
H88: =+AVERAGE(H79,H59,H28) -> 22.935242

Sheet AESI_Live_Sheet
A1: Issuer: Atlas Energy Solutions | C1: 2500783373 | F1: 2020 | G1: 2021 | H1: 2022 | I1: 2023 | J1: 2024 | K1: 2025 | L1: 2026 | M1: 2027 | O1: 2020 Q1 | P1: 2020 Q2 | Q1: 2020 Q3 | R1: 2020 Q4 | S1: 2021 Q1 | T1: 2021 Q2 | U1: 2021 Q3 | V1: 2021 Q4 | W1: 2022 Q1 | X1: 2022 Q2 | Y1: 2022 Q3 | Z1: 2022 Q4 | AA1: 2023 Q1 | AB1: 2023 Q2 | AC1: 2023 Q3 | AD1: 2023 Q4 | AE1: 2024 Q1 | AF1: 2024 Q2 | AG1: 2024 Q3 | AH1: 2024 Q4 | AI1: 2025 Q1 | AJ1: 2025 Q2 | AK1: 2025 Q3 | AL1: 2025 Q4 | AM1: 2026 Q1 | AN1: 2026 Q2 | AO1: 2026 Q3 | AP1: 2026 Q4 | AQ1: 2027 Q1 | AR1: 2027 Q2 | AS1: 2027 Q3 | AT1: 2027 Q4
F2: Actual | G2: Actual | H2: Actual | I2: Actual | J2: Estimate | K2: Estimate | L2: Estimate | M2: Estimate | O2: Actual | P2: Actual | Q2: Actual | R2: Actual | S2: Actual | T2: Actual | U2: Actual | V2: Actual | W2: Actual | X2: Actual | Y2: Actual | Z2: Actual | AA2: Actual | AB2: Actual | AC2: Actual | AD2: Actual | AE2: Actual | AF2: Actual | AG2: Actual | AH2: Estimate | AI2: Estimate | AJ2: Estimate | AK2: Estimate | AL2: Estimate | AM2: Estimate | AN2: Estimate | AO2: Estimate | AP2: Estimate | AQ2: Estimate | AR2: Estimate | AS2: Estimate | AT2: Estimate
F3: 44196 | G3: 44561 | H3: 44926 | I3: 45291 | J3: 45657 | K3: 46022 | L3: 46387 | M3: 46752 | O3: 43921 | P3: 44012 | Q3: 44104 | R3: 44196 | S3: 44286 | T3: 44377 | U3: 44469 | V3: 44561 | W3: 44651 | X3: 44742 | Y3: 44834 | Z3: 44926 | AA3: 45016 | AB3: 45107 | AC3: 45199 | AD3: 45291 | AE3: 45382 | AF3: 45473 | AG3: 45565 | AH3: 45657 | AI3: 45747 | AJ3: 45838 | AK3: 45930 | AL3: 46022 | AM3: 46112 | AN3: 46203 | AO3: 46295 | AP3: 46387 | AQ3: 46477 | AR3: 46568 | AS3: 46660 | AT3: 46752
A4: Issuer: Atlas Energy Solutions | B4: 1510B3H
A5: Reference Data
B6: Issuer Name | C6: Issuer Name | E6: Atlas Energy Solutions
B7: Reporting Currency | C7: CURRENCY_ISO | E7: USD
A8: General Information
B9: M&A probability (1 = high, 3 = low) | C9: MA_PROB | E9: 3
A10: Income Statement
B11: Sales, net revenue | C11: SALES | D11: =AESI_Live_Sheet!L_CURRENCY_ISSR_208021701_REP -> USD | F11: 111.77163 | G11: 172.40566 | H11: 482.59377 | I11: 613.96 | J11: 1063.6907 | K11: 1321.3546 | L11: 1357.5616 | M11: 1409.0723 | O11: 42.722146 | P11: 13.737979 | Q11: 28.992068 | R11: 26.319435 | S11: 31.831894 | T11: 44.428787 | U11: 43.297373 | V11: 52.847608 | W11: 59.853818 | X11: 131.32338 | Y11: 141.55213 | Z11: 149.86444 | AA11: 153.418 | AB11: 161.788 | AC11: 157.616 | AD11: 141.138 | AE11: 192.667 | AF11: 287.518 | AG11: 304.434 | AH11: 279.07171 | AI11: 314.47631 | AJ11: 330.92099 | AK11: 337.31654 | AL11: 338.64074 | AM11: 332.0986 | AN11: 337.02854 | AO11: 342.77966 | AP11: 345.65478 | AQ11: 348.0172 | AR11: 351.09643 | AS11: 354.20298 | AT11: 355.75565
B12: Cost of goods sold, COGS | C12: COST_GD_SD | D12: =AESI_Live_Sheet!L_CURRENCY_ISSR_208021701_REP -> USD | F12: -73.118 | G12: -84.656 | H12: -198.96207 | I12: -260.396 | J12: -738.68196 | K12: -882.64942 | L12: -862.04063 | M12: -868.7222 | O12: -18.2795 | P12: -18.2795 | Q12: -18.2795 | R12: -18.2795 | S12: -18.92 | T12: -21.912 | U12: -21.912 | V12: -21.912 | W12: -24.494075 | X12: -47.044394 | Y12: -60.138574 | Z12: -67.285024 | AA12: -62.555 | AB12: -63.504 | AC12: -67.77 | AD12: -66.567 | AE12: -106.746 | AF12: -202.136 | AG12: -225.347 | AH12: -204.45296 | AI12: -223.40134 | AJ12: -218.47626 | AK12: -220.32899 | AL12: -220.44283 | AM12: -212.67077 | AN12: -214.91263 | AO12: -217.0316 | AP12: -217.42563 | AQ12: -215.76729 | AR12: -216.92247 | AS12: -218.00239 | AT12: -218.03005
B13: SG&A, selling, general and admin. expense | C13: SEL_GL_AD | D13: =AESI_Live_Sheet!L_CURRENCY_ISSR_208021701_REP -> USD | F13: -14.506318 | G13: -16.019176 | H13: -22.520389 | I13: -48.636 | J13: -101.33302 | K13: -92.494821 | L13: -95.02931 | M13: -98.635058 | O13: -4.0907364 | P13: -2.4430765 | Q13: -3.4044525 | R13: -4.5680524 | S13: -3.9740135 | T13: -3.7569652 | U13: -3.5100979 | V13: -4.778099 | W13: -4.7567287 | X13: -4.843585 | Y13: -5.4519953 | Z13: -7.4680798 | AA13: -8.504 | AB13: -12.183 | AC13: -14.301 | AD13: -13.648 | AE13: -29.069 | AF13: -27.266 | AG13: -25.463 | AH13: -19.53502 | AI13: -22.013342 | AJ13: -23.164469 | AK13: -23.612158 | AL13: -23.704852 | AM13: -23.246902 | AN13: -23.591998 | AO13: -23.994576 | AP13: -24.195835 | AQ13: -24.361204 | AR13: -24.57675 | AS13: -24.794209 | AT13: -24.902895
B14: Total operating expense | C14: OP_COST | D14: =AESI_Live_Sheet!L_CURRENCY_ISSR_208021701_REP -> USD | F14: -87.624318 | G14: -100.67518 | H14: -221.48246 | I14: -309.032 | J14: -840.01498 | K14: -975.14424 | L14: -957.06994 | M14: -967.35725 | O14: -22.370236 | P14: -20.722577 | Q14: -21.683952 | R14: -22.847552 | S14: -22.894014 | T14: -25.668965 | U14: -25.422098 | V14: -26.690099 | W14: -29.250804 | X14: -51.887979 | Y14: -65.59057 | Z14: -74.753104 | AA14: -71.059 | AB14: -75.687 | AC14: -82.071 | AD14: -80.215 | AE14: -135.815 | AF14: -229.402 | AG14: -250.81 | AH14: -223.98798 | AI14: -245.41468 | AJ14: -241.64073 | AK14: -243.94114 | AL14: -244.14768 | AM14: -235.91768 | AN14: -238.50463 | AO14: -241.02617 | AP14: -241.62146 | AQ14: -240.12849 | AR14: -241.49922 | AS14: -242.7966 | AT14: -242.93295
B15: R&D expense | C15: RD_EXP | D15: =AESI_Live_Sheet!L_CURRENCY_ISSR_208021701_REP -> USD
B16: ESO expense (pre-tax) | C16: ESO_PRE_TAX | D16: =AESI_Live_Sheet!L_CURRENCY_ISSR_208021701_REP -> USD
B17: Other operating income/(expense) (incl. leases) | C17: OTH_OP_INC_EXP | D17: =AESI_Live_Sheet!L_CURRENCY_ISSR_208021701_REP -> USD
B18: Total operating expense (incl. D&A) | C18: TOT_OPS_EXP_DDA | D18: =AESI_Live_Sheet!L_CURRENCY_ISSR_208021701_REP -> USD | F18: -109.14101 | G18: -125.21607 | H18: -249.93645 | I18: -348.83 | J18: -934.48533 | K18: -1079.9416 | L18: -1061.8673 | M18: -1072.1546 | O18: -27.987938 | P18: -25.429196 | Q18: -27.15319 | R18: -28.570688 | S18: -28.575479 | T18: -31.834319 | U18: -31.597161 | V18: -33.20911 | W18: -35.715276 | X18: -58.619829 | Y18: -72.87123 | Z18: -82.730112 | AA18: -79.578 | AB18: -85.12 | AC18: -92.292 | AD18: -91.84 | AE18: -152.99 | AF18: -254.429 | AG18: -276.879 | AH18: -250.18733 | AI18: -271.61403 | AJ18: -267.84007 | AK18: -270.14049 | AL18: -270.34703 | AM18: -262.11702 | AN18: -264.70397 | AO18: -267.22552 | AP18: -267.82081 | AQ18: -266.32784 | AR18: -267.69856 | AS18: -268.99594 | AT18: -269.13229
B19: Total operating expense (excl. D&A) | C19: TOT_OPS_EXP | D19: =AESI_Live_Sheet!L_CURRENCY_ISSR_208021701_REP -> USD | F19: -87.624318 | G19: -100.67518 | H19: -221.48246 | I19: -309.032 | J19: -840.01498 | K19: -975.14424 | L19: -957.06994 | M19: -967.35725 | O19: -22.370236 | P19: -20.722577 | Q19: -21.683952 | R19: -22.847552 | S19: -22.894014 | T19: -25.668965 | U19: -25.422098 | V19: -26.690099 | W19: -29.250804 | X19: -51.887979 | Y19: -65.59057 | Z19: -74.753104 | AA19: -71.059 | AB19: -75.687 | AC19: -82.071 | AD19: -80.215 | AE19: -135.815 | AF19: -229.402 | AG19: -250.81 | AH19: -223.98798 | AI19: -245.41468 | AJ19: -241.64073 | AK19: -243.94114 | AL19: -244.14768 | AM19: -235.91768 | AN19: -238.50463 | AO19: -241.02617 | AP19: -241.62146 | AQ19: -240.12849 | AR19: -241.49922 | AS19: -242.7966 | AT19: -242.93295
B20: EBITDA | C20: EBITDA_CALC | D20: =AESI_Live_Sheet!L_CURRENCY_ISSR_208021701_REP -> USD | F20: 22.897311 | G20: 71.730486 | H20: 261.11132 | I20: 321.963 | J20: 288.02169 | K20: 373.909 | L20: 436.16541 | M20: 486.27241 | O20: 20.03941 | P20: -7.2970977 | Q20: 6.995616 | R20: 3.1593829 | S20: 8.9378806 | T20: 18.759821 | U20: 17.875275 | V20: 26.157509 | W20: 30.603014 | X20: 79.435402 | Y20: 75.961561 | Z20: 75.11134 | AA20: 82.359 | AB20: 86.101 | AC20: 75.545 | AD20: 68.706 | AE20: 75.543 | AF20: 79.072 | AG20: 71.051 | AH20: 62.355694 | AI20: 76.023014 | AJ20: 95.815313 | AK20: 100.0135 | AL20: 102.05718 | AM20: 104.50677 | AN20: 107.12014 | AO20: 110.92412 | AP20: 113.61439 | AQ20: 118.30888 | AR20: 120.54486 | AS20: 122.81556 | AT20: 124.6031
B21: Depreciation | C21: DEPREC | D21: =AESI_Live_Sheet!L_CURRENCY_ISSR_208021701_REP -> USD | F21: -21.516694 | G21: -24.540894 | H21: -28.453991 | I21: -39.798 | J21: -94.470345 | K21: -104.79738 | L21: -104.79738 | M21: -104.79738 | O21: -5.6177018 | P21: -4.7066194 | Q21: -5.4692377 | R21: -5.7231352 | S21: -5.6814658 | T21: -6.1653538 | U21: -6.1750633 | V21: -6.5190106 | W21: -6.4644721 | X21: -6.7318501 | Y21: -7.2806603 | Z21: -7.9770085 | AA21: -8.519 | AB21: -9.433 | AC21: -10.221 | AD21: -11.625 | AE21: -17.175 | AF21: -25.027 | AG21: -26.069 | AH21: -26.199345 | AI21: -26.199345 | AJ21: -26.199345 | AK21: -26.199345 | AL21: -26.199345 | AM21: -26.199345 | AN21: -26.199345 | AO21: -26.199345 | AP21: -26.199345 | AQ21: -26.199345 | AR21: -26.199345 | AS21: -26.199345 | AT21: -26.199345
B22: Amortization | C22: GOODWILL_AMORT | D22: =AESI_Live_Sheet!L_CURRENCY_ISSR_208021701_REP -> USD
B23: EBIT, operating profit | C23: EBIT | D23: =AESI_Live_Sheet!L_CURRENCY_ISSR_208021701_REP -> USD | F23: 2.6306168 | G23: 47.189592 | H23: 232.65733 | I23: 265.13 | J23: 129.20539 | K23: 241.41297 | L23: 295.69426 | M23: 336.91763 | O23: 14.734208 | P23: -11.691217 | Q23: 1.8388783 | R23: -2.2512523 | S23: 3.2564148 | T23: 12.594468 | U23: 11.700211 | V23: 19.638499 | W23: 24.138542 | X23: 72.703552 | Y23: 68.680901 | Z23: 67.134332 | AA23: 73.84 | AB23: 76.668 | AC23: 65.324 | AD23: 49.298 | AE23: 39.677 | AF23: 33.089 | AG23: 27.555 | AH23: 28.884387 | AI23: 42.86228 | AJ23: 63.080917 | AK23: 67.176055 | AL23: 68.293717 | AM23: 69.981576 | AN23: 72.324562 | AO23: 75.554144 | AP23: 77.833974 | AQ23: 81.689367 | AR23: 83.397864 | AS23: 85.207038 | AT23: 86.623357
B24: Interest income | C24: INT_INC_IND | D24: =AESI_Live_Sheet!L_CURRENCY_ISSR_208021701_REP -> USD
B25: Interest expense | C25: INT_EXP_IND | D25: =AESI_Live_Sheet!L_CURRENCY_ISSR_208021701_REP -> USD | F25: -32.819165 | G25: -30.276282 | H25: -15.739831 | I25: -7.689 | J25: -37.822 | K25: -24.391786 | L25: -13.037606 | M25: -13.037606 | O25: -7.5915417 | P25: -8.0636007 | Q25: -8.4732294 | R25: -8.6907927 | S25: -8.4997901 | T25: -8.5120422 | U25: -8.2526235 | V25: -5.0118261 | W25: -3.9897278 | X25: -3.8835333 | Y25: -3.8762648 | Z25: -3.9903049 | AA25: -3.442 | AB25: -0.521 | AC25: -1.496 | AD25: -2.23 | AE25: -4.978 | AF25: -10.458 | AG25: -11.193 | AH25: -11.193 | AI25: -8.9544 | AJ25: -7.16352 | AK25: -5.014464 | AL25: -3.2594016 | AM25: -3.2594016 | AN25: -3.2594016 | AO25: -3.2594016 | AP25: -3.2594016 | AQ25: -3.2594016 | AR25: -3.2594016 | AS25: -3.2594016 | AT25: -3.2594016
B26: Net interest income/(expense) | C26: NET_INT_EXP | D26: =AESI_Live_Sheet!L_CURRENCY_ISSR_208021701_REP -> USD | F26: -32.819165 | G26: -30.276282 | H26: -15.739831 | I26: -7.689 | J26: -37.822 | K26: -24.391786 | L26: -13.037606 | M26: -13.037606 | O26: -7.5915417 | P26: -8.0636007 | Q26: -8.4732294 | R26: -8.6907927 | S26: -8.4997901 | T26: -8.5120422 | U26: -8.2526235 | V26: -5.0118261 | W26: -3.9897278 | X26: -3.8835333 | Y26: -3.8762648 | Z26: -3.9903049 | AA26: -3.442 | AB26: -0.521 | AC26: -1.496 | AD26: -2.23 | AE26: -4.978 | AF26: -10.458 | AG26: -11.193 | AH26: -11.193 | AI26: -8.9544 | AJ26: -7.16352 | AK26: -5.014464 | AL26: -3.2594016 | AM26: -3.2594016 | AN26: -3.2594016 | AO26: -3.2594016 | AP26: -3.2594016 | AQ26: -3.2594016 | AR26: -3.2594016 | AS26: -3.2594016 | AT26: -3.2594016
B27: Income/(loss) from unconsolidated subs & associates | C27: ASSOCIATE | D27: =AESI_Live_Sheet!L_CURRENCY_ISSR_208021701_REP -> USD
B28: Profit/(loss) on disposals of assets, pre-tax | C28: PROFIT_ON_DISP | D28: =AESI_Live_Sheet!L_CURRENCY_ISSR_208021701_REP -> USD
B29: Other non-ops income/(expense) | C29: OTH_COST_INC | D29: =AESI_Live_Sheet!L_CURRENCY_ISSR_208021701_REP -> USD | F29: -5.1314379 | G29: 4.5908677 | I29: 0.43 | J29: -16.734 | O29: -1.3893248 | P29: -2.4962639 | Q29: -0.43985546 | R29: -0.80599374 | S29: 0.01130557 | T29: 4.4923336 | U29: 0.03033345 | V29: 0.056895 | AA29: 0.184 | AB29: 0.118 | AC29: 0.136 | AD29: -0.008 | AE29: 0.023 | AF29: 5.004 | AG29: 12.607
B30: Pre-tax profit | C30: PT_PROF | D30: =AESI_Live_Sheet!L_CURRENCY_ISSR_208021701_REP -> USD | F30: -35.319986 | G30: 21.504178 | H30: 216.9175 | I30: 257.871 | J30: 74.649387 | K30: 217.02118 | L30: 282.65665 | M30: 323.88002 | O30: 5.7533413 | P30: -22.251082 | Q30: -7.0742065 | R30: -11.748039 | S30: -5.2320697 | T30: 8.5747592 | U30: 3.4779213 | V30: 14.683567 | W30: 20.148815 | X30: 68.820018 | Y30: 64.804636 | Z30: 63.144027 | AA30: 70.582 | AB30: 76.265 | AC30: 63.964 | AD30: 47.06 | AE30: 34.722 | AF30: 17.903 | AG30: 4.333 | AH30: 17.691387 | AI30: 33.90788 | AJ30: 55.917397 | AK30: 62.161591 | AL30: 65.034315 | AM30: 66.722174 | AN30: 69.065161 | AO30: 72.294742 | AP30: 74.574572 | AQ30: 78.429965 | AR30: 80.138462 | AS30: 81.947636 | AT30: 83.363956
A31: Additional Income Statement Items
B32: Operating lease cost | C32: LEASE_PAY | D32: =AESI_Live_Sheet!L_CURRENCY_ISSR_208021701_REP -> USD
B33: Lease payments (deemed interest portion) | C33: LEASE_DEEM_INT | D33: =AESI_Live_Sheet!L_CURRENCY_ISSR_208021701_REP -> USD
B34: Lease payments (deemed depreciation portion) | C34: LEASE_DEEM_DEPR | D34: =AESI_Live_Sheet!L_CURRENCY_ISSR_208021701_REP -> USD
B35: Gross interest charge | C35: NET_INT_CH | D35: =AESI_Live_Sheet!L_CURRENCY_ISSR_208021701_REP -> USD
B36: Income from associates (operating) | C36: ASSOCIATE_OP | D36: =AESI_Live_Sheet!L_CURRENCY_ISSR_208021701_REP -> USD
B37: Depreciation ROU assets (applicable to IFRS cos.) | C37: DEPR_ROU_ASSETS | D37: =AESI_Live_Sheet!L_CURRENCY_ISSR_208021701_REP -> USD
B38: Lease interest charge (applicable to IFRS cos.) | C38: LEASE_INT_CHG | D38: =AESI_Live_Sheet!L_CURRENCY_ISSR_208021701_REP -> USD
B39: Lease standard adopted (US GAAP ASC 842/ IFRS 16) | C39: LEASE_ADOPT | E39: Y
A40: Balance Sheet
B41: Cash & cash equivalents | C41: CASH_EQ | D41: =AESI_Live_Sheet!L_CURRENCY_ISSR_208021701_REP -> USD | F41: 36.072472 | G41: 40.400985 | H41: 82.010041 | I41: 210.174 | J41: 53.791109 | K41: 162.9476 | L41: 330.49317 | M41: 526.19782 | W41: 53.83638 | X41: 69.009332 | Y41: 90.719619 | Z41: 82.010041 | AA41: 352.656 | AB41: 341.674 | AC41: 264.538 | AD41: 210.174 | AE41: 187.12 | AF41: 104.723 | AG41: 78.637 | AH41: 53.791109 | AI41: 19.684141 | AJ41: 27.927618 | AK41: 102.00957 | AL41: 162.9476 | AM41: 184.57885 | AN41: 230.53035 | AO41: 263.36556 | AP41: 330.49317 | AQ41: 372.69241 | AR41: 409.61442 | AS41: 439.31219 | AT41: 526.19782
B42: Accounts receivable | C42: DEBTORS | D42: =AESI_Live_Sheet!L_CURRENCY_ISSR_208021701_REP -> USD | F42: 11.508702 | G42: 29.41804 | H42: 73.341285 | I42: 71.17 | J42: 168.23329 | K42: 136.64848 | L42: 203.08112 | M42: 210.68777 | W42: 33.146973 | X42: 74.028675 | Y42: 72.611938 | Z42: 73.341285 | AA42: 95.112 | AB42: 85.94 | AC42: 102.234 | AD42: 71.17 | AE42: 185.758 | AF42: 197.072 | AG42: 179.924 | AH42: 168.23329 | AI42: 199.05512 | AJ42: 209.46416 | AK42: 160.13428 | AL42: 136.64848 | AM42: 167.51074 | AN42: 176.7973 | AO42: 201.39191 | AP42: 203.08112 | AQ42: 153.35183 | AR42: 198.0271 | AS42: 209.76823 | AT42: 210.68777
B43: Inventory | C43: STOCKS | D43: =AESI_Live_Sheet!L_CURRENCY_ISSR_208021701_REP -> USD | F43: 11.058387 | G43: 14.359091 | H43: 23.380277 | I43: 37.342 | J43: 50.475576 | K43: 49.972685 | L43: 50.148797 | M43: 55.397488 | W43: 12.860898 | X43: 14.44792 | Y43: 16.394109 | Z43: 23.380277 | AA43: 22.886 | AB43: 26.654 | AC43: 34.752 | AD43: 37.342 | AE43: 52.619 | AF43: 63.361 | AG43: 57.952 | AH43: 50.475576 | AI43: 56.256646 | AJ43: 56.666909 | AK43: 54.290084 | AL43: 49.972685 | AM43: 49.175037 | AN43: 52.178083 | AO43: 52.692541 | AP43: 50.148797 | AQ43: 53.747608 | AR43: 55.116071 | AS43: 55.390459 | AT43: 55.397488
B44: Other current assets | C44: OTH_CUR_ASS | D44: =AESI_Live_Sheet!L_CURRENCY_ISSR_208021701_REP -> USD
B45: Total current assets | C45: CUR_ASS | D45: =AESI_Live_Sheet!L_CURRENCY_ISSR_208021701_REP -> USD | F45: 58.63956 | G45: 84.178116 | H45: 178.7316 | I45: 318.686 | J45: 272.49997 | K45: 349.56877 | L45: 583.72308 | M45: 792.28307 | W45: 99.844252 | X45: 157.48593 | Y45: 179.72567 | Z45: 178.7316 | AA45: 470.654 | AB45: 454.268 | AC45: 401.524 | AD45: 318.686 | AE45: 425.497 | AF45: 365.156 | AG45: 316.513 | AH45: 272.49997 | AI45: 274.99591 | AJ45: 294.05869 | AK45: 316.43394 | AL45: 349.56877 | AM45: 401.26463 | AN45: 459.50574 | AO45: 517.45001 | AP45: 583.72308 | AQ45: 579.79184 | AR45: 662.75759 | AS45: 704.47089 | AT45: 792.28307
B46: Gross fixed assets, PP&E | C46: GR_FIX_ASS | D46: =AESI_Live_Sheet!L_CURRENCY_ISSR_208021701_REP -> USD | F46: 25737.84 | G46: 25444.951 | H46: 25261.412 | I46: 25408.182 | J46: 25766.569 | K46: 25696.527 | L46: 25541.389 | M46: 25365.364 | W46: 25380.37 | X46: 25323.152 | Y46: 25292.876 | Z46: 25261.412 | AA46: 25258.66 | AB46: 25294.528 | AC46: 25362.253 | AD46: 25408.182 | AE46: 25708.095 | AF46: 25777.893 | AG46: 25778.988 | AH46: 25766.569 | AI46: 25736.26 | AJ46: 25712.786 | AK46: 25701.249 | AL46: 25696.527 | AM46: 25666.676 | AN46: 25629.401 | AO46: 25585.395 | AP46: 25541.389 | AQ46: 25497.383 | AR46: 25453.376 | AS46: 25409.37 | AT46: 25365.364
B47: Accumulated depreciation | C47: ACC_DDA | D47: =AESI_Live_Sheet!L_CURRENCY_ISSR_208021701_REP -> USD | F47: -25276.75 | G47: -24986.634 | H47: -24719.888 | I47: -24473.522 | J47: -24283.648 | K47: -24125.195 | L47: -23977.992 | M47: -23830.79 | W47: -24919.349 | X47: -24852.331 | Y47: -24785.661 | Z47: -24719.888 | AA47: -24656.696 | AB47: -24594.51 | AC47: -24533.256 | AD47: -24473.522 | AE47: -24420.59 | AF47: -24374.476 | AG47: -24329.448 | AH47: -24283.648 | AI47: -24237.847 | AJ47: -24200.296 | AK47: -24162.746 | AL47: -24125.195 | AM47: -24088.394 | AN47: -24051.594 | AO47: -24014.793 | AP47: -23977.992 | AQ47: -23941.192 | AR47: -23904.391 | AS47: -23867.59 | AT47: -23830.79
B48: Net PP&E | C48: NET_FIX_ASS | D48: =AESI_Live_Sheet!L_CURRENCY_ISSR_208021701_REP -> USD | F48: 461.08988 | G48: 458.31674 | H48: 541.5241 | I48: 934.66 | J48: 1482.9219 | K48: 1571.3321 | L48: 1563.3965 | M48: 1534.5742 | W48: 461.02157 | X48: 470.82171 | Y48: 507.21506 | Z48: 541.5241 | AA48: 601.964 | AB48: 700.018 | AC48: 828.997 | AD48: 934.66 | AE48: 1287.505 | AF48: 1403.417 | AG48: 1449.54 | AH48: 1482.9219 | AI48: 1498.4131 | AJ48: 1512.4902 | AK48: 1538.5038 | AL48: 1571.3321 | AM48: 1578.282 | AN48: 1577.8077 | AO48: 1570.6021 | AP48: 1563.3965 | AQ48: 1556.191 | AR48: 1548.9854 | AS48: 1541.7798 | AT48: 1534.5742
B49: Gross intangibles | C49: GR_INTANG | D49: =AESI_Live_Sheet!L_CURRENCY_ISSR_208021701_REP -> USD
B50: Accumulated amortization | C50: ACC_AMORT | D50: =AESI_Live_Sheet!L_CURRENCY_ISSR_208021701_REP -> USD
B51: Net intangible assets | C51: NET_INTANG | D51: =AESI_Live_Sheet!L_CURRENCY_ISSR_208021701_REP -> USD
B52: Equity method investments | C52: FIX_ASS_INV | D52: =AESI_Live_Sheet!L_CURRENCY_ISSR_208021701_REP -> USD
B53: Investments in securities | C53: INV_SECUR | D53: =AESI_Live_Sheet!L_CURRENCY_ISSR_208021701_REP -> USD
B54: Other long-term assets | C54: OTH_LT_ASS | D54: =AESI_Live_Sheet!L_CURRENCY_ISSR_208021701_REP -> USD | F54: 2.0129288 | G54: 1.2599388 | H54: 30.743889 | I54: 8.34 | J54: 22.937 | K54: 22.937 | L54: 22.937 | M54: 22.937 | W54: 11.267572 | X54: 11.52586 | Y54: 19.824797 | Z54: 30.743889 | AA54: 31.25 | AB54: 44.334 | AC54: 8.75 | AD54: 8.34 | AE54: 25.049 | AF54: 26.115 | AG54: 22.937 | AH54: 22.937 | AI54: 22.937 | AJ54: 22.937 | AK54: 22.937 | AL54: 22.937 | AM54: 22.937 | AN54: 22.937 | AO54: 22.937 | AP54: 22.937 | AQ54: 22.937 | AR54: 22.937 | AS54: 22.937 | AT54: 22.937
B55: Total assets | C55: TOT_ASSET | D55: =AESI_Live_Sheet!L_CURRENCY_ISSR_208021701_REP -> USD | F55: 521.74237 | G55: 543.75479 | H55: 750.99959 | I55: 1261.686 | J55: 1962.8589 | K55: 2128.3379 | L55: 2354.5566 | M55: 2534.2942 | W55: 572.13339 | X55: 639.8335 | Y55: 706.76553 | Z55: 750.99959 | AA55: 1103.868 | AB55: 1198.62 | AC55: 1239.271 | AD55: 1261.686 | AE55: 1941.684 | AF55: 1982.329 | AG55: 1973.49 | AH55: 1962.8589 | AI55: 1980.846 | AJ55: 2013.9859 | AK55: 2062.3748 | AL55: 2128.3379 | AM55: 2186.9837 | AN55: 2244.7505 | AO55: 2295.4892 | AP55: 2354.5566 | AQ55: 2343.4198 | AR55: 2419.1799 | AS55: 2453.6877 | AT55: 2534.2942
B56: Accounts payable | C56: ACC_PAY_GQ | D56: =AESI_Live_Sheet!L_CURRENCY_ISSR_208021701_REP -> USD | F56: 9.9828414 | G56: 21.547045 | H56: 62.620646 | I56: 92.592 | J56: 225.53849 | K56: 338.38137 | L56: 465.71033 | M56: 519.86993 | W56: 26.724534 | X56: 43.016331 | Y56: 60.389729 | Z56: 62.620646 | AA56: 79.128 | AB56: 111.462 | AC56: 100.559 | AD56: 92.592 | AE56: 165.996 | AF56: 208.78 | AG56: 221.953 | AH56: 225.53849 | AI56: 246.44104 | AJ56: 265.10883 | AK56: 294.09271 | AL56: 338.38137 | AM56: 375.41889 | AN56: 409.72646 | AO56: 434.45453 | AP56: 465.71033 | AQ56: 425.18563 | AR56: 470.2082 | AS56: 472.54907 | AT56: 519.86993
B57: Short-term debt | C57: SHORT_T_DEBT | D57: =AESI_Live_Sheet!L_CURRENCY_ISSR_208021701_REP -> USD
B58: Current lease liabilities (op lease: US GAAP) | C58: ST_LEASE_LIAB | D58: =AESI_Live_Sheet!L_CURRENCY_ISSR_208021701_REP -> USD
B59: Other current liabilities | C59: OTH_CUR_LIABS | D59: =AESI_Live_Sheet!L_CURRENCY_ISSR_208021701_REP -> USD | F59: 0.96980359 | G59: 2 | H59: 5.6634607 | I59: 0 | J59: 0 | K59: 0 | L59: 0 | M59: 0 | W59: 3.3485737 | X59: 10.703048 | Y59: 9.2147967 | Z59: 5.6634607 | AA59: 0 | AB59: 0 | AC59: 0 | AD59: 0 | AE59: 0 | AF59: 0 | AG59: 0 | AH59: 0 | AI59: 0 | AJ59: 0 | AK59: 0 | AL59: 0 | AM59: 0 | AN59: 0 | AO59: 0 | AP59: 0 | AQ59: 0 | AR59: 0 | AS59: 0 | AT59: 0
B60: Total current liabilities | C60: SHORT_TERM_LIABS | D60: =AESI_Live_Sheet!L_CURRENCY_ISSR_208021701_REP -> USD | F60: 10.952645 | G60: 23.547045 | H60: 68.284107 | I60: 92.592 | J60: 261.75749 | K60: 374.60037 | L60: 501.92933 | M60: 556.08893 | W60: 30.073108 | X60: 53.719379 | Y60: 69.604526 | Z60: 68.284107 | AA60: 104.23 | AB60: 141.208 | AC60: 100.559 | AD60: 92.592 | AE60: 190.125 | AF60: 239.333 | AG60: 258.172 | AH60: 261.75749 | AI60: 282.66004 | AJ60: 301.32783 | AK60: 330.31171 | AL60: 374.60037 | AM60: 411.63789 | AN60: 445.94546 | AO60: 470.67353 | AP60: 501.92933 | AQ60: 461.40463 | AR60: 506.4272 | AS60: 508.76807 | AT60: 556.08893
B61: Long-term debt | C61: LT_DEBT | D61: =AESI_Live_Sheet!L_CURRENCY_ISSR_208021701_REP -> USD | F61: 173.11224 | G61: 177.53899 | H61: 147.17383 | I61: 172.82 | J61: 431.043 | K61: 399.043 | L61: 367.043 | M61: 335.043 | W61: 173.7204 | X61: 164.827 | Y61: 156.98195 | Z61: 147.17383 | AA61: 114.018 | AB61: 101.201 | AC61: 172.511 | AD61: 172.82 | AE61: 457.17 | AF61: 447.45 | AG61: 439.043 | AH61: 431.043 | AI61: 423.043 | AJ61: 415.043 | AK61: 407.043 | AL61: 399.043 | AM61: 391.043 | AN61: 383.043 | AO61: 375.043 | AP61: 367.043 | AQ61: 359.043 | AR61: 351.043 | AS61: 343.043 | AT61: 335.043
B62: Non-current lease liabilities (op lease: US GAAP) | C62: LT_LEASE_LIAB | D62: =AESI_Live_Sheet!L_CURRENCY_ISSR_208021701_REP -> USD | F62: 0.45406749 | H62: 21.229012 | I62: 0 | W62: 4.4635244 | X62: 4.1674121 | Y62: 15.374806 | Z62: 21.229012 | AA62: 0 | AB62: 0 | AC62: 0 | AD62: 0 | AE62: 0
B63: Other long-term liabilities | C63: OTH_LT_CRED_GQ | D63: =AESI_Live_Sheet!L_CURRENCY_ISSR_208021701_REP -> USD | F63: 5.9834283 | G63: 3.3041172 | H63: 3.1529783 | I63: 6.921 | J63: 22.912 | K63: 22.912 | L63: 22.912 | M63: 22.912 | W63: 3.9623062 | X63: 3.7078709 | Y63: 1.1420248 | Z63: 3.1529783 | AA63: 27.733 | AB63: 38.012 | AC63: 6.363 | AD63: 6.921 | AE63: 28.53 | AF63: 26.559 | AG63: 22.912 | AH63: 22.912 | AI63: 22.912 | AJ63: 22.912 | AK63: 22.912 | AL63: 22.912 | AM63: 22.912 | AN63: 22.912 | AO63: 22.912 | AP63: 22.912 | AQ63: 22.912 | AR63: 22.912 | AS63: 22.912 | AT63: 22.912
B64: Total long-term liabilities | C64: TOT_LT_LIAB | D64: =AESI_Live_Sheet!L_CURRENCY_ISSR_208021701_REP -> USD | F64: 179.54974 | G64: 180.84311 | H64: 171.55582 | I64: 301.27 | J64: 661.137 | K64: 629.137 | L64: 597.137 | M64: 565.137 | W64: 182.14623 | X64: 172.70228 | Y64: 173.49878 | Z64: 171.55582 | AA64: 165.218 | AB64: 178.283 | AC64: 227.553 | AD64: 301.27 | AE64: 685.129 | AF64: 681.036 | AG64: 669.137 | AH64: 661.137 | AI64: 653.137 | AJ64: 645.137 | AK64: 637.137 | AL64: 629.137 | AM64: 621.137 | AN64: 613.137 | AO64: 605.137 | AP64: 597.137 | AQ64: 589.137 | AR64: 581.137 | AS64: 573.137 | AT64: 565.137
B65: Total liabilities | C65: TOT_LIAB | D65: =AESI_Live_Sheet!L_CURRENCY_ISSR_208021701_REP -> USD | F65: 190.50238 | G65: 204.39015 | H65: 239.83993 | I65: 393.862 | J65: 922.89449 | K65: 1003.7374 | L65: 1099.0663 | M65: 1121.2259 | W65: 212.21933 | X65: 226.42166 | Y65: 243.10331 | Z65: 239.83993 | AA65: 269.448 | AB65: 319.491 | AC65: 328.112 | AD65: 393.862 | AE65: 875.254 | AF65: 920.369 | AG65: 927.309 | AH65: 922.89449 | AI65: 935.79704 | AJ65: 946.46483 | AK65: 967.44871 | AL65: 1003.7374 | AM65: 1032.7749 | AN65: 1059.0825 | AO65: 1075.8105 | AP65: 1099.0663 | AQ65: 1050.5416 | AR65: 1087.5642 | AS65: 1081.9051 | AT65: 1121.2259
B66: Preferred shares | C66: PREF_SH | D66: =AESI_Live_Sheet!L_CURRENCY_ISSR_208021701_REP -> USD
B67: Total common equity | C67: ORD_SH_FUND | D67: =AESI_Live_Sheet!L_CURRENCY_ISSR_208021701_REP -> USD | F67: 331.69405 | G67: 339.36464 | H67: 511.15966 | I67: 867.824 | J67: 1039.9644 | K67: 1124.6005 | L67: 1255.4903 | M67: 1413.0683 | W67: 359.91406 | X67: 413.41184 | Y67: 463.66222 | Z67: 511.15966 | AA67: 56.465 | AB67: 76.686 | AC67: -75.992 | AD67: 867.824 | AE67: 1066.43 | AF67: 1061.96 | AG67: 1046.181 | AH67: 1039.9644 | AI67: 1045.049 | AJ67: 1067.521 | AK67: 1094.926 | AL67: 1124.6005 | AM67: 1154.2088 | AN67: 1185.668 | AO67: 1219.6786 | AP67: 1255.4903 | AQ67: 1292.8782 | AR67: 1331.6158 | AS67: 1371.7826 | AT67: 1413.0683
B68: Minority interest | C68: MINORITIES | D68: =AESI_Live_Sheet!L_CURRENCY_ISSR_208021701_REP -> USD | I68: 0 | J68: 0 | K68: 0 | L68: 0 | M68: 0 | AA68: 777.955 | AB68: 802.443 | AC68: 987.151 | AD68: 0 | AE68: 0 | AF68: 0 | AG68: 0 | AH68: 0 | AI68: 0 | AJ68: 0 | AK68: 0 | AL68: 0 | AM68: 0 | AN68: 0 | AO68: 0 | AP68: 0 | AQ68: 0 | AR68: 0 | AS68: 0 | AT68: 0
B69: Total shareholders' equity | C69: EQ | D69: =AESI_Live_Sheet!L_CURRENCY_ISSR_208021701_REP -> USD | F69: 331.69405 | G69: 339.36464 | H69: 511.15966 | I69: 867.824 | J69: 1039.9644 | K69: 1124.6005 | L69: 1255.4903 | M69: 1413.0683 | W69: 359.91406 | X69: 413.41184 | Y69: 463.66222 | Z69: 511.15966 | AA69: 834.42 | AB69: 879.129 | AC69: 911.159 | AD69: 867.824 | AE69: 1066.43 | AF69: 1061.96 | AG69: 1046.181 | AH69: 1039.9644 | AI69: 1045.049 | AJ69: 1067.521 | AK69: 1094.926 | AL69: 1124.6005 | AM69: 1154.2088 | AN69: 1185.668 | AO69: 1219.6786 | AP69: 1255.4903 | AQ69: 1292.8782 | AR69: 1331.6158 | AS69: 1371.7826 | AT69: 1413.0683
B70: Total liabilities and equity | C70: TOT_LIAB_EQ | D70: =AESI_Live_Sheet!L_CURRENCY_ISSR_208021701_REP -> USD | F70: 522.19643 | G70: 543.75479 | H70: 750.99959 | I70: 1261.686 | J70: 1962.8589 | K70: 2128.3379 | L70: 2354.5566 | M70: 2534.2942 | W70: 572.13339 | X70: 639.8335 | Y70: 706.76553 | Z70: 750.99959 | AA70: 1103.868 | AB70: 1198.62 | AC70: 1239.271 | AD70: 1261.686 | AE70: 1941.684 | AF70: 1982.329 | AG70: 1973.49 | AH70: 1962.8589 | AI70: 1980.846 | AJ70: 2013.9859 | AK70: 2062.3748 | AL70: 2128.3379 | AM70: 2186.9837 | AN70: 2244.7505 | AO70: 2295.4892 | AP70: 2354.5566 | AQ70: 2343.4198 | AR70: 2419.1799 | AS70: 2453.6877 | AT70: 2534.2942
A71: Additional Balance Sheet Items
B72: Total US$ debt (in US$) | C72: TOT_USD_DEBT
B73: % US$ debt hedged (principal) | C73: TOT_PCT_USD_DEBT_HEDGED
B74: % Floating debt (local currency debt) | C74: FLOATING_PCT_LOCAL_DEBT
B75: % floating debt hedged (rates) | C75: FLOATING_PCT_LOCAL_DEBT_HEDGED
B76: Net debt | C76: NET_DEBT | D76: =AESI_Live_Sheet!L_CURRENCY_ISSR_208021701_REP -> USD | F76: 137.49384 | G76: 137.13801 | H76: 86.392805 | I76: -37.354 | J76: 413.47089 | K76: 272.3144 | L76: 72.768831 | M76: -154.93582 | W76: 124.34754 | X76: 99.985081 | Y76: 81.637139 | Z76: 86.392805 | AA76: -213.536 | AB76: -210.727 | AC76: -92.027 | AD76: -37.354 | AE76: 294.179 | AF76: 373.28 | AG76: 396.625 | AH76: 413.47089 | AI76: 439.57786 | AJ76: 423.33438 | AK76: 341.25243 | AL76: 272.3144 | AM76: 242.68315 | AN76: 188.73165 | AO76: 147.89644 | AP76: 72.768831 | AQ76: 22.569594 | AR76: -22.352422 | AS76: -60.050195 | AT76: -154.93582
B77: Capitalized operating leases (off-balance sheet) | C77: CAP_LEASES | D77: =AESI_Live_Sheet!L_CURRENCY_ISSR_208021701_REP -> USD
B78: Deferred income taxes | C78: DEF_INC_TAX | D78: =AESI_Live_Sheet!L_CURRENCY_ISSR_208021701_REP -> USD
B79: Net operating loss carryforwards (NOLs) | C79: NET_OP_LOSS_CFWD | D79: =AESI_Live_Sheet!L_CURRENCY_ISSR_208021701_REP -> USD
B80: Associates (mkt value) used in EV calculation | C80: MV_ASSOCIATES | D80: =AESI_Live_Sheet!L_CURRENCY_ISSR_208021701_REP -> USD
B81: Net debt adjustment | C81: NET_DEBT_ADJ | D81: =AESI_Live_Sheet!L_CURRENCY_ISSR_208021701_REP -> USD
B82: Company borrowing margin | C82: CO_BOR_MARGIN
B83: Unfunded pensions & other provisions | C83: UNF_PENS | D83: =AESI_Live_Sheet!L_CURRENCY_ISSR_208021701_REP -> USD
B84: Unfunded pension liabilities (off balance sheet) | C84: UNF_PENS_OFF | D84: =AESI_Live_Sheet!L_CURRENCY_ISSR_208021701_REP -> USD
B85: Unfunded pension liabilities & other, used in EV | C85: UNF_PENS_LIAB_OTH | D85: =AESI_Live_Sheet!L_CURRENCY_ISSR_208021701_REP -> USD
B86: Adjustment for unfunded pensions & goodwill | C86: ADJ_UNF_PENS_GOOD | D86: =AESI_Live_Sheet!L_CURRENCY_ISSR_208021701_REP -> USD
B87: Other GCI adjustments | C87: OTH_GCI_ADJ | D87: =AESI_Live_Sheet!L_CURRENCY_ISSR_208021701_REP -> USD
B88: GCI inflator | C88: GCI_INFL
B89: Minority interest | C89: BAL_MINO_INT | D89: =AESI_Live_Sheet!L_CURRENCY_ISSR_208021701_REP -> USD
B90: Right-of-use assets (op lease assets under US GAAP) | C90: ROU_ASSET | D90: =AESI_Live_Sheet!L_CURRENCY_ISSR_208021701_REP -> USD
A91: Cash Flow Statement
B92: Minority interest add-back | C92: CF_INC_MINORITY | D92: =AESI_Live_Sheet!L_CURRENCY_ISSR_208021701_REP -> USD
B93: Depreciation & amortization add-back | C93: DEPR_AMORT | D93: =AESI_Live_Sheet!L_CURRENCY_ISSR_208021701_REP -> USD | F93: 21.516694 | G93: 24.540894 | H93: 28.25379 | I93: 41.634 | J93: 98.125345 | K93: 104.79738 | L93: 104.79738 | M93: 104.79738 | W93: 6.4644721 | X93: 6.7318501 | Y93: 7.0806603 | Z93: 7.976807 | AA93: 8.808 | AB93: 9.814 | AC93: 10.746 | AD93: 12.266 | AE93: 19.068 | AF93: 25.886 | AG93: 26.972 | AH93: 26.199345 | AI93: 26.199345 | AJ93: 26.199345 | AK93: 26.199345 | AL93: 26.199345 | AM93: 26.199345 | AN93: 26.199345 | AO93: 26.199345 | AP93: 26.199345 | AQ93: 26.199345 | AR93: 26.199345 | AS93: 26.199345 | AT93: 26.199345
B94: (Increase)/decrease in working capital | C94: WORK_CAP | D94: =AESI_Live_Sheet!L_CURRENCY_ISSR_208021701_REP -> USD | F94: -1.262 | G94: -6.1381909 | H94: -43.568843 | I94: -6.947 | J94: 46.115625 | K94: 144.93058 | L94: 60.720214 | M94: 41.30426 | W94: -3.105 | X94: -26.476335 | Y94: 8.0453098 | Z94: -22.032818 | AA94: -22.319 | AB94: 15.212 | AC94: -22.781 | AD94: 22.941 | AE94: -18.5 | AF94: 6.586 | AG94: 35.277 | AH94: 22.752625 | AI94: -15.700344 | AJ94: 7.8484796 | AK94: 80.690587 | AL94: 72.091859 | AM94: 6.9729101 | AN94: 22.017958 | AO94: -0.38099621 | AP94: 32.110342 | AQ94: 5.60577 | AR94: -1.0211624 | AS94: -9.6746547 | AT94: 46.394307
B95: Other operating cash flow items | C95: OTH_OP_CF | D95: =AESI_Live_Sheet!L_CURRENCY_ISSR_208021701_REP -> USD | F95: 26.675736 | G95: 20.1 | H95: 3.6661641 | I95: 30.442 | J95: 28.815 | W95: -0.73 | X95: 2.795 | Y95: 0.67168326 | Z95: 0.92948084 | AA95: 4.219 | AB95: 6.022 | AC95: 9.7 | AD95: 10.501 | AE95: 8.001 | AF95: 8.081 | AG95: 12.733
B96: Cash flow from operating activities | C96: CF_OPS | D96: =AESI_Live_Sheet!L_CURRENCY_ISSR_208021701_REP -> USD | F96: 12.486 | G96: 43.430616 | H96: 205.84186 | I96: 299.031 | J96: 255.00108 | K96: 446.3307 | L96: 413.97235 | M96: 427.12286 | W96: 23.679829 | X96: 51.77694 | Y96: 80.877322 | Z96: 49.507772 | AA96: 54.235 | AB96: 103.883 | AC96: 55.406 | AD96: 85.507 | AE96: 39.562 | AF96: 60.856 | AG96: 85.189 | AH96: 69.394079 | AI96: 43.575226 | AJ96: 84.511568 | AK96: 162.28659 | AL96: 155.95731 | AM96: 92.171773 | AN96: 109.06778 | AO96: 89.220195 | AP96: 123.5126 | AQ96: 100.05379 | AR96: 94.776568 | AS96: 87.552323 | AT96: 144.74018
B97: Capital expenditures, Capex | C97: CAPEX | D97: =AESI_Live_Sheet!L_CURRENCY_ISSR_208021701_REP -> USD | F97: -9.532 | G97: -19.356 | H97: -89.591968 | I97: -365.486 | J97: -357.13325 | K97: -193.20758 | L97: -96.861822 | M97: -75.975 | W97: -6.0347149 | X97: -12.393604 | Y97: -36.202858 | Z97: -34.960791 | AA97: -60.94 | AB97: -85.895 | AC97: -98.858 | AD97: -119.793 | AE97: -95.486 | AF97: -115.79 | AG97: -86.276 | AH97: -59.58125 | AI97: -41.690538 | AJ97: -40.276435 | AK97: -52.212982 | AL97: -59.027627 | AM97: -33.149285 | AN97: -25.725037 | AO97: -18.99375 | AP97: -18.99375 | AQ97: -18.99375 | AR97: -18.99375 | AS97: -18.99375 | AT97: -18.99375
B98: Acquisitions | C98: ACQ | D98: =AESI_Live_Sheet!L_CURRENCY_ISSR_208021701_REP -> USD
B99: Divestitures | C99: DIVEST | D99: =AESI_Live_Sheet!L_CURRENCY_ISSR_208021701_REP -> USD
B100: Other investing cash flow items | C100: OTH_INV_CF | D100: =AESI_Live_Sheet!L_CURRENCY_ISSR_208021701_REP -> USD
...

Sheet AESI_Validation_Sheet
A1: d50ffbf1-b4f1-40f2-ab05-0ee809f33152
A2: =CELL("filename",AESI_Validation_Sheet!$A2) -> H:\[testModel.xlsx]AESI_Validation_Sheet
A3: =_xll.Exchange.Rtd.QVS(AESI_Validation_Sheet!$A1,AESI_Validation_Sheet!$A2,#REF!,AESI_Annotation_Sheet!B2:AT315,AESI_Live_Sheet!B2:AT315) -> #NAME?
A7: Scalar|||208021701|||ISSR|||CURRENCY_ISO|||False||| | C7: V_KEYWORD_ISSR_208021701_CURRENCY_ISO
A9: Scalar|||208021701|||ISSR|||MA_PROB|||False||| | C9: V_KEYWORD_ISSR_208021701_MA_PROB
A11: Vector|||208021701|||ISSR|||SALES|||False||| | C11: V_KEYWORD_ISSR_208021701_SALES
A12: Vector|||208021701|||ISSR|||COST_GD_SD|||False||| | C12: V_KEYWORD_ISSR_208021701_COST_GD_SD
A13: Vector|||208021701|||ISSR|||SEL_GL_AD|||False||| | C13: V_KEYWORD_ISSR_208021701_SEL_GL_AD
A14: Vector|||208021701|||ISSR|||OP_COST|||False||| | C14: V_KEYWORD_ISSR_208021701_OP_COST
A15: Vector|||208021701|||ISSR|||RD_EXP|||False||| | C15: V_KEYWORD_ISSR_208021701_RD_EXP
A16: Vector|||208021701|||ISSR|||ESO_PRE_TAX|||False||| | C16: V_KEYWORD_ISSR_208021701_ESO_PRE_TAX
A17: Vector|||208021701|||ISSR|||OTH_OP_INC_EXP|||False||| | C17: V_KEYWORD_ISSR_208021701_OTH_OP_INC_EXP
A18: Vector|||208021701|||ISSR|||TOT_OPS_EXP_DDA|||False||| | C18: V_KEYWORD_ISSR_208021701_TOT_OPS_EXP_DDA
A19: Vector|||208021701|||ISSR|||TOT_OPS_EXP|||False||| | C19: V_KEYWORD_ISSR_208021701_TOT_OPS_EXP
A20: Vector|||208021701|||ISSR|||EBITDA_CALC|||False||| | C20: V_KEYWORD_ISSR_208021701_EBITDA_CALC
... A315: Scalar|||200022132|||EQTY|||RISK_FR_RATE|||False||| | C315: V_KEYWORD_EQTY_200022132_RISK_FR_RATE

Sheet AESI_Annotation_Sheet
A1: Issuer: Atlas Energy Solutions | F1: 2020 | G1: 2021 | H1: 2022 | I1: 2023 | J1: 2024 | K1: 2025 | L1: 2026 | M1: 2027 | O1: 2020 Q1 | P1: 2020 Q2 | Q1: 2020 Q3 | R1: 2020 Q4 | S1: 2021 Q1 | T1: 2021 Q2 | U1: 2021 Q3 | V1: 2021 Q4 | W1: 2022 Q1 | X1: 2022 Q2 | Y1: 2022 Q3 | Z1: 2022 Q4 | AA1: 2023 Q1 | AB1: 2023 Q2 | AC1: 2023 Q3 | AD1: 2023 Q4 | AE1: 2024 Q1 | AF1: 2024 Q2 | AG1: 2024 Q3 | AH1: 2024 Q4 | AI1: 2025 Q1 | AJ1: 2025 Q2 | AK1: 2025 Q3 | AL1: 2025 Q4 | AM1: 2026 Q1 | AN1: 2026 Q2 | AO1: 2026 Q3 | AP1: 2026 Q4 | AQ1: 2027 Q1 | AR1: 2027 Q2 | AS1: 2027 Q3 | AT1: 2027 Q4
A4: Issuer: Atlas Energy Solutions
A5: Reference Data
B6: Issuer Name | C6: Issuer Name | E6: Atlas Energy Solutions
B7: Reporting Currency | C7: CURRENCY_ISO | E7: USD
A8: General Information
B9: M&A probability (1 = high, 3 = low) | C9: MA_PROB
A10: Income Statement
B11: Sales, net revenue | C11: SALES | D11: =E_CURRENCY_ISSR_208021701_REP -> #NAME?
B12: Cost of goods sold, COGS | C12: COST_GD_SD | D12: =E_CURRENCY_ISSR_208021701_REP -> #NAME?
B13: SG&A, selling, general and admin. expense | C13: SEL_GL_AD | D13: =E_CURRENCY_ISSR_208021701_REP -> #NAME?
B14: Total operating expense | C14: OP_COST | D14: =E_CURRENCY_ISSR_208021701_REP -> #NAME?
B15: R&D expense | C15: RD_EXP | D15: =E_CURRENCY_ISSR_208021701_REP -> #NAME?
B16: ESO expense (pre-tax) | C16: ESO_PRE_TAX | D16: =E_CURRENCY_ISSR_208021701_REP -> #NAME?
B17: Other operating income/(expense) (incl. leases) | C17: OTH_OP_INC_EXP | D17: =E_CURRENCY_ISSR_208021701_REP -> #NAME?
B18: Total operating expense (incl. D&A) | C18: TOT_OPS_EXP_DDA | D18: =E_CURRENCY_ISSR_208021701_REP -> #NAME?
B19: Total operating expense (excl. D&A) | C19: TOT_OPS_EXP | D19: =E_CURRENCY_ISSR_208021701_REP -> #NAME?
B20: EBITDA | C20: EBITDA_CALC | D20: =E_CURRENCY_ISSR_208021701_REP -> #NAME?
B21: Depreciation | C21: DEPREC | D21: =E_CURRENCY_ISSR_208021701_REP -> #NAME?
B22: Amortization | C22: GOODWILL_AMORT | D22: =E_CURRENCY_ISSR_208021701_REP -> #NAME?
... B30: Pre-tax profit | C30: PT_PROF | D30: =E_CURRENCY_ISSR_208021701_REP -> #NAME?
A31: Additional Income Statement Items
B32: Operating lease cost | C32: LEASE_PAY | D32: =E_CURRENCY_ISSR_208021701_REP -> #NAME?
B33: Lease payments (deemed interest portion) | C33: LEASE_DEEM_INT | D33: =E_CURRENCY_ISSR_208021701_REP -> #NAME?
B34: Lease payments (deemed depreciation portion) | C34: LEASE_DEEM_DEPR | D34: =E_CURRENCY_ISSR_208021701_REP -> #NAME?
B35: Gross interest charge | C35: NET_INT_CH | D35: =E_CURRENCY_ISSR_208021701_REP -> #NAME?
B36: Income from associates (operating) | C36: ASSOCIATE_OP | D36: =E_CURRENCY_ISSR_208021701_REP -> #NAME?
B37: Depreciation ROU assets (applicable to IFRS cos.) | C37: DEPR_ROU_ASSETS | D37: =E_CURRENCY_ISSR_208021701_REP -> #NAME?
B38: Lease interest charge (applicable to IFRS cos.) | C38: LEASE_INT_CHG | D38: =E_CURRENCY_ISSR_208021701_REP -> #NAME?
B39: Lease standard adopted (US GAAP ASC 842/ IFRS 16) | C39: LEASE_ADOPT
A40: Balance Sheet
B41: Cash & cash equivalents | C41: CASH_EQ | D41: =E_CURRENCY_ISSR_208021701_REP -> #NAME?
B42: Accounts receivable | C42: DEBTORS | D42: =E_CURRENCY_ISSR_208021701_REP -> #NAME?
B43: Inventory | C43: STOCKS | D43: =E_CURRENCY_ISSR_208021701_REP -> #NAME?
B44: Other current assets | C44: OTH_CUR_ASS | D44: =E_CURRENCY_ISSR_208021701_REP -> #NAME?
B45: Total current assets | C45: CUR_ASS | D45: =E_CURRENCY_ISSR_208021701_REP -> #NAME?
B46: Gross fixed assets, PP&E | C46: GR_FIX_ASS | D46: =E_CURRENCY_ISSR_208021701_REP -> #NAME?
B47: Accumulated depreciation | C47: ACC_DDA | D47: =E_CURRENCY_ISSR_208021701_REP -> #NAME?
B48: Net PP&E | C48: NET_FIX_ASS | D48: =E_CURRENCY_ISSR_208021701_REP -> #NAME?
B49: Gross intangibles | C49: GR_INTANG | D49: =E_CURRENCY_ISSR_208021701_REP -> #NAME?
B50: Accumulated amortization | C50: ACC_AMORT | D50: =E_CURRENCY_ISSR_208021701_REP -> #NAME?
B51: Net intangible assets | C51: NET_INTANG | D51: =E_CURRENCY_ISSR_208021701_REP -> #NAME?
B52: Equity method investments | C52: FIX_ASS_INV | D52: =E_CURRENCY_ISSR_208021701_REP -> #NAME?
... B70: Total liabilities and equity | C70: TOT_LIAB_EQ | D70: =E_CURRENCY_ISSR_208021701_REP -> #NAME?
A71: Additional Balance Sheet Items
B72: Total US$ debt (in US$) | C72: TOT_USD_DEBT
B73: % US$ debt hedged (principal) | C73: TOT_PCT_USD_DEBT_HEDGED
B74: % Floating debt (local currency debt) | C74: FLOATING_PCT_LOCAL_DEBT
B75: % floating debt hedged (rates) | C75: FLOATING_PCT_LOCAL_DEBT_HEDGED
B76: Net debt | C76: NET_DEBT | D76: =E_CURRENCY_ISSR_208021701_REP -> #NAME?
B77: Capitalized operating leases (off-balance sheet) | C77: CAP_LEASES | D77: =E_CURRENCY_ISSR_208021701_REP -> #NAME?
B78: Deferred income taxes | C78: DEF_INC_TAX | D78: =E_CURRENCY_ISSR_208021701_REP -> #NAME?
B79: Net operating loss carryforwards (NOLs) | C79: NET_OP_LOSS_CFWD | D79: =E_CURRENCY_ISSR_208021701_REP -> #NAME?
B80: Associates (mkt value) used in EV calculation | C80: MV_ASSOCIATES | D80: =E_CURRENCY_ISSR_208021701_REP -> #NAME?
B81: Net debt adjustment | C81: NET_DEBT_ADJ | D81: =E_CURRENCY_ISSR_208021701_REP -> #NAME?
B82: Company borrowing margin | C82: CO_BOR_MARGIN
B83: Unfunded pensions & other provisions | C83: UNF_PENS | D83: =E_CURRENCY_ISSR_208021701_REP -> #NAME?
B84: Unfunded pension liabilities (off balance sheet) | C84: UNF_PENS_OFF | D84: =E_CURRENCY_ISSR_208021701_REP -> #NAME?
B85: Unfunded pension liabilities & other, used in EV | C85: UNF_PENS_LIAB_OTH | D85: =E_CURRENCY_ISSR_208021701_REP -> #NAME?
B86: Adjustment for unfunded pensions & goodwill | C86: ADJ_UNF_PENS_GOOD | D86: =E_CURRENCY_ISSR_208021701_REP -> #NAME?
B87: Other GCI adjustments | C87: OTH_GCI_ADJ | D87: =E_CURRENCY_ISSR_208021701_REP -> #NAME?
B88: GCI inflator | C88: GCI_INFL
B89: Minority interest | C89: BAL_MINO_INT | D89: =E_CURRENCY_ISSR_208021701_REP -> #NAME?
B90: Right-of-use assets (op lease assets under US GAAP) | C90: ROU_ASSET | D90: =E_CURRENCY_ISSR_208021701_REP -> #NAME?
A91: Cash Flow Statement
B92: Minority interest add-back | C92: CF_INC_MINORITY | D92: =E_CURRENCY_ISSR_208021701_REP -> #NAME?
B93: Depreciation & amortization add-back | C93: DEPR_AMORT | D93: =E_CURRENCY_ISSR_208021701_REP -> #NAME?
B94: (Increase)/decrease in working capital | C94: WORK_CAP | D94: =E_CURRENCY_ISSR_208021701_REP -> #NAME?
B95: Other operating cash flow items | C95: OTH_OP_CF | D95: =E_CURRENCY_ISSR_208021701_REP -> #NAME?
B96: Cash flow from operating activities | C96: CF_OPS | D96: =E_CURRENCY_ISSR_208021701_REP -> #NAME?
B97: Capital expenditures, Capex | C97: CAPEX | D97: =E_CURRENCY_ISSR_208021701_REP -> #NAME?
B98: Acquisitions | C98: ACQ | D98: =E_CURRENCY_ISSR_208021701_REP -> #NAME?
B99: Divestitures | C99: DIVEST | D99: =E_CURRENCY_ISSR_208021701_REP -> #NAME?
B100: Other investing cash flow items | C100: OTH_INV_CF | D100: =E_CURRENCY_ISSR_208021701_REP -> #NAME?
B101: Cash flow from investing | C101: CF_INV | D101: =E_CURRENCY_ISSR_208021701_REP -> #NAME?
B102: Dividends paid | C102: DIV_PAID | D102: =E_CURRENCY_ISSR_208021701_REP -> #NAME?
B103: Common stock issuance/(repurchase) | C103: SH_REPUR | D103: =E_CURRENCY_ISSR_208021701_REP -> #NAME?
... B108: Total cash flow | C108: TOT_CF | D108: =E_CURRENCY_ISSR_208021701_REP -> #NAME?
A109: Additional Cash Flow Items
B110: Associate and JV add-back | C110: ASSOC_JV_ADDBK | D110: =E_CURRENCY_ISSR_208021701_REP -> #NAME?
B111: Profit/(loss) on sale of assets | C111: PL_SALE_ASSETS | D111: =E_CURRENCY_ISSR_208021701_REP -> #NAME?
B112: Other non-cash adjustments | C112: OTH_NONCASH_ADJ | D112: =E_CURRENCY_ISSR_208021701_REP -> #NAME?
B113: Other DACF adjustments | C113: OTH_DACF_ADJ | D113: =E_CURRENCY_ISSR_208021701_REP -> #NAME?
B114: Change in LT deferred income taxes (Cash flow) | C114: CHG_DEF_TAX_CF | D114: =E_CURRENCY_ISSR_208021701_REP -> #NAME?
B115: Other items/adjustments for computing cash tax rate (except def taxes) | C115: OTH_ADJ_CASH_TAX | D115: =E_CURRENCY_ISSR_208021701_REP -> #NAME?
B116: Cash interest expense | C116: CASH_INT_EXP | D116: =E_CURRENCY_ISSR_208021701_REP -> #NAME?
B117: Cash tax expense | C117: CASH_TAX_EXP | D117: =E_CURRENCY_ISSR_208021701_REP -> #NAME?
B118: Dividends received from associates/JVs | C118: DIVDS_ASSOC_JV | D118: =E_CURRENCY_ISSR_208021701_REP -> #NAME?
B119: Capex maintenance | C119: CAPEX_MAINTENANCE | D119: =E_CURRENCY_ISSR_208021701_REP -> #NAME?
B120: Capex expansion | C120: CAPEX_EXPANSION | D120: =E_CURRENCY_ISSR_208021701_REP -> #NAME?
B121: Non-PP&E capex | C121: NONPPE_CAPEX | D121: =E_CURRENCY_ISSR_208021701_REP -> #NAME?
B122: Dividends paid to minorities | C122: DIVDS_PD_MINORITIES | D122: =E_CURRENCY_ISSR_208021701_REP -> #NAME?
A123: Other Items
B124: Number of employees | C124: EMPLOYEES
B125: NGL production (000s bbl/day) | C125: NGL_PROD
B126: Condensate production (000s bbl/day) | C126: COND_PROD
A127: Operating Metrics
B128: Order backlog | C128: ORDER_BACKLOG | D128: =E_CURRENCY_ISSR_208021701_REP -> #NAME?
B129: Order intake | C129: ORDER_INTAKE | D129: =E_CURRENCY_ISSR_208021701_REP -> #NAME?
B130: Average age of drilling fleet | C130: AVG_DRILL_FLEET_AGE
...

Sheet Income Statement
A2: x | B2: Atlas Energy Solutions Limited
B3: Income Statement
B4: (US$ Millions)
C5: =VALUE(LEFT(C6,4)) -> 2005 | D5: =VALUE(LEFT(C6,4)) -> 2005 | E5: =VALUE(LEFT(C6,4)) -> 2005 | F5: =VALUE(LEFT(C6,4)) -> 2005 | G5: =VALUE(LEFT(G6,4)) -> 2006 | H5: =VALUE(LEFT(G6,4)) -> 2006 | I5: =VALUE(LEFT(G6,4)) -> 2006 | J5: =VALUE(LEFT(G6,4)) -> 2006 | K5: =VALUE(LEFT(K6,4)) -> 2007 | L5: =VALUE(LEFT(K6,4)) -> 2007 | M5: =VALUE(LEFT(K6,4)) -> 2007 | N5: =VALUE(LEFT(K6,4)) -> 2007 | O5: =VALUE(LEFT(O6,4)) -> 2008 | P5: =VALUE(LEFT(O6,4)) -> 2008 | Q5: =VALUE(LEFT(O6,4)) -> 2008 | R5: =VALUE(LEFT(O6,4)) -> 2008 | S5: =VALUE(LEFT(S6,4)) -> 2009 | T5: =VALUE(LEFT(S6,4)) -> 2009 | U5: =VALUE(LEFT(S6,4)) -> 2009 | V5: =VALUE(LEFT(S6,4)) -> 2009 | W5: =VALUE(LEFT(W6,4)) -> 2010 | X5: =VALUE(LEFT(W6,4)) -> 2010 | Y5: =VALUE(LEFT(W6,4)) -> 2010 | Z5: =VALUE(LEFT(W6,4)) -> 2010 | AA5: =VALUE(LEFT(AA6,4)) -> 2011 | AB5: =VALUE(LEFT(AA6,4)) -> 2011 | AC5: =VALUE(LEFT(AA6,4)) -> 2011 | AD5: =VALUE(LEFT(AA6,4)) -> 2011 | AE5: =VALUE(LEFT(AE6,4)) -> 2012 | AF5: =VALUE(LEFT(AE6,4)) -> 2012 | AG5: =VALUE(LEFT(AE6,4)) -> 2012 | AH5: =VALUE(LEFT(AE6,4)) -> 2012 | AI5: =VALUE(LEFT(AI6,4)) -> 2013 | AJ5: =VALUE(LEFT(AI6,4)) -> 2013 | AK5: =VALUE(LEFT(AI6,4)) -> 2013 | AL5: =VALUE(LEFT(AI6,4)) -> 2013 | AM5: =VALUE(LEFT(AM6,4)) -> 2014 | AN5: =VALUE(LEFT(AM6,4)) -> 2014 | AO5: =VALUE(LEFT(AM6,4)) -> 2014 | AP5: =VALUE(LEFT(AM6,4)) -> 2014 | AQ5: =VALUE(LEFT(AQ6,4)) -> 2015 | AR5: =VALUE(LEFT(AQ6,4)) -> 2015 | AS5: =VALUE(LEFT(AQ6,4)) -> 2015 | AT5: =VALUE(LEFT(AQ6,4)) -> 2015 | AU5: =VALUE(LEFT(AU6,4)) -> 2016 | AV5: =VALUE(LEFT(AU6,4)) -> 2016 | AW5: =VALUE(LEFT(AU6,4)) -> 2016 | AX5: =VALUE(LEFT(AU6,4)) -> 2016 | AY5: =VALUE(LEFT(AY6,4)) -> 2017 | AZ5: =VALUE(LEFT(AY6,4)) -> 2017 | BA5: =VALUE(LEFT(AY6,4)) -> 2017 | BB5: =VALUE(LEFT(AY6,4)) -> 2017 | BC5: =VALUE(LEFT(BC6,4)) -> 2018 | BD5: =VALUE(LEFT(BC6,4)) -> 2018 | BE5: =VALUE(LEFT(BC6,4)) -> 2018 | BF5: =VALUE(LEFT(BC6,4)) -> 2018 | BG5: =VALUE(LEFT(BG6,4)) -> 2019 | BH5: =VALUE(LEFT(BG6,4)) -> 2019 | BI5: =VALUE(LEFT(BG6,4)) -> 2019 | BJ5: =VALUE(LEFT(BG6,4)) -> 2019 | BK5: =VALUE(LEFT(BK6,4)) -> 2020 | BL5: =VALUE(LEFT(BK6,4)) -> 2020 | BM5: =VALUE(LEFT(BK6,4)) -> 2020 | BN5: =VALUE(LEFT(BK6,4)) -> 2020 | BO5: =VALUE(LEFT(BO6,4)) -> 2021 | BP5: =VALUE(LEFT(BO6,4)) -> 2021 | BQ5: =VALUE(LEFT(BO6,4)) -> 2021 | BR5: =VALUE(LEFT(BO6,4)) -> 2021 | BS5: =VALUE(LEFT(BS6,4)) -> 2022 | BT5: =VALUE(LEFT(BS6,4)) -> 2022 | BU5: =VALUE(LEFT(BS6,4)) -> 2022 | BV5: =VALUE(LEFT(BS6,4)) -> 2022 | BW5: =VALUE(LEFT(BW6,4)) -> 2023 | BX5: =VALUE(LEFT(BW6,4)) -> 2023 | BY5: =VALUE(LEFT(BW6,4)) -> 2023 | BZ5: =VALUE(LEFT(BW6,4)) -> 2023 | CA5: =VALUE(LEFT(CA6,4)) -> 2024 | CB5: =VALUE(LEFT(CA6,4)) -> 2024 | CC5: =VALUE(LEFT(CA6,4)) -> 2024 | CD5: =VALUE(LEFT(CA6,4)) -> 2024 | CE5: =VALUE(LEFT(CE6,4)) -> 2025 | CF5: =VALUE(LEFT(CE6,4)) -> 2025 | CG5: =VALUE(LEFT(CE6,4)) -> 2025 | CH5: =VALUE(LEFT(CE6,4)) -> 2025 | CI5: =VALUE(LEFT(CI6,4)) -> 2026 | CJ5: =VALUE(LEFT(CI6,4)) -> 2026 | CK5: =VALUE(LEFT(CI6,4)) -> 2026 | CL5: =VALUE(LEFT(CI6,4)) -> 2026 | CM5: =VALUE(LEFT(CM6,4)) -> 2027 | CN5: =VALUE(LEFT(CM6,4)) -> 2027 | CO5: =VALUE(LEFT(CM6,4)) -> 2027 | CP5: =VALUE(LEFT(CM6,4)) -> 2027 | CQ5: =VALUE(LEFT(CQ6,4)) -> 2028 | CR5: =VALUE(LEFT(CQ6,4)) -> 2028 | CS5: =VALUE(LEFT(CQ6,4)) -> 2028 | CT5: =VALUE(LEFT(CQ6,4)) -> 2028 | CU5: =VALUE(LEFT(CU6,4)) -> 2029 | CV5: =VALUE(LEFT(CU6,4)) -> 2029 | CW5: =VALUE(LEFT(CU6,4)) -> 2029 | CX5: =VALUE(LEFT(CU6,4)) -> 2029 | CY5: =VALUE(LEFT(CY6,4)) -> 2030 | CZ5: =VALUE(LEFT(CY6,4)) -> 2030 | DA5: =VALUE(LEFT(CY6,4)) -> 2030 | DB5: =VALUE(LEFT(CY6,4)) -> 2030 | DF5: =VALUE(LEFT(DF7,4)) -> 2005 | DG5: =VALUE(LEFT(DG7,4)) -> 2006 | DH5: =VALUE(LEFT(DH7,4)) -> 2007 | DI5: =VALUE(LEFT(DI7,4)) -> 2008 | DJ5: =VALUE(LEFT(DJ7,4)) -> 2009 | DK5: =VALUE(LEFT(DK7,4)) -> 2010 | DL5: =VALUE(LEFT(DL7,4)) -> 2011 | DM5: =VALUE(LEFT(DM7,4)) -> 2012 | ... EE5: =VALUE(LEFT(EE7,4)) -> 2030
C6: 2005 | G6: 2006 | K6: 2007 | O6: 2008 | S6: 2009 | W6: 2010 | AA6: 2011 | AE6: 2012 | AI6: 2013 | AM6: 2014 | AQ6: 2015 | AU6: 2016 | AY6: 2017 | BC6: 2018 | BG6: =BC6+1 -> 2019 | BK6: =BG6+1 -> 2020 | BO6: =BK6+1 -> 2021 | BS6: =BO6+1 -> 2022 | BW6: =BS6+1 -> 2023 | CA6: =BW6+1 -> 2024 | CE6: =CA6+1 -> 2025 | CI6: =CE6+1 -> 2026 | CM6: =CI6+1 -> 2027 | CQ6: =CM6+1 -> 2028 | CU6: =CQ6+1 -> 2029 | CY6: =CU6+1 -> 2030 | DE6: Income Statement (Full year ending Dec 31)
C7: ="1Q"&RIGHT(C6,2) -> 1Q05 | D7: ="2Q"&RIGHT(C6,2) -> 2Q05 | E7: ="3Q"&RIGHT(C6,2) -> 3Q05 | F7: ="4Q"&RIGHT(C6,2) -> 4Q05 | G7: ="1Q"&RIGHT(G6,2) -> 1Q06 | H7: ="2Q"&RIGHT(G6,2) -> 2Q06 | I7: ="3Q"&RIGHT(G6,2) -> 3Q06 | J7: ="4Q"&RIGHT(G6,2) -> 4Q06 | K7: ="1Q"&RIGHT(K6,2) -> 1Q07 | L7: ="2Q"&RIGHT(K6,2) -> 2Q07 | M7: ="3Q"&RIGHT(K6,2) -> 3Q07 | N7: ="4Q"&RIGHT(K6,2) -> 4Q07 | O7: ="1Q"&RIGHT(O6,2) -> 1Q08 | P7: ="2Q"&RIGHT(O6,2) -> 2Q08 | Q7: ="3Q"&RIGHT(O6,2) -> 3Q08 | R7: ="4Q"&RIGHT(O6,2) -> 4Q08 | S7: ="1Q"&RIGHT(S6,2) -> 1Q09 | T7: ="2Q"&RIGHT(S6,2) -> 2Q09 | U7: ="3Q"&RIGHT(S6,2) -> 3Q09 | V7: ="4Q"&RIGHT(S6,2) -> 4Q09 | W7: ="1Q"&RIGHT(W6,2) -> 1Q10 | X7: ="2Q"&RIGHT(W6,2) -> 2Q10 | Y7: ="3Q"&RIGHT(W6,2) -> 3Q10 | Z7: ="4Q"&RIGHT(W6,2) -> 4Q10 | AA7: ="1Q"&RIGHT(AA6,2) -> 1Q11 | AB7: ="2Q"&RIGHT(AA6,2) -> 2Q11 | AC7: ="3Q"&RIGHT(AA6,2) -> 3Q11 | AD7: ="4Q"&RIGHT(AA6,2) -> 4Q11 | AE7: ="1Q"&RIGHT(AE6,2) -> 1Q12 | AF7: ="2Q"&RIGHT(AE6,2) -> 2Q12 | AG7: ="3Q"&RIGHT(AE6,2) -> 3Q12 | AH7: ="4Q"&RIGHT(AE6,2) -> 4Q12 | AI7: ="1Q"&RIGHT(AI6,2) -> 1Q13 | AJ7: ="2Q"&RIGHT(AI6,2) -> 2Q13 | AK7: ="3Q"&RIGHT(AI6,2) -> 3Q13 | AL7: ="4Q"&RIGHT(AI6,2) -> 4Q13 | AM7: ="1Q"&RIGHT(AM6,2) -> 1Q14 | AN7: ="2Q"&RIGHT(AM6,2) -> 2Q14 | AO7: ="3Q"&RIGHT(AM6,2) -> 3Q14 | AP7: ="4Q"&RIGHT(AM6,2) -> 4Q14 | AQ7: ="1Q"&RIGHT(AQ6,2) -> 1Q15 | AR7: ="2Q"&RIGHT(AQ6,2) -> 2Q15 | AS7: ="3Q"&RIGHT(AQ6,2) -> 3Q15 | AT7: ="4Q"&RIGHT(AQ6,2) -> 4Q15 | AU7: ="1Q"&RIGHT(AU6,2) -> 1Q16 | AV7: ="2Q"&RIGHT(AU6,2) -> 2Q16 | AW7: ="3Q"&RIGHT(AU6,2) -> 3Q16 | AX7: ="4Q"&RIGHT(AU6,2) -> 4Q16 | AY7: ="1Q"&RIGHT(AY6,2) -> 1Q17 | AZ7: ="2Q"&RIGHT(AY6,2) -> 2Q17 | BA7: ="3Q"&RIGHT(AY6,2) -> 3Q17 | BB7: ="4Q"&RIGHT(AY6,2) -> 4Q17 | BC7: ="1Q"&RIGHT(BC6,2) -> 1Q18 | BD7: ="2Q"&RIGHT(BC6,2) -> 2Q18 | BE7: ="3Q"&RIGHT(BC6,2) -> 3Q18 | BF7: ="4Q"&RIGHT(BC6,2) -> 4Q18 | BG7: ="1Q"&RIGHT(BG6,2) -> 1Q19 | BH7: ="2Q"&RIGHT(BG6,2) -> 2Q19 | BI7: ="3Q"&RIGHT(BG6,2) -> 3Q19 | BJ7: ="4Q"&RIGHT(BG6,2) -> 4Q19 | BK7: ="1Q"&RIGHT(BK6,2) -> 1Q20 | BL7: ="2Q"&RIGHT(BK6,2) -> 2Q20 | BM7: ="3Q"&RIGHT(BK6,2) -> 3Q20 | BN7: ="4Q"&RIGHT(BK6,2) -> 4Q20 | BO7: ="1Q"&RIGHT(BO6,2) -> 1Q21 | BP7: ="2Q"&RIGHT(BO6,2) -> 2Q21 | BQ7: ="3Q"&RIGHT(BO6,2) -> 3Q21 | BR7: ="4Q"&RIGHT(BO6,2) -> 4Q21 | BS7: ="1Q"&RIGHT(BS6,2) -> 1Q22 | BT7: ="2Q"&RIGHT(BS6,2) -> 2Q22 | BU7: ="3Q"&RIGHT(BS6,2) -> 3Q22 | BV7: ="4Q"&RIGHT(BS6,2) -> 4Q22 | BW7: ="1Q"&RIGHT(BW6,2) -> 1Q23 | BX7: ="2Q"&RIGHT(BW6,2) -> 2Q23 | BY7: ="3Q"&RIGHT(BW6,2) -> 3Q23 | BZ7: ="4Q"&RIGHT(BW6,2) -> 4Q23 | CA7: ="1Q"&RIGHT(CA6,2) -> 1Q24 | CB7: ="2Q"&RIGHT(CA6,2) -> 2Q24 | CC7: ="3Q"&RIGHT(CA6,2) -> 3Q24 | CD7: ="4Q"&RIGHT(CA6,2) -> 4Q24 | CE7: ="1Q"&RIGHT(CE6,2) -> 1Q25 | CF7: ="2Q"&RIGHT(CE6,2) -> 2Q25 | CG7: ="3Q"&RIGHT(CE6,2) -> 3Q25 | CH7: ="4Q"&RIGHT(CE6,2) -> 4Q25 | CI7: ="1Q"&RIGHT(CI6,2) -> 1Q26 | CJ7: ="2Q"&RIGHT(CI6,2) -> 2Q26 | CK7: ="3Q"&RIGHT(CI6,2) -> 3Q26 | CL7: ="4Q"&RIGHT(CI6,2) -> 4Q26 | CM7: ="1Q"&RIGHT(CM6,2) -> 1Q27 | CN7: ="2Q"&RIGHT(CM6,2) -> 2Q27 | CO7: ="3Q"&RIGHT(CM6,2) -> 3Q27 | CP7: ="4Q"&RIGHT(CM6,2) -> 4Q27 | CQ7: ="1Q"&RIGHT(CQ6,2) -> 1Q28 | CR7: ="2Q"&RIGHT(CQ6,2) -> 2Q28 | CS7: ="3Q"&RIGHT(CQ6,2) -> 3Q28 | CT7: ="4Q"&RIGHT(CQ6,2) -> 4Q28 | CU7: ="1Q"&RIGHT(CU6,2) -> 1Q29 | CV7: ="2Q"&RIGHT(CU6,2) -> 2Q29 | CW7: ="3Q"&RIGHT(CU6,2) -> 3Q29 | CX7: ="4Q"&RIGHT(CU6,2) -> 4Q29 | CY7: ="1Q"&RIGHT(CY6,2) -> 1Q30 | CZ7: ="2Q"&RIGHT(CY6,2) -> 2Q30 | DA7: ="3Q"&RIGHT(CY6,2) -> 3Q30 | DB7: ="4Q"&RIGHT(CY6,2) -> 4Q30 | DE7: (US$ Millions) | DF7: 2005 | DG7: =DF7+1 -> 2006 | DH7: =DG7+1 -> 2007 | DI7: =DH7+1 -> 2008 | DJ7: =DI7+1 -> 2009 | DK7: =DJ7+1 -> 2010 | DL7: =DK7+1 -> 2011 | DM7: =DL7+1 -> 2012 | DN7: =DM7+1 -> 2013 | ... DR7: =DQ7+1 -> 2017 | DS7: 2018 | DT7: =DS7+1 -> 2019 | DU7: =DT7+1 -> 2020 | DV7: =DU7+1 -> 2021 | DW7: =DV7+1 -> 2022 | DX7: =DW7+1 -> 2023 | DY7: =DX7+1 -> 2024 | DZ7: =DY7+1 -> 2025 | EA7: =DZ7+1 -> 2026 | ... EE7: =ED7+1 -> 2030
A8: x
B9: Product Revenue | BK9: =Sand!K9 -> 31.196277 | BL9: =Sand!L9 -> 7.403368 | BM9: =Sand!M9 -> 18.895485 | BN9: =Sand!N9 -> 22.374471 | BO9: =Sand!O9 -> 26.055639 | BP9: =Sand!P9 -> 35.496581 | BQ9: =Sand!Q9 -> 36.64477 | BR9: =Sand!R9 -> 44.322811 | ... DB9: =Sand!BB9 -> 190.66337 | DE9: =B9 -> Product Revenue | DS9: =SUMIF($C$5:$DC$5,DS$5,$C9:$DC9) -> 0 | DT9: =SUMIF($C$5:$DC$5,DT$5,$C9:$DC9) -> 0 | DU9: =SUMIF($C$5:$DC$5,DU$5,$C9:$DC9) -> 79.869601 | DV9: =SUMIF($C$5:$DC$5,DV$5,$C9:$DC9) -> 142.5198 | DW9: =SUMIF($C$5:$DC$5,DW$5,$C9:$DC9) -> 408.32798 | DX9: =SUMIF($C$5:$DC$5,DX$5,$C9:$DC9) -> 468.119 | DY9: =SUMIF($C$5:$DC$5,DY$5,$C9:$DC9) -> 515.434 | DZ9: =SUMIF($C$5:$DC$5,DZ$5,$C9:$DC9) -> 629.80808 | ... EE9: =SUMIF($C$5:$DC$5,EE$5,$C9:$DC9) -> 761.33422
B10: Service Revenue | BK10: =Logistics!K9 -> 11.525869 | BL10: =Logistics!L9 -> 6.3346108 | BM10: =Logistics!M9 -> 10.096583 | BN10: =Logistics!N9 -> 3.9449641 | BO10: =Logistics!O9 -> 5.7762551 | BP10: =Logistics!P9 -> 8.9322059 | BQ10: =Logistics!Q9 -> 6.6526026 | BR10: =Logistics!R9 -> 8.524797 | ... DB10: =Logistics!BB9 -> 171.28522 | DE10: =B10 -> Service Revenue | DS10: =SUMIF($C$5:$DC$5,DS$5,$C10:$DC10) -> 0 | DT10: =SUMIF($C$5:$DC$5,DT$5,$C10:$DC10) -> 0 | DU10: =SUMIF($C$5:$DC$5,DU$5,$C10:$DC10) -> 31.902027 | DV10: =SUMIF($C$5:$DC$5,DV$5,$C10:$DC10) -> 29.885861 | DW10: =SUMIF($C$5:$DC$5,DW$5,$C10:$DC10) -> 74.265797 | DX10: =SUMIF($C$5:$DC$5,DX$5,$C10:$DC10) -> 145.841 | DY10: =SUMIF($C$5:$DC$5,DY$5,$C10:$DC10) -> 542.0102 | DZ10: =SUMIF($C$5:$DC$5,DZ$5,$C10:$DC10) -> 663.71998 | ... EE10: =SUMIF($C$5:$DC$5,EE$5,$C10:$DC10) -> 681.56055
B11: Revenue | BK11: =SUM(BK9:BK10) -> 42.722146 | BL11: =SUM(BL9:BL10) -> 13.737979 | BM11: =SUM(BM9:BM10) -> 28.992068 | BN11: =SUM(BN9:BN10) -> 26.319435 | BO11: =SUM(BO9:BO10) -> 31.831894 | BP11: =SUM(BP9:BP10) -> 44.428787 | BQ11: =SUM(BQ9:BQ10) -> 43.297373 | BR11: =SUM(BR9:BR10) -> 52.847608 | ... DB11: =SUM(DB9:DB10) -> 361.94859 | DE11: Total Revenue | DF11: =SUMIF($C$5:$DC$5,DF$5,$C11:$DC11) -> 0 | DG11: =SUMIF($C$5:$DC$5,DG$5,$C11:$DC11) -> 0 | DH11: =SUMIF($C$5:$DC$5,DH$5,$C11:$DC11) -> 0 | DI11: =SUMIF($C$5:$DC$5,DI$5,$C11:$DC11) -> 0 | DJ11: =SUMIF($C$5:$DC$5,DJ$5,$C11:$DC11) -> 0 | DK11: =SUMIF($C$5:$DC$5,DK$5,$C11:$DC11) -> 0 | DL11: =SUMIF($C$5:$DC$5,DL$5,$C11:$DC11) -> 0 | DM11: =SUMIF($C$5:$DC$5,DM$5,$C11:$DC11) -> 0 | ... EE11: =SUMIF($C$5:$DC$5,EE$5,$C11:$DC11) -> 1442.8948
B12: Sequential Change | BL12: =BL11/BK11-1 -> -0.67843425 | BM12: =BM11/BL11-1 -> 1.1103591 | BN12: =BN11/BM11-1 -> -0.09218498 | BO12: =BO11/BN11-1 -> 0.20944442 | BP12: =BP11/BO11-1 -> 0.3957318 | BQ12: =BQ11/BP11-1 -> -0.02546579 | BR12: =BR11/BQ11-1 -> 0.2205731 | BS12: =BS11/BR11-1 -> 0.13257384 | ... DB12: =DB11/DA11-1 -> 0.00060848565 | DE12: Sequential Change | DT12: =IFERROR(DT11/DS11-1,"") | DU12: =IFERROR(DU11/DT11-1,"") | DV12: =IFERROR(DV11/DU11-1,"") -> 0.54248143 | DW12: =IFERROR(DW11/DV11-1,"") -> 1.7991759 | DX12: =IFERROR(DX11/DW11-1,"") -> 0.2722087 | DY12: =IFERROR(DY11/DX11-1,"") -> 0.72233403 | DZ12: =IFERROR(DZ11/DY11-1,"") -> 0.22325893 | EA12: =IFERROR(EA11/DZ11-1,"") -> 0.049502995 | ... EE12: =IFERROR(EE11/ED11-1,"") -> 0.0028639521
B14: Product Cost of Sales | BK14: =-Sand!K15 -> -15.5 | BL14: =-Sand!L15 -> -6.1 | BM14: =-Sand!M15 -> -12.6 | BN14: =-Sand!N15 -> -12.9 | BO14: =-Sand!O15 -> -13.1 | BP14: =-Sand!P15 -> -11.7 | BQ14: =-Sand!Q15 -> -13.1 | BR14: =-Sand!R15 -> -16.7 | ... DB14: =-Sand!BB15 -> -71.322252 | DE14: =B14 -> Product Cost of Sales | DS14: =SUMIF($C$5:$DC$5,DS$5,$C14:$DC14) -> 0 | DT14: =SUMIF($C$5:$DC$5,DT$5,$C14:$DC14) -> 0 | DU14: =SUMIF($C$5:$DC$5,DU$5,$C14:$DC14) -> -47.1 | DV14: =SUMIF($C$5:$DC$5,DV$5,$C14:$DC14) -> -54.6 | DW14: =SUMIF($C$5:$DC$5,DW$5,$C14:$DC14) -> -131.35795 | DX14: =SUMIF($C$5:$DC$5,DX$5,$C14:$DC14) -> -124.2208 | DY14: =SUMIF($C$5:$DC$5,DY$5,$C14:$DC14) -> -269.94247 | DZ14: =SUMIF($C$5:$DC$5,DZ$5,$C14:$DC14) -> -300.84468 | ... EE14: =SUMIF($C$5:$DC$5,EE$5,$C14:$DC14) -> -285.25075
B15: Service Cost of Sales | BK15: =BK16-BK14 -> -2.7795 | BL15: =BL16-BL14 -> -12.1795 | BM15: =BM16-BM14 -> -5.6795 | BN15: =BN16-BN14 -> -5.3795 | BO15: =BO16-BO14 -> -5.82 | BP15: =BP16-BP14 -> -10.212 | BQ15: =BQ16-BQ14 -> -8.812 | BR15: =BR16-BR14 -> -5.212 | BS15: =-Logistics!S12 -> -4.6940753 | BT15: =-Logistics!T12 -> -17.044394 | BU15: =-Logistics!U12 -> -20.443735 | BV15: =-Logistics!V12 -> -25.421909 | BW15: =-Logistics!W12 -> -16.939043 | BX15: =-Logistics!X12 -> -31.9 | BY15: =-Logistics!Y12 -> -37.6 | BZ15: =-Logistics!Z12 -> -36.3 | ... DB15: =-Logistics!BB12 -> -146.88969 | DE15: =B15 -> Service Cost of Sales | DS15: =SUMIF($C$5:$DC$5,DS$5,$C15:$DC15) -> 0 | DT15: =SUMIF($C$5:$DC$5,DT$5,$C15:$DC15) -> 0 | DU15: =SUMIF($C$5:$DC$5,DU$5,$C15:$DC15) -> -26.018 | DV15: =SUMIF($C$5:$DC$5,DV$5,$C15:$DC15) -> -30.056 | DW15: =SUMIF($C$5:$DC$5,DW$5,$C15:$DC15) -> -67.604113 | DX15: =SUMIF($C$5:$DC$5,DX$5,$C15:$DC15) -> -122.73904 | DY15: =SUMIF($C$5:$DC$5,DY$5,$C15:$DC15) -> -458.71969 | DZ15: =SUMIF($C$5:$DC$5,DZ$5,$C15:$DC15) -> -567.77285 | ... EE15: =SUMIF($C$5:$DC$5,EE$5,$C15:$DC15) -> -584.48863
B16: Cost of Sales | BK16: =-73.118/4 -> -18.2795 | BL16: =-73.118/4 -> -18.2795 | BM16: =-73.118/4 -> -18.2795 | BN16: =-73.118/4 -> -18.2795 | BO16: -18.92 | BP16: =-(84.656+$BO$16)/3 -> -21.912 | BQ16: =-(84.656+$BO$16)/3 -> -21.912 | BR16: =-(84.656+$BO$16)/3 -> -21.912 | BS16: =SUM(BS14:BS15) -> -24.494075 | BT16: =SUM(BT14:BT15) -> -47.044394 | BU16: =SUM(BU14:BU15) -> -60.138574 | BV16: =SUM(BV14:BV15) -> -67.285024 | BW16: -62.555 | BX16: -63.504 | BY16: -67.77 | BZ16: -66.567 | CA16: -106.746 | CB16: -202.136 | CC16: -225.347 | CD16: =SUM(CD14:CD15) -> -194.56217 | CE16: =SUM(CE14:CE15) -> -209.36946 | CF16: =SUM(CF14:CF15) -> -218.47626 | CG16: =SUM(CG14:CG15) -> -220.32899 | CH16: =SUM(CH14:CH15) -> -220.44283 | CI16: =SUM(CI14:CI15) -> -212.67077 | CJ16: =SUM(CJ14:CJ15) -> -214.91263 | CK16: =SUM(CK14:CK15) -> -217.0316 | ... DB16: =SUM(DB14:DB15) -> -218.21194 | DE16: =B16 -> Cost of Sales | DS16: =SUMIF($C$5:$DC$5,DS$5,$C16:$DC16) -> 0 | DT16: =SUMIF($C$5:$DC$5,DT$5,$C16:$DC16) -> 0 | DU16: =SUMIF($C$5:$DC$5,DU$5,$C16:$DC16) -> -73.118 | DV16: =SUMIF($C$5:$DC$5,DV$5,$C16:$DC16) -> -84.656 | DW16: =SUMIF($C$5:$DC$5,DW$5,$C16:$DC16) -> -198.96207 | DX16: =SUMIF($C$5:$DC$5,DX$5,$C16:$DC16) -> -260.396 | DY16: =SUMIF($C$5:$DC$5,DY$5,$C16:$DC16) -> -728.79117 | DZ16: =SUMIF($C$5:$DC$5,DZ$5,$C16:$DC16) -> -868.61754 | ... EE16: =SUMIF($C$5:$DC$5,EE$5,$C16:$DC16) -> -869.73938
B17: Cost of Sales/Revenue (%) | BK17: =-BK16/BK11 -> 0.42786942 | BL17: =-BL16/BL11 -> 1.3305815 | BM17: =-BM16/BM11 -> 0.63050003 | BN17: =-BN16/BN11 -> 0.69452478 | BO17: =-BO16/BO11 -> 0.59437242 | BP17: =-BP16/BP11 -> 0.49319375 | BQ17: =-BQ16/BQ11 -> 0.50608152 | BR17: =-BR16/BR11 -> 0.41462614 | ... DB17: =-DB16/DB11 -> 0.60288104 | DE17: =B17 -> Cost of Sales/Revenue (%) | DS17: =IFERROR(-DS16/DS11,"") | DT17: =IFERROR(-DT16/DT11,"") | DU17: =IFERROR(-DU16/DU11,"") -> 0.65417316 | DV17: =IFERROR(-DV16/DV11,"") -> 0.49102796 | DW17: =IFERROR(-DW16/DW11,"") -> 0.41227649 | DX17: =IFERROR(-DX16/DX11,"") -> 0.42412535 | DY17: =IFERROR(-DY16/DY11,"") -> 0.68920059 | DZ17: =IFERROR(-DZ16/DZ11,"") -> 0.67151039 | ... EE17: =IFERROR(-EE16/EE11,"") -> 0.60277395
B19: Product Gross Margins | BK19: =BK9+BK14 -> 15.696277 | BL19: =BL9+BL14 -> 1.303368 | BM19: =BM9+BM14 -> 6.2954851 | BN19: =BN9+BN14 -> 9.4744712 | BO19: =BO9+BO14 -> 12.955639 | BP19: =BP9+BP14 -> 23.796581 | BQ19: =BQ9+BQ14 -> 23.54477 | BR19: =BR9+BR14 -> 27.622811 | ... DB19: =DB9+DB14 -> 119.34112 | DE19: Product Gross Margins | DS19: =SUMIF($C$5:$DC$5,DS$5,$C19:$DC19) -> 0 | DT19: =SUMIF($C$5:$DC$5,DT$5,$C19:$DC19) -> 0 | DU19: =SUMIF($C$5:$DC$5,DU$5,$C19:$DC19) -> 32.769601 | DV19: =SUMIF($C$5:$DC$5,DV$5,$C19:$DC19) -> 87.919801 | DW19: =SUMIF($C$5:$DC$5,DW$5,$C19:$DC19) -> 276.97002 | DX19: =SUMIF($C$5:$DC$5,DX$5,$C19:$DC19) -> 343.8982 | DY19: =SUMIF($C$5:$DC$5,DY$5,$C19:$DC19) -> 245.49153 | DZ19: =SUMIF($C$5:$DC$5,DZ$5,$C19:$DC19) -> 328.9634 | ... EE19: =SUMIF($C$5:$DC$5,EE$5,$C19:$DC19) -> 476.08347
B20: Service Gross Margins | BK20: =BK21-BK19 -> 8.746369 | BL20: =BL21-BL19 -> -5.8448892 | BM20: =BM21-BM19 -> 4.4170834 | BN20: =BN21-BN19 -> -1.4345359 | BO20: =BO21-BO19 -> -0.04374487 | BP20: =BP21-BP19 -> -1.2797941 | BQ20: =BQ21-BQ19 -> -2.1593974 | BR20: =BR21-BR19 -> 3.312797 | BS20: =BS21-BS19 -> 0.29694124 | BT20: =BT10+BT15 -> 1.747107 | BU20: =BU10+BU15 -> 2.0562651 | BV20: =BV10+BV15 -> 2.5613707 | BW20: =BW10+BW15 -> 8.3369572 | BX20: =BX10+BX15 -> 4.672 | BY20: =BY10+BY15 -> 5.243 | BZ20: =BZ10+BZ15 -> 4.85 | CA20: =CA10+CA15 -> 12.035 | ... DB20: =DB10+DB15 -> 24.395529 | DE20: Service Gross Margins | DS20: =SUMIF($C$5:$DC$5,DS$5,$C20:$DC20) -> 0 | DT20: =SUMIF($C$5:$DC$5,DT$5,$C20:$DC20) -> 0 | DU20: =SUMIF($C$5:$DC$5,DU$5,$C20:$DC20) -> 5.8840273 | DV20: =SUMIF($C$5:$DC$5,DV$5,$C20:$DC20) -> -0.17013939 | DW20: =SUMIF($C$5:$DC$5,DW$5,$C20:$DC20) -> 6.661684 | DX20: =SUMIF($C$5:$DC$5,DX$5,$C20:$DC20) -> 23.101957 | DY20: =SUMIF($C$5:$DC$5,DY$5,$C20:$DC20) -> 83.290509 | DZ20: =SUMIF($C$5:$DC$5,DZ$5,$C20:$DC20) -> 95.947124 | ... EE20: =SUMIF($C$5:$DC$5,EE$5,$C20:$DC20) -> 97.07192
B21: Total Gross Margins | BK21: =BK11+BK16 -> 24.442646 | BL21: =BL11+BL16 -> -4.5415212 | BM21: =BM11+BM16 -> 10.712568 | BN21: =BN11+BN16 -> 8.0399352 | BO21: =BO11+BO16 -> 12.911894 | BP21: =BP11+BP16 -> 22.516787 | BQ21: =BQ11+BQ16 -> 21.385373 | BR21: =BR11+BR16 -> 30.935608 | ... DB21: =DB11+DB16 -> 143.73665 | DE21: Total Gross Margins | DS21: =DS11+DS16 -> 0 | DT21: =DT11+DT16 -> 0 | DU21: =DU11+DU16 -> 38.653629 | DV21: =DV11+DV16 -> 87.749662 | DW21: =DW11+DW16 -> 283.63171 | DX21: =DX11+DX16 -> 353.564 | DY21: =DY11+DY16 -> 328.65303 | DZ21: =DZ11+DZ16 -> 424.91052 | ... EE21: =EE11+EE16 -> 573.15539
B22: Gross Margins (%) | BK22: =BK21/BK11 -> 0.57213058 | BL22: =BL21/BL11 -> -0.33058147 | BM22: =BM21/BM11 -> 0.36949997 | BN22: =BN21/BN11 -> 0.30547522 | BO22: =BO21/BO11 -> 0.40562758 | BP22: =BP21/BP11 -> 0.50680625 | BQ22: =BQ21/BQ11 -> 0.49391848 | BR22: =BR21/BR11 -> 0.58537386 | ... DB22: =DB21/DB11 -> 0.39711896 | DE22: Gross Margins (%) | DS22: =IFERROR(-DS21/DS16,"") | DT22: =IFERROR(-DT21/DT16,"") | DU22: =IFERROR(-DU21/DU16,"") -> 0.52864724 | DV22: =IFERROR(-DV21/DV16,"") -> 1.0365439 | DW22: =IFERROR(-DW21/DW16,"") -> 1.4255567 | DX22: =IFERROR(-DX21/DX16,"") -> 1.3577935 | DY22: =IFERROR(-DY21/DY16,"") -> 0.45095639 | DZ22: =IFERROR(-DZ21/DZ16,"") -> 0.48918023 | ... EE22: =IFERROR(-EE21/EE16,"") -> 0.65899671
B24: SG&A | BG24: -4.2434202 | BH24: -4.5911024 | BI24: -3.9203252 | BJ24: -4.0146686 | BK24: -4.0907364 | BL24: -2.4430765 | BM24: -3.4044525 | BN24: -4.5680524 | BO24: -3.9740135 | BP24: -3.7569652 | BQ24: -3.5100979 | BR24: -4.778099 | BS24: -4.7567287 | BT24: -4.843585 | BU24: -5.4519953 | BV24: -7.4680798 | BW24: -8.504 | BX24: -12.183 | BY24: -14.301 | BZ24: -13.648 | CA24: -29.069 | CB24: -27.266 | CC24: -25.463 | CD24: =-CD25*CD11 -> -19.097764 | CE24: =-CE25*CE11 -> -20.065485 | CF24: =-CF25*CF11 -> -23.164469 | CG24: =-CG25*CG11 -> -23.612158 | CH24: =-CH25*CH11 -> -23.704852 | CI24: =-CI25*CI11 -> -23.246902 | CJ24: =-CJ25*CJ11 -> -23.591998 | CK24: =-CK25*CK11 -> -23.994576 | ... DB24: =-DB25*DB11 -> -25.336401 | DE24: =B24 -> SG&A | DS24: =SUMIF($C$5:$DC$5,DS$5,$C24:$DC24) -> 0 | DT24: =SUMIF($C$5:$DC$5,DT$5,$C24:$DC24) -> -16.769516 | DU24: =SUMIF($C$5:$DC$5,DU$5,$C24:$DC24) -> -14.506318 | DV24: =SUMIF($C$5:$DC$5,DV$5,$C24:$DC24) -> -16.019176 | DW24: =SUMIF($C$5:$DC$5,DW$5,$C24:$DC24) -> -22.520389 | DX24: =SUMIF($C$5:$DC$5,DX$5,$C24:$DC24) -> -48.636 | DY24: =SUMIF($C$5:$DC$5,DY$5,$C24:$DC24) -> -100.89576 | DZ24: =SUMIF($C$5:$DC$5,DZ$5,$C24:$DC24) -> -90.546964 | ... EE24: =SUMIF($C$5:$DC$5,EE$5,$C24:$DC24) -> -101.00263
B25: SG&A as a % of Sales | BK25: =-BK24/BK11 -> 0.095752129 | BL25: =-BL24/BL11 -> 0.17783377 | BM25: =-BM24/BM11 -> 0.11742703 | BN25: =-BN24/BN11 -> 0.17356194 | BO25: =-BO24/BO11 -> 0.12484377 | BP25: =-BP24/BP11 -> 0.084561509 | BQ25: =-BQ24/BQ11 -> 0.081069536 | BR25: =-BR24/BR11 -> 0.090412777 | ... CC25: =-CC24/CC11 -> 0.083640461 | CD25: 0.07 | CE25: 0.07 | CF25: 0.07 | CG25: 0.07 | CH25: 0.07 | CI25: 0.07 | CJ25: 0.07 | CK25: 0.07 | CL25: 0.07 | CM25: 0.07 | CN25: 0.07 | CO25: 0.07 | CP25: 0.07 | CQ25: 0.07 | CR25: 0.07 | CS25: 0.07 | CT25: 0.07 | CU25: 0.07 | CV25: 0.07 | CW25: 0.07 | CX25: 0.07 | CY25: 0.07 | CZ25: 0.07 | DA25: 0.07 | DB25: 0.07 | DE25: =B25 -> SG&A as a % of Sales | DS25: =IFERROR(-DS24/DS11,"") | DT25: =IFERROR(-DT24/DT11,"") | DU25: =IFERROR(-DU24/DU11,"") -> 0.12978533 | DV25: =IFERROR(-DV24/DV11,"") -> 0.092915601 | DW25: =IFERROR(-DW24/DW11,"") -> 0.046665312 | DX25: =IFERROR(-DX24/DX11,"") -> 0.079216887 | DY25: =IFERROR(-DY24/DY11,"") -> 0.095414741 | DZ25: =IFERROR(-DZ24/DZ11,"") -> 0.07 | ... EE25: =IFERROR(-EE24/EE11,"") -> 0.07
B27: Depreciation and Amortization | BG27: -4.821297 | BH27: -5.110327 | BI27: -5.742968 | BJ27: -5.2334756 | BK27: -5.6177018 | BL27: -4.7066194 | BM27: -5.4692377 | BN27: -5.7231352 | BO27: -5.6814658 | BP27: -6.1653538 | BQ27: -6.1750633 | BR27: -6.5190106 | BS27: -6.4644721 | BT27: -6.7318501 | BU27: -7.2806603 | BV27: -7.9770085 | BW27: -8.519 | BX27: -9.433 | BY27: -10.221 | BZ27: -11.625 | CA27: =-17.175 -> -17.175 | CB27: -25.027 | CC27: -26.069 | CD27: =CD95 -> -26.199345 | CE27: =CE95 -> -26.199345 | CF27: =CF95 -> -26.199345 | CG27: =CG95 -> -26.199345 | CH27: =CH95 -> -26.199345 | CI27: =CI95 -> -26.199345 | CJ27: =CJ95 -> -26.199345 | CK27: =CK95 -> -26.199345 | ... DB27: =DB95 -> -26.199345 | DE27: =B27 -> Depreciation and Amortization | DS27: =SUMIF($C$5:$DC$5,DS$5,$C27:$DC27) -> 0 | DT27: =SUMIF($C$5:$DC$5,DT$5,$C27:$DC27) -> -20.908068 | DU27: =SUMIF($C$5:$DC$5,DU$5,$C27:$DC27) -> -21.516694 | DV27: =SUMIF($C$5:$DC$5,DV$5,$C27:$DC27) -> -24.540894 | DW27: =SUMIF($C$5:$DC$5,DW$5,$C27:$DC27) -> -28.453991 | DX27: =SUMIF($C$5:$DC$5,DX$5,$C27:$DC27) -> -39.798 | DY27: =SUMIF($C$5:$DC$5,DY$5,$C27:$DC27) -> -94.470345 | DZ27: =SUMIF($C$5:$DC$5,DZ$5,$C27:$DC27) -> -104.79738 | ... EE27: =SUMIF($C$5:$DC$5,EE$5,$C27:$DC27) -> -104.79738
B29: Total Operating Income | BK29: =SUM(BK11,BK16,BK24,BK27) -> 14.734208 | BL29: =SUM(BL11,BL16,BL24,BL27) -> -11.691217 | BM29: =SUM(BM11,BM16,BM24,BM27) -> 1.8388783 | BN29: =SUM(BN11,BN16,BN24,BN27) -> -2.2512523 | BO29: =SUM(BO11,BO16,BO24,BO27) -> 3.2564148 | BP29: =SUM(BP11,BP16,BP24,BP27) -> 12.594468 | BQ29: =SUM(BQ11,BQ16,BQ24,BQ27) -> 11.700211 | BR29: =SUM(BR11,BR16,BR24,BR27) -> 19.638499 | ... DB29: =SUM(DB11,DB16,DB24,DB27) -> 92.200902 | DE29: Total Segment Operating Income | DF29: =SUMIF($C$5:$DC$5,DF$5,$C29:$DC29) -> 0 | DG29: =SUMIF($C$5:$DC$5,DG$5,$C29:$DC29) -> 0 | DH29: =SUMIF($C$5:$DC$5,DH$5,$C29:$DC29) -> 0 | DI29: =SUMIF($C$5:$DC$5,DI$5,$C29:$DC29) -> 0 | DJ29: =SUMIF($C$5:$DC$5,DJ$5,$C29:$DC29) -> 0 | DK29: =SUMIF($C$5:$DC$5,DK$5,$C29:$DC29) -> 0 | DL29: =SUMIF($C$5:$DC$5,DL$5,$C29:$DC29) -> 0 | DM29: =SUMIF($C$5:$DC$5,DM$5,$C29:$DC29) -> 0 | ... EE29: =SUMIF($C$5:$DC$5,EE$5,$C29:$DC29) -> 367.35537
B30: Corporate & Other Expenses | BK30: =-1.25/4 -> -0.3125 | BL30: =-1.25/4 -> -0.3125 | BM30: =-1.25/4 -> -0.3125 | BN30: =-1.25/4 -> -0.3125 | BO30: 0 | BP30: 0 | BQ30: 0 | BR30: 0 | BS30: 0 | BT30: 0 | BU30: 0 | BV30: 0 | BW30: 0 | BX30: 0 | BY30: 0 | BZ30: 0 | CA30: 0 | CB30: =3.768+11.098-10 -> 4.866 | CC30: =3.744+8.574 -> 12.318 | CD30: 0 | CE30: =CD30 -> 0 | CF30: =CE30 -> 0 | CG30: =CF30 -> 0 | CH30: =CG30 -> 0 | CI30: =CH30 -> 0 | CJ30: =CI30 -> 0 | CK30: =CJ30 -> 0 | CL30: =CK30 -> 0 | ... DB30: =DA30 -> 0 | DE30: Corporate & Other | DF30: =SUMIF($C$5:$DC$5,DF$5,$C30:$DC30) -> 0 | DG30: =SUMIF($C$5:$DC$5,DG$5,$C30:$DC30) -> 0 | DH30: =SUMIF($C$5:$DC$5,DH$5,$C30:$DC30) -> 0 | DI30: =SUMIF($C$5:$DC$5,DI$5,$C30:$DC30) -> 0 | DJ30: =SUMIF($C$5:$DC$5,DJ$5,$C30:$DC30) -> 0 | DK30: =SUMIF($C$5:$DC$5,DK$5,$C30:$DC30) -> 0 | DL30: =SUMIF($C$5:$DC$5,DL$5,$C30:$DC30) -> 0 | DM30: =SUMIF($C$5:$DC$5,DM$5,$C30:$DC30) -> 0 | ... EE30: =SUMIF($C$5:$DC$5,EE$5,$C30:$DC30) -> 0
A31: x | B31: Total Operating Income | BK31: =BK29+BK30 -> 14.421708 | BL31: =BL29+BL30 -> -12.003717 | BM31: =BM29+BM30 -> 1.5263783 | BN31: =BN29+BN30 -> -2.5637523 | BO31: =BO29+BO30 -> 3.2564148 | BP31: =BP29+BP30 -> 12.594468 | BQ31: =BQ29+BQ30 -> 11.700211 | BR31: =BR29+BR30 -> 19.638499 | ... CA31: =CA29+CA30 -> 39.677 | CB31: =CB29-CB30 -> 28.223 | CC31: =CC29-CC30 -> 15.237 | CD31: =CD29-CD30 -> 32.965925 | CE31: =CE29-CE30 -> 31.015491 | CF31: =CF29-CF30 -> 63.080917 | CG31: =CG29-CG30 -> 67.176055 | CH31: =CH29-CH30 -> 68.293717 | CI31: =CI29-CI30 -> 69.981576 | ... DB31: =DB29-DB30 -> 92.200902 | DE31: Total Operating Income | DF31: =SUMIF($C$5:$DC$5,DF$5,$C31:$DC31) -> 0 | DG31: =SUMIF($C$5:$DC$5,DG$5,$C31:$DC31) -> 0 | DH31: =SUMIF($C$5:$DC$5,DH$5,$C31:$DC31) -> 0 | DI31: =SUMIF($C$5:$DC$5,DI$5,$C31:$DC31) -> 0 | DJ31: =SUMIF($C$5:$DC$5,DJ$5,$C31:$DC31) -> 0 | DK31: =SUMIF($C$5:$DC$5,DK$5,$C31:$DC31) -> 0 | DL31: =SUMIF($C$5:$DC$5,DL$5,$C31:$DC31) -> 0 | DM31: =SUMIF($C$5:$DC$5,DM$5,$C31:$DC31) -> 0 | ... EE31: =SUMIF($C$5:$DC$5,EE$5,$C31:$DC31) -> 367.35537
B32: Interest Expense | BK32: -7.5915417 | BL32: -8.0636007 | BM32: -8.4732294 | BN32: -8.6907927 | BO32: -8.4997901 | BP32: -8.5120422 | BQ32: -8.2526235 | BR32: -5.0118261 | BS32: -3.9897278 | BT32: -3.8835333 | BU32: -3.8762648 | BV32: -3.9903049 | BW32: -3.442 | BX32: -0.521 | BY32: -1.496 | BZ32: -2.23 | CA32: -4.978 | CB32: -10.458 | CC32: -11.193 | CD32: =+CC32 -> -11.193 | CE32: =CD32*0.8 -> -8.9544 | CF32: =CE32*0.8 -> -7.16352 | CG32: =CF32*0.7 -> -5.014464 | CH32: =CG32*0.65 -> -3.2594016 | CI32: =CH32 -> -3.2594016 | CJ32: =CI32 -> -3.2594016 | CK32: =CJ32 -> -3.2594016 | CL32: =CK32 -> -3.2594016 | CM32: =CL32 -> -3.2594016 | CN32: =CM32 -> -3.2594016 | CO32: =CN32 -> -3.2594016 | CP32: =CO32 -> -3.2594016 | ... DB32: =DA32 -> -3.2594016 | DE32: Interest Income | DF32: =SUMIF($C$5:$DC$5,DF$5,$C32:$DC32) -> 0 | DG32: =SUMIF($C$5:$DC$5,DG$5,$C32:$DC32) -> 0 | DH32: =SUMIF($C$5:$DC$5,DH$5,$C32:$DC32) -> 0 | DI32: =SUMIF($C$5:$DC$5,DI$5,$C32:$DC32) -> 0 | DJ32: =SUMIF($C$5:$DC$5,DJ$5,$C32:$DC32) -> 0 | DK32: =SUMIF($C$5:$DC$5,DK$5,$C32:$DC32) -> 0 | DL32: =SUMIF($C$5:$DC$5,DL$5,$C32:$DC32) -> 0 | DM32: =SUMIF($C$5:$DC$5,DM$5,$C32:$DC32) -> 0 | ... EE32: =SUMIF($C$5:$DC$5,EE$5,$C32:$DC32) -> -13.037606
B33: Other Income | BK33: -1.0768248 | BL33: -2.1837639 | BM33: -0.12735546 | BN33: -0.49349374 | BO33: 0.01130557 | BP33: 4.4923336 | BQ33: 0.03033345 | BR33: 0.056895 | BS33: 0 | BT33: 0 | BU33: 0 | BV33: 0 | BW33: 0.184 | BX33: 0.118 | BY33: 0.136 | BZ33: -0.008 | CA33: 0.023 | CB33: =0.138 -> 0.138 | CC33: 0.289 | CD33: 0 | CE33: 0 | CF33: 0 | CG33: 0 | CH33: 0 | CI33: 0 | CJ33: 0 | CK33: 0 | CL33: 0 | CM33: 0 | CN33: 0 | CO33: 0 | CP33: 0 | CQ33: 0 | CR33: 0 | CS33: 0 | CT33: 0 | CU33: 0 | CV33: 0 | CW33: 0 | CX33: 0 | CY33: 0 | CZ33: 0 | DA33: 0 | DB33: 0 | DE33: Other Income | DF33: =SUMIF($C$5:$DC$5,DF$5,$C33:$DC33) -> 0 | DG33: =SUMIF($C$5:$DC$5,DG$5,$C33:$DC33) -> 0 | DH33: =SUMIF($C$5:$DC$5,DH$5,$C33:$DC33) -> 0 | DI33: =SUMIF($C$5:$DC$5,DI$5,$C33:$DC33) -> 0 | DJ33: =SUMIF($C$5:$DC$5,DJ$5,$C33:$DC33) -> 0 | DK33: =SUMIF($C$5:$DC$5,DK$5,$C33:$DC33) -> 0 | DL33: =SUMIF($C$5:$DC$5,DL$5,$C33:$DC33) -> 0 | DM33: =SUMIF($C$5:$DC$5,DM$5,$C33:$DC33) -> 0 | ... EE33: =SUMIF($C$5:$DC$5,EE$5,$C33:$DC33) -> 0
B34: Pretax Income | BK34: =SUM(BK31:BK33) -> 5.7533412 | BL34: =SUM(BL31:BL33) -> -22.251082 | BM34: =SUM(BM31:BM33) -> -7.0742065 | BN34: =SUM(BN31:BN33) -> -11.748039 | BO34: =SUM(BO31:BO33) -> -5.2320697 | BP34: =SUM(BP31:BP33) -> 8.5747592 | BQ34: =SUM(BQ31:BQ33) -> 3.4779213 | BR34: =SUM(BR31:BR33) -> 14.683567 | ... DB34: =SUM(DB31:DB33) -> 88.941501 | DE34: Pretax Income | DF34: =SUMIF($C$5:$DC$5,DF$5,$C34:$DC34) -> 0 | DG34: =SUMIF($C$5:$DC$5,DG$5,$C34:$DC34) -> 0 | DH34: =SUMIF($C$5:$DC$5,DH$5,$C34:$DC34) -> 0 | DI34: =SUMIF($C$5:$DC$5,DI$5,$C34:$DC34) -> 0 | DJ34: =SUMIF($C$5:$DC$5,DJ$5,$C34:$DC34) -> 0 | DK34: =SUMIF($C$5:$DC$5,DK$5,$C34:$DC34) -> 0 | DL34: =SUMIF($C$5:$DC$5,DL$5,$C34:$DC34) -> 0 | DM34: =SUMIF($C$5:$DC$5,DM$5,$C34:$DC34) -> 0 | ... EE34: =SUMIF($C$5:$DC$5,EE$5,$C34:$DC34) -> 354.31777
B36: Income Taxes | BG36: -0.0821475 | BH36: -0.0875625 | BI36: -0.025545 | BJ36: -0.041565 | BK36: -0.0857925 | BL36: 0.0131925 | BM36: -0.0253725 | BN36: -0.274951 | BO36: -0.10268001 | BP36: -0.11680255 | BQ36: -0.10268034 | BR36: -0.14824142 | BS36: -0.22512244 | BT36: -0.59279696 | BU36: -0.58053417 | BV36: -0.63080949 | BW36: -7.677 | BX36: -5.054 | BY36: -7.637 | BZ36: -11.01 | CA36: -7.935 | CB36: -3.066 | CC36: -0.415 | CD36: =-CD34*CD37 -> -4.3545851 | CE36: =-CE34*CE37 -> -4.6328291 | CF36: =-CF34*CF37 -> -11.742653 | CG36: =-CG34*CG37 -> -13.053934 | CH36: =-CH34*CH37 -> -13.657206 | CI36: =-CI34*CI37 -> -14.011657 | CJ36: =-CJ34*CJ37 -> -14.503684 | CK36: =-CK34*CK37 -> -15.181896 | ... DB36: =-DB34*DB37 -> -18.677715 | DE36: Income Taxes | DF36: =SUMIF($C$5:$DC$5,DF$5,$C36:$DC36) -> 0 | DG36: =SUMIF($C$5:$DC$5,DG$5,$C36:$DC36) -> 0 | DH36: =SUMIF($C$5:$DC$5,DH$5,$C36:$DC36) -> 0 | DI36: =SUMIF($C$5:$DC$5,DI$5,$C36:$DC36) -> 0 | DJ36: =SUMIF($C$5:$DC$5,DJ$5,$C36:$DC36) -> 0 | DK36: =SUMIF($C$5:$DC$5,DK$5,$C36:$DC36) -> 0 | DL36: =SUMIF($C$5:$DC$5,DL$5,$C36:$DC36) -> 0 | DM36: =SUMIF($C$5:$DC$5,DM$5,$C36:$DC36) -> 0 | ... EE36: =SUMIF($C$5:$DC$5,EE$5,$C36:$DC36) -> -74.406731
B37: Tax Rate | BK37: =-BK36/BK34 -> 0.01491177 | BL37: =-BL36/BL34 -> 0.00059289253 | BM37: =-BM36/BM34 -> -0.0035866213 | BN37: =-BN36/BN34 -> -0.023403991 | BO37: =-BO36/BO34 -> -0.019625123 | BP37: =-BP36/BP34 -> 0.013621671 | BQ37: =-BQ36/BQ34 -> 0.02952348 | BR37: =-BR36/BR34 -> 0.010095736 | ... CC37: =-CC36/CC34 -> 0.095776598 | CD37: 0.2 | CE37: 0.21 | CF37: 0.21 | CG37: 0.21 | CH37: 0.21 | CI37: 0.21 | CJ37: 0.21 | CK37: 0.21 | CL37: 0.21 | CM37: 0.21 | CN37: 0.21 | CO37: 0.21 | CP37: 0.21 | CQ37: 0.21 | CR37: 0.21 | CS37: 0.21 | CT37: 0.21 | CU37: 0.21 | CV37: 0.21 | CW37: 0.21 | CX37: 0.21 | CY37: 0.21 | CZ37: 0.21 | DA37: 0.21 | DB37: 0.21 | DE37: Tax Rate | DF37: =-DF36/DF34 -> #DIV/0! | DG37: =-DG36/DG34 -> #DIV/0! | DH37: =-DH36/DH34 -> #DIV/0! | DI37: =-DI36/DI34 -> #DIV/0! | DJ37: =-DJ36/DJ34 -> #DIV/0! | DK37: =-DK36/DK34 -> #DIV/0! | DL37: =-DL36/DL34 -> #DIV/0! | DM37: =-DM36/DM34 -> #DIV/0! | ... DR37: =-DR36/DR34 -> #DIV/0! | DU37: =-DU36/DU34 -> -0.010558427 | DV37: =-DV36/DV34 -> 0.02187502 | DW37: =-DW36/DW34 -> 0.0093549995 | DX37: =-DX36/DX34 -> 0.121681 | DY37: =-DY36/DY34 -> 0.20030992 | DZ37: =-DZ36/DZ34 -> 0.21 | EA37: =-EA36/EA34 -> 0.21 | EB37: =-EB36/EB34 -> 0.21 | ... EE37: =-EE36/EE34 -> 0.21
B38: Minority Interest | BK38: 0 | BL38: 0 | BM38: 0 | BN38: 0 | BO38: 0 | BP38: 0 | BQ38: 0 | BR38: 0 | BS38: 0 | BT38: 0 | BU38: 0 | BV38: 0 | BW38: 0 | BX38: 0 | BY38: 0 | BZ38: 0 | CA38: 0 | CB38: 0 | CC38: 0 | CD38: =CC38 -> 0 | CE38: =CD38 -> 0 | CF38: =CE38 -> 0 | CG38: =CF38 -> 0 | CH38: =CG38 -> 0 | CI38: =CH38 -> 0 | CJ38: =CI38 -> 0 | CK38: =CJ38 -> 0 | ... DB38: =DA38 -> 0 | DE38: Minority Interests | DF38: =SUMIF($C$5:$DC$5,DF$5,$C38:$DC38) -> 0 | DG38: =SUMIF($C$5:$DC$5,DG$5,$C38:$DC38) -> 0 | DH38: =SUMIF($C$5:$DC$5,DH$5,$C38:$DC38) -> 0 | DI38: =SUMIF($C$5:$DC$5,DI$5,$C38:$DC38) -> 0 | DJ38: =SUMIF($C$5:$DC$5,DJ$5,$C38:$DC38) -> 0 | DK38: =SUMIF($C$5:$DC$5,DK$5,$C38:$DC38) -> 0 | DL38: =SUMIF($C$5:$DC$5,DL$5,$C38:$DC38) -> 0 | DM38: =SUMIF($C$5:$DC$5,DM$5,$C38:$DC38) -> 0 | ... EE38: =SUMIF($C$5:$DC$5,EE$5,$C38:$DC38) -> 0
A39: x | B39: Net Income | BK39: =BK34+BK36+BK38 -> 5.6675487 | BL39: =BL34+BL36+BL38 -> -22.237889 | BM39: =BM34+BM36+BM38 -> -7.099579 | BN39: =BN34+BN36+BN38 -> -12.02299 | BO39: =BO34+BO36+BO38 -> -5.3347498 | BP39: =BP34+BP36+BP38 -> 8.4579566 | BQ39: =BQ34+BQ36+BQ38 -> 3.375241 | BR39: =BR34+BR36+BR38 -> 14.535326 | ... DB39: =DB34+DB36+DB38 -> 70.263786 | DE39: Net Income | DF39: =SUMIF($C$5:$DC$5,DF$5,$C39:$DC39) -> 0 | DG39: =SUMIF($C$5:$DC$5,DG$5,$C39:$DC39) -> 0 | DH39: =SUMIF($C$5:$DC$5,DH$5,$C39:$DC39) -> 0 | DI39: =SUMIF($C$5:$DC$5,DI$5,$C39:$DC39) -> 0 | DJ39: =SUMIF($C$5:$DC$5,DJ$5,$C39:$DC39) -> 0 | DK39: =SUMIF($C$5:$DC$5,DK$5,$C39:$DC39) -> 0 | DL39: =SUMIF($C$5:$DC$5,DL$5,$C39:$DC39) -> 0 | DM39: =SUMIF($C$5:$DC$5,DM$5,$C39:$DC39) -> 0 | ... EE39: =SUMIF($C$5:$DC$5,EE$5,$C39:$DC39) -> 279.91104
B41: Operating Earnings Per Share | DE41: Operating Earnings Per Share
B42: EPS, Adjusted (Basic) | BK42: =IFERROR(BK$39/BK58,"") | BL42: =IFERROR(BL$39/BL58,"") | BM42: =IFERROR(BM$39/BM58,"") | BN42: =IFERROR(BN$39/BN58,"") | BO42: =IFERROR(BO$39/BO58,"") | BP42: =IFERROR(BP$39/BP58,"") | BQ42: =IFERROR(BQ$39/BQ58,"") | BR42: =IFERROR(BR$39/BR58,"") | ... DB42: =IFERROR(DB$39/DB58,"") -> 0.63944182 | DE42: EPS, Adjusted (Basic) | DF42: =DF$39/DF58 -> #DIV/0! | DG42: =DG$39/DG58 -> #DIV/0! | DH42: =DH$39/DH58 -> #DIV/0! | DI42: =DI$39/DI58 -> #DIV/0! | DJ42: =DJ$39/DJ58 -> #DIV/0! | DK42: =DK$39/DK58 -> #DIV/0! | DL42: =DL$39/DL58 -> #DIV/0! | DM42: =DM$39/DM58 -> #DIV/0! | ... EE42: =EE$39/EE58 -> 2.5473552
A43: x | B43: EPS, Adjusted (Diluted) | BK43: =IFERROR(BK$39/BK59,"") | BL43: =IFERROR(BL$39/BL59,"") | BM43: =IFERROR(BM$39/BM59,"") | BN43: =IFERROR(BN$39/BN59,"") | BO43: =IFERROR(BO$39/BO59,"") | BP43: =IFERROR(BP$39/BP59,"") | BQ43: =IFERROR(BQ$39/BQ59,"") | BR43: =IFERROR(BR$39/BR59,"") | ... DB43: =IFERROR(DB$39/DB59,"") -> 0.63256257 | DE43: EPS, Adjusted (Diluted) | DF43: =DF$39/DF59 -> #DIV/0! | DG43: =DG$39/DG59 -> #DIV/0! | DH43: =DH$39/DH59 -> #DIV/0! | DI43: =DI$39/DI59 -> #DIV/0! | DJ43: =DJ$39/DJ59 -> #DIV/0! | DK43: =DK$39/DK59 -> #DIV/0! | DL43: =DL$39/DL59 -> #DIV/0! | DM43: =DM$39/DM59 -> #DIV/0! | ... EE43: =EE$39/EE59 -> 2.5199503
A45: x | B45: EBITDA | BK45: =BK31-BK27 -> 20.03941 | BL45: =BL31-BL27 -> -7.2970977 | BM45: =BM31-BM27 -> 6.995616 | BN45: =BN31-BN27 -> 3.1593829 | BO45: =BO31-BO27 -> 8.9378806 | BP45: =BP31-BP27 -> 18.759821 | BQ45: =BQ31-BQ27 -> 17.875275 | BR45: =BR31-BR27 -> 26.157509 | ... CA45: =CA31-CA27 -> 56.852 | CB45: =CB29-CB27 -> 58.116 | CC45: =CC29-CC27 -> 53.624 | CD45: =CD29-CD27 -> 59.16527 | CE45: =CE29-CE27 -> 57.214836 | CF45: =CF29-CF27 -> 89.280262 | CG45: =CG29-CG27 -> 93.3754 | CH45: =CH29-CH27 -> 94.493062 | CI45: =CI29-CI27 -> 96.180921 | ... DB45: =DB29-DB27 -> 118.40025 | DE45: EBITDA | DF45: =SUMIF($C$5:$DC$5,DF$5,$C45:$DC45) -> 0 | DG45: =SUMIF($C$5:$DC$5,DG$5,$C45:$DC45) -> 0 | DH45: =SUMIF($C$5:$DC$5,DH$5,$C45:$DC45) -> 0 | DI45: =SUMIF($C$5:$DC$5,DI$5,$C45:$DC45) -> 0 | DJ45: =SUMIF($C$5:$DC$5,DJ$5,$C45:$DC45) -> 0 | DK45: =SUMIF($C$5:$DC$5,DK$5,$C45:$DC45) -> 0 | DL45: =SUMIF($C$5:$DC$5,DL$5,$C45:$DC45) -> 0 | DM45: =SUMIF($C$5:$DC$5,DM$5,$C45:$DC45) -> 0 | ... EE45: =SUMIF($C$5:$DC$5,EE$5,$C45:$DC45) -> 472.15275
B47: Adj. EBITDA | BK47: =+BK45+BK154 -> 20.03941 | BL47: =+BL45+BL154 -> -7.2970977 | BM47: =+BM45+BM154 -> 6.995616 | BN47: =+BN45+BN154 -> 3.1593829 | BO47: =+BO45+BO154 -> 8.9378806 | BP47: =+BP45+BP154 -> 18.759821 | BQ47: =+BQ45+BQ154 -> 17.875275 | BR47: =+BR45+BR154 -> 26.157509 | ... BZ47: =+BZ45+BZ154 -> 68.706 | CA47: =+CA45+CA154+CA155 -> 75.543 | CB47: =+CB45+CB154+CB155 -> 79.072 | CC47: =+CC45+CC154+CC155 -> 71.051 | CD47: =+CD45+CD154+CD155 -> 66.437233 | CE47: =+CE45+CE154+CE155 -> 64.158248 | CF47: =+CF45+CF154+CF155 -> 95.809991 | CG47: =+CG45+CG154+CG155 -> 99.937323 | CH47: =+CH45+CH154+CH155 -> 101.98101 | ... DB47: =+DB45+DB154+DB155 -> 138.18656 | DE47: Adj. EBITDA | DU47: =SUMIF($C$5:$DC$5,DU$5,$C47:$DC47) -> 22.897311 | DV47: =SUMIF($C$5:$DC$5,DV$5,$C47:$DC47) -> 71.730486 | DW47: =SUMIF($C$5:$DC$5,DW$5,$C47:$DC47) -> 261.11132 | DX47: =SUMIF($C$5:$DC$5,DX$5,$C47:$DC47) -> 321.963 | DY47: =SUMIF($C$5:$DC$5,DY$5,$C47:$DC47) -> 292.10323 | DZ47: =SUMIF($C$5:$DC$5,DZ$5,$C47:$DC47) -> 361.88657 | EA47: =SUMIF($C$5:$DC$5,EA$5,$C47:$DC47) -> 435.86073 | EB47: =SUMIF($C$5:$DC$5,EB$5,$C47:$DC47) -> 485.96772 | ... EE47: =SUMIF($C$5:$DC$5,EE$5,$C47:$DC47) -> 547.66709
B48: Cash Flow | BK48: =BK39-BK72 -> 5.6675487 | BL48: =BL39-BL72 -> -22.237889 | BM48: =BM39-BM72 -> -7.099579 | BN48: =BN39-BN72 -> -12.02299 | BO48: =BO39-BO72 -> 0.35025025 | BP48: =BP39-BP72 -> 8.4579566 | BQ48: =BQ39-BQ72 -> 3.375241 | BR48: =BR39-BR72 -> 22.734764 | ... DB48: =DB39-DB72 -> 96.463131 | DE48: Cash Flow | DF48: =SUMIF($C$5:$DC$5,DF$5,$C48:$DC48) -> 0 | DG48: =SUMIF($C$5:$DC$5,DG$5,$C48:$DC48) -> 0 | DH48: =SUMIF($C$5:$DC$5,DH$5,$C48:$DC48) -> 0 | DI48: =SUMIF($C$5:$DC$5,DI$5,$C48:$DC48) -> 0 | DJ48: =SUMIF($C$5:$DC$5,DJ$5,$C48:$DC48) -> 0 | DK48: =SUMIF($C$5:$DC$5,DK$5,$C48:$DC48) -> 0 | DL48: =SUMIF($C$5:$DC$5,DL$5,$C48:$DC48) -> 0 | DM48: =SUMIF($C$5:$DC$5,DM$5,$C48:$DC48) -> 0 | ... EE48: =SUMIF($C$5:$DC$5,EE$5,$C48:$DC48) -> 384.70842
B49: CFPS | BK49: =IFERROR(BK48/BK59,"") | BL49: =IFERROR(BL48/BL59,"") | BM49: =IFERROR(BM48/BM59,"") | BN49: =IFERROR(BN48/BN59,"") | BO49: =IFERROR(BO48/BO59,"") | BP49: =IFERROR(BP48/BP59,"") | BQ49: =IFERROR(BQ48/BQ59,"") | BR49: =IFERROR(BR48/BR59,"") | ... DB49: =IFERROR(DB48/DB59,"") -> 0.86842697 | DE49: CFPS | DF49: =SUMIF($C$5:$DC$5,DF$5,$C49:$DC49) -> 0 | DG49: =SUMIF($C$5:$DC$5,DG$5,$C49:$DC49) -> 0 | DH49: =SUMIF($C$5:$DC$5,DH$5,$C49:$DC49) -> 0 | DI49: =SUMIF($C$5:$DC$5,DI$5,$C49:$DC49) -> 0 | DJ49: =SUMIF($C$5:$DC$5,DJ$5,$C49:$DC49) -> 0 | DK49: =SUMIF($C$5:$DC$5,DK$5,$C49:$DC49) -> 0 | DL49: =SUMIF($C$5:$DC$5,DL$5,$C49:$DC49) -> 0 | DM49: =SUMIF($C$5:$DC$5,DM$5,$C49:$DC49) -> 0 | ... EE49: =SUMIF($C$5:$DC$5,EE$5,$C49:$DC49) -> 3.4634078
A50: x | B50: Free Cash Flow | BK50: ='Cash Flow'!BK25+'Cash Flow'!BK28 -> -2.383 | BL50: ='Cash Flow'!BL25+'Cash Flow'!BL28 -> -2.383 | BM50: ='Cash Flow'!BM25+'Cash Flow'!BM28 -> -2.383 | BN50: ='Cash Flow'!BN25+'Cash Flow'!BN28 -> -2.383 | BO50: ='Cash Flow'!BO25+'Cash Flow'!BO28 -> 2.744 | BP50: ='Cash Flow'!BP25+'Cash Flow'!BP28 -> -7.032 | BQ50: ='Cash Flow'!BQ25+'Cash Flow'!BQ28 -> -7.032 | BR50: ='Cash Flow'!BR25+'Cash Flow'!BR28 -> 2.58855 | ... DB50: ='Cash Flow'!DB25+'Cash Flow'!DB28 -> 164.87868 | DE50: Free Cash Flow | DF50: =SUMIF($C$5:$DC$5,DF$5,$C50:$DC50) -> 0 | DG50: =SUMIF($C$5:$DC$5,DG$5,$C50:$DC50) -> 0 | DH50: =SUMIF($C$5:$DC$5,DH$5,$C50:$DC50) -> 0 | DI50: =SUMIF($C$5:$DC$5,DI$5,$C50:$DC50) -> 0 | DJ50: =SUMIF($C$5:$DC$5,DJ$5,$C50:$DC50) -> 0 | DK50: =SUMIF($C$5:$DC$5,DK$5,$C50:$DC50) -> 0 | DL50: =SUMIF($C$5:$DC$5,DL$5,$C50:$DC50) -> 0 | DM50: =SUMIF($C$5:$DC$5,DM$5,$C50:$DC50) -> 0 | ... EE50: =SUMIF($C$5:$DC$5,EE$5,$C50:$DC50) -> 406.14191
B51: FCF/Share | BK51: =IFERROR(#REF!/BK59,"") | BL51: =IFERROR(#REF!/BL59,"") | BM51: =IFERROR(#REF!/BM59,"") | BN51: =IFERROR(#REF!/BN59,"") | BO51: =IFERROR(#REF!/BO59,"") | BP51: =IFERROR(#REF!/BP59,"") | BQ51: =IFERROR(#REF!/BQ59,"") | BR51: =IFERROR(#REF!/BR59,"") | ... CA51: =IFERROR(#REF!/CA59,"") | CC51: =IFERROR(#REF!/CC59,"") | CD51: =IFERROR(#REF!/CD59,"") | CE51: =IFERROR(#REF!/CE59,"") | CF51: =IFERROR(#REF!/CF59,"") | CG51: =IFERROR(#REF!/CG59,"") | CH51: =IFERROR(#REF!/CH59,"") | CI51: =IFERROR(#REF!/CI59,"") | CJ51: =IFERROR(#REF!/CJ59,"") | ... DB51: =IFERROR(#REF!/DB59,"") | DE51: FCF/Share | DF51: =SUMIF($C$5:$DC$5,DF$5,$C51:$DC51) -> 0 | DG51: =SUMIF($C$5:$DC$5,DG$5,$C51:$DC51) -> 0 | DH51: =SUMIF($C$5:$DC$5,DH$5,$C51:$DC51) -> 0 | DI51: =SUMIF($C$5:$DC$5,DI$5,$C51:$DC51) -> 0 | DJ51: =SUMIF($C$5:$DC$5,DJ$5,$C51:$DC51) -> 0 | DK51: =SUMIF($C$5:$DC$5,DK$5,$C51:$DC51) -> 0 | DL51: =SUMIF($C$5:$DC$5,DL$5,$C51:$DC51) -> 0 | DM51: =SUMIF($C$5:$DC$5,DM$5,$C51:$DC51) -> 0 | ... EE51: =SUMIF($C$5:$DC$5,EE$5,$C51:$DC51) -> 0
B52: FCF Yield (LTM) | BK52: =SUM(BH51:BK51)/#REF! -> #REF! | BL52: =SUM(BI51:BL51)/#REF! -> #REF! | BM52: =SUM(BJ51:BM51)/#REF! -> #REF! | BN52: =SUM(BK51:BN51)/#REF! -> #REF! | BO52: =SUM(BL51:BO51)/#REF! -> #REF! | BP52: =SUM(BM51:BP51)/#REF! -> #REF! | BQ52: =SUM(BN51:BQ51)/#REF! -> #REF! | BR52: =SUM(BO51:BR51)/#REF! -> #REF! | ... DB52: =SUM(CY51:DB51)/#REF! -> #REF! | DE52: FCF Yield | DF52: =DF51/#REF! -> #REF! | DG52: =DG51/#REF! -> #REF! | DH52: =DH51/#REF! -> #REF! | DI52: =DI51/#REF! -> #REF! | DJ52: =DJ51/#REF! -> #REF! | DK52: =DK51/#REF! -> #REF! | DL52: =DL51/#REF! -> #REF! | DM52: =DM51/#REF! -> #REF! | ... EE52: =EE51/#REF! -> #REF!
BZ54: =+BZ45/BZ11 -> 0.43165554 | CA54: =+CA47/CA11 -> 0.39209102 | CB54: =+CB47/CB11 -> 0.27501583 | CC54: =+CC47/CC11 -> 0.2333872 | CD54: =+CD47/CD11 -> 0.24351575 | CE54: =+CE47/CE11 -> 0.22382102 | CF54: =+CF47/CF11 -> 0.28952528 | CG54: =+CG47/CG11 -> 0.29627163 | CH54: =+CH47/CH11 -> 0.30114808 | ... DB54: =+DB47/DB11 -> 0.38178505 | DF54: =+DF45/DF11 -> #DIV/0! | DG54: =+DG45/DG11 -> #DIV/0! | DH54: =+DH45/DH11 -> #DIV/0! | DI54: =+DI45/DI11 -> #DIV/0! | DJ54: =+DJ45/DJ11 -> #DIV/0! | DK54: =+DK45/DK11 -> #DIV/0! | DL54: =+DL45/DL11 -> #DIV/0! | DM54: =+DM45/DM11 -> #DIV/0! | ... EE54: =+EE45/EE11 -> 0.32722605
CD55: =+CD47/CC47-1 -> -0.064935992 | DZ55: =+(DZ54-DY54)*1000 -> 43.104937
CD56: =+CD47-CC47 -> -4.6137672
A57: x | B57: Shares Outstanding | DE57: Shares Outstanding
B58: - Basic | BT58: =BS58+(BT59-BS59) -> 0 | BU58: =BT58+(BU59-BT59) -> 0 | BV58: =BU58+(BV59-BU59) -> 0 | BW58: 100 | BX58: =BW58+(BX59-BW59) -> 100 | BY58: =BX58+(BY59-BX59) -> 100 | BZ58: 99.566 | CA58: 102.931 | CB58: 111.064 | CC58: 109.883 | CD58: =+CC58-CD161 -> 109.883 | CE58: =+CD58-CE161 -> 109.883 | CF58: =+CE58-CF161 -> 109.883 | CG58: =+CF58-CG161 -> 109.883 | CH58: =+CG58-CH161 -> 109.883 | CI58: =+CH58-CI161 -> 109.883 | CJ58: =+CI58-CJ161 -> 109.883 | CK58: =+CJ58-CK161 -> 109.883 | ... DB58: =+DA58-DB161 -> 109.883 | DE58: - Basic | DF58: =AVERAGE(C58:F58) -> #DIV/0! | DG58: =AVERAGE(G58:J58) -> #DIV/0! | DH58: =AVERAGE(K58:N58) -> #DIV/0! | DI58: =AVERAGE(O58:R58) -> #DIV/0! | DJ58: =AVERAGE(S58:V58) -> #DIV/0! | DK58: =AVERAGE(W58:Z58) -> #DIV/0! | DL58: =AVERAGE(AA58:AD58) -> #DIV/0! | DM58: =AVERAGE(AE58:AH58) -> #DIV/0! | DN58: =AVERAGE(AI58:AL58) -> #DIV/0! | DO58: =AVERAGE(AM58:AP58) -> #DIV/0! | DP58: =AVERAGE(AQ58:AT58) -> #DIV/0! | DQ58: =AVERAGE(AU58:AX58) -> #DIV/0! | DR58: =AVERAGE(AY58:BB58) -> #DIV/0! | DS58: =AVERAGE(BC58:BF58) -> #DIV/0! | DT58: =AVERAGE(BG58:BJ58) -> #DIV/0! | DU58: =INDEX($C58:$DC58,MATCH(DU$5,$C$6:$DC$6,0)+3) -> 0 | DV58: =INDEX($C58:$DC58,MATCH(DV$5,$C$6:$DC$6,0)+3) -> 0 | DW58: =INDEX($C58:$DC58,MATCH(DW$5,$C$6:$DC$6,0)+3) -> 0 | DX58: =INDEX($C58:$DC58,MATCH(DX$5,$C$6:$DC$6,0)+3) -> 99.566 | DY58: =INDEX($C58:$DC58,MATCH(DY$5,$C$6:$DC$6,0)+3) -> 109.883 | DZ58: =INDEX($C58:$DC58,MATCH(DZ$5,$C$6:$DC$6,0)+3) -> 109.883 | EA58: =INDEX($C58:$DC58,MATCH(EA$5,$C$6:$DC$6,0)+3) -> 109.883 | EB58: =INDEX($C58:$DC58,MATCH(EB$5,$C$6:$DC$6,0)+3) -> 109.883 | ... EE58: =INDEX($C58:$DC58,MATCH(EE$5,$C$6:$DC$6,0)+3) -> 109.883
B59: - Diluted | BT59: =BS59 -> 0 | BU59: =BT59 -> 0 | BV59: =BU59 -> 0 | BW59: 100 | BX59: 100 | BY59: 100 | BZ59: 100.242 | CA59: 103.822 | CB59: 112.023 | CC59: 111.078 | CD59: =+CC59-CD161 -> 111.078 | CE59: =+CD59-CE161 -> 111.078 | CF59: =+CE59-CF161 -> 111.078 | CG59: =+CF59-CG161 -> 111.078 | CH59: =+CG59-CH161 -> 111.078 | CI59: =+CH59-CI161 -> 111.078 | CJ59: =+CI59-CJ161 -> 111.078 | CK59: =+CJ59-CK161 -> 111.078 | ... DB59: =+DA59-DB161 -> 111.078 | DE59: - Diluted | DF59: =AVERAGE(C59:F59) -> #DIV/0! | DG59: =AVERAGE(G59:J59) -> #DIV/0! | DH59: =AVERAGE(K59:N59) -> #DIV/0! | DI59: =AVERAGE(O59:R59) -> #DIV/0! | DJ59: =AVERAGE(S59:V59) -> #DIV/0! | DK59: =AVERAGE(W59:Z59) -> #DIV/0! | DL59: =AVERAGE(AA59:AD59) -> #DIV/0! | DM59: =AVERAGE(AE59:AH59) -> #DIV/0! | DN59: =AVERAGE(AI59:AL59) -> #DIV/0! | DO59: =AVERAGE(AM59:AP59) -> #DIV/0! | DP59: =AVERAGE(AQ59:AT59) -> #DIV/0! | DQ59: =AVERAGE(AU59:AX59) -> #DIV/0! | DR59: =AVERAGE(AY59:BB59) -> #DIV/0! | DS59: =AVERAGE(BC59:BF59) -> #DIV/0! | DT59: =AVERAGE(BG59:BJ59) -> #DIV/0! | DU59: =INDEX($C59:$DC59,MATCH(DU$5,$C$6:$DC$6,0)+3) -> 0 | DV59: =INDEX($C59:$DC59,MATCH(DV$5,$C$6:$DC$6,0)+3) -> 0 | DW59: =INDEX($C59:$DC59,MATCH(DW$5,$C$6:$DC$6,0)+3) -> 0 | DX59: =INDEX($C59:$DC59,MATCH(DX$5,$C$6:$DC$6,0)+3) -> 100.242 | DY59: =INDEX($C59:$DC59,MATCH(DY$5,$C$6:$DC$6,0)+3) -> 111.078 | DZ59: =INDEX($C59:$DC59,MATCH(DZ$5,$C$6:$DC$6,0)+3) -> 111.078 | EA59: =INDEX($C59:$DC59,MATCH(EA$5,$C$6:$DC$6,0)+3) -> 111.078 | EB59: =INDEX($C59:$DC59,MATCH(EB$5,$C$6:$DC$6,0)+3) -> 111.078 | ... EE59: =INDEX($C59:$DC59,MATCH(EE$5,$C$6:$DC$6,0)+3) -> 111.078
B61: Dividend Per Share | C61: 0 | D61: 0 | E61: 0 | F61: 0 | G61: 0 | H61: 0 | I61: 0 | J61: 0 | K61: 0 | L61: 0 | M61: 0 | N61: 0 | O61: 0 | P61: 0 | Q61: 0 | R61: 0 | S61: 0 | T61: 0 | U61: 0 | V61: 0 | W61: 0 | X61: 0 | Y61: 0 | Z61: 0 | AA61: 0 | AB61: 0 | AC61: 0 | AD61: 0 | AE61: 0 | AF61: 0 | AG61: 0 | AH61: 0 | AI61: 0 | AJ61: 0 | AK61: 0 | AL61: 0 | AM61: 0 | AN61: 0 | AO61: 0 | AP61: 0 | AQ61: 0 | AR61: 0 | AS61: 0 | AT61: 0 | AU61: 0 | AV61: 0 | AW61: 0 | AX61: 0 | AY61: 0 | AZ61: 0 | BA61: 0 | BB61: 0 | BC61: 0 | BD61: 0 | BE61: 0 | BF61: 0 | BG61: 0 | BH61: 0 | BI61: 0 | BJ61: 0 | BK61: 0 | BL61: 0 | BM61: 0 | BN61: 0 | BO61: 0 | BP61: 0 | BQ61: 0 | BR61: 0 | BS61: 0 | BT61: =+BS61 -> 0 | BU61: =+BT61 -> 0 | BV61: =+BU61 -> 0 | BW61: 0.15 | BX61: 0.2 | BY61: 0.2 | BZ61: 0.21 | CA61: 0.22 | CB61: 0.23 | CC61: 0.24 | CD61: =+CC61 -> 0.24 | CE61: =+CD61*1.05 -> 0.252 | CF61: =+CE61 -> 0.252 | CG61: =+CF61 -> 0.252 | CH61: =+CG61 -> 0.252 | CI61: =+CH61*1.05 -> 0.2646 | CJ61: =+CI61 -> 0.2646 | CK61: =+CJ61 -> 0.2646 | CL61: =+CK61 -> 0.2646 | CM61: =+CL61*1.05 -> 0.27783 | CN61: =+CM61 -> 0.27783 | CO61: =+CN61 -> 0.27783 | CP61: =+CO61 -> 0.27783 | CQ61: =+CP61*1.05 -> 0.2917215 | CR61: =+CQ61 -> 0.2917215 | CS61: =+CR61 -> 0.2917215 | CT61: =+CS61 -> 0.2917215 | CU61: =+CT61*1.05 -> 0.30630758 | CV61: =+CU61 -> 0.30630758 | CW61: =+CV61 -> 0.30630758 | CX61: =+CW61 -> 0.30630758 | CY61: =+CX61*1.05 -> 0.32162295 | CZ61: =+CY61 -> 0.32162295 | DA61: =+CZ61 -> 0.32162295 | DB61: =+DA61 -> 0.32162295 | DE61: Dividend Per Share | DF61: =SUM(C61:F61) -> 0 | DG61: =SUM(G61:J61) -> 0 | DH61: =SUM(K61:N61) -> 0 | DI61: =SUM(O61:R61) -> 0 | DJ61: =SUM(S61:V61) -> 0 | DK61: =SUM(W61:Z61) -> 0 | DL61: =SUM(AA61:AD61) -> 0 | DM61: =SUM(AE61:AH61) -> 0 | DN61: =SUM(AI61:AL61) -> 0 | DO61: =SUM(AM61:AP61) -> 0 | DP61: =SUM(AQ61:AT61) -> 0 | DQ61: =SUM(AU61:AX61) -> 0 | DR61: =SUM(AY61:BB61) -> 0 | DS61: =SUMIF($C$5:$DC$5,DS$5,$C61:$DC61) -> 0 | DT61: =SUMIF($C$5:$DC$5,DT$5,$C61:$DC61) -> 0 | DU61: =SUMIF($C$5:$DC$5,DU$5,$C61:$DC61) -> 0 | DV61: =SUMIF($C$5:$DC$5,DV$5,$C61:$DC61) -> 0 | DW61: =SUMIF($C$5:$DC$5,DW$5,$C61:$DC61) -> 0 | DX61: =SUMIF($C$5:$DC$5,DX$5,$C61:$DC61) -> 0.76 | DY61: =SUMIF($C$5:$DC$5,DY$5,$C61:$DC61) -> 0.93 | DZ61: =SUMIF($C$5:$DC$5,DZ$5,$C61:$DC61) -> 1.008 | ... EE61: =SUMIF($C$5:$DC$5,EE$5,$C61:$DC61) -> 1.2864918
A63: x | B63: Other Income Statement Items | CC63: 390 | CE63: =+CE61*4 -> 1.008 | DE63: Other Income Statement Items
B65: Cost of goods sold (products/services) | BK65: =-BK16 -> 18.2795 | BL65: =-BL16 -> 18.2795 | BM65: =-BM16 -> 18.2795 | BN65: =-BN16 -> 18.2795 | BO65: =-BO16 -> 18.92 | BP65: =-BP16 -> 21.912 | BQ65: =-BQ16 -> 21.912 | BR65: =-BR16 -> 21.912 | ... CS65: =-CS16 -> 218.12392 | CU65: =-CU16 -> 216.10841 | CV65: =-CV16 -> 217.14623 | CW65: =-CW16 -> 218.17873 | CX65: =-CX16 -> 218.18621 | CY65: =-CY16 -> 216.14588 | CZ65: =-CZ16 -> 217.17596 | DA65: =-DA16 -> 218.2056 | DB65: =-DB16 -> 218.21194 | DE65: Cost of goods sold (products/services) | DF65: =SUMIF($C$5:$DC$5,DF$5,$C65:$DC65) -> 0 | DG65: =SUMIF($C$5:$DC$5,DG$5,$C65:$DC65) -> 0 | DH65: =SUMIF($C$5:$DC$5,DH$5,$C65:$DC65) -> 0 | DI65: =SUMIF($C$5:$DC$5,DI$5,$C65:$DC65) -> 0 | DJ65: =SUMIF($C$5:$DC$5,DJ$5,$C65:$DC65) -> 0 | DK65: =SUMIF($C$5:$DC$5,DK$5,$C65:$DC65) -> 0 | DL65: =SUMIF($C$5:$DC$5,DL$5,$C65:$DC65) -> 0 | DM65: =SUMIF($C$5:$DC$5,DM$5,$C65:$DC65) -> 0 | ... EE65: =SUMIF($C$5:$DC$5,EE$5,$C65:$DC65) -> 869.73938
B66: % of revenue | C66: =C65/'Income Statement'!C11 -> #DIV/0! | D66: =D65/'Income Statement'!D11 -> #DIV/0! | E66: =E65/'Income Statement'!E11 -> #DIV/0! | F66: =F65/'Income Statement'!F11 -> #DIV/0! | G66: =G65/'Income Statement'!G11 -> #DIV/0! | H66: =H65/'Income Statement'!H11 -> #DIV/0! | I66: =I65/'Income Statement'!I11 -> #DIV/0! | J66: =J65/'Income Statement'!J11 -> #DIV/0! | ... DB66: =DB65/'Income Statement'!DB11 -> 0.60288104 | DE66: % of revenue | DG66: =DG65/'Balance Sheet'!DG$72 -> #DIV/0! | DH66: =DH65/'Balance Sheet'!DH$72 -> #DIV/0! | DI66: =DI65/'Balance Sheet'!DI$72 -> #DIV/0! | DJ66: =DJ65/'Balance Sheet'!DJ$72 -> #DIV/0! | DK66: =DK65/'Balance Sheet'!DK$72 -> #DIV/0! | DL66: =DL65/'Balance Sheet'!DL$72 -> #DIV/0! | DM66: =DM65/'Balance Sheet'!DM$72 -> #DIV/0! | DN66: =DN65/'Balance Sheet'!DN$72 -> #DIV/0! | ... EE66: =EE65/'Balance Sheet'!EE$72 -> 0.60277395
B67: R&E Expenses | BQ67: ='Balance Sheet'!BQ$72*BQ68 -> 0 | BR67: ='Balance Sheet'!BR$72*BR68 -> 0 | BS67: ='Balance Sheet'!BS$72*BS68 -> 0 | BT67: ='Balance Sheet'!BT$72*BT68 -> 0 | BU67: ='Balance Sheet'!BU$72*BU68 -> 0 | BV67: ='Balance Sheet'!BV$72*BV68 -> 0 | BW67: ='Balance Sheet'!BW$72*BW68 -> 0 | BX67: ='Balance Sheet'!BX$72*BX68 -> 0 | ... DB67: ='Balance Sheet'!DB$72*DB68 -> 0 | DE67: R&E Expenses | DF67: =SUMIF($C$5:$DC$5,DF$5,$C67:$DC67) -> 0 | DG67: =SUMIF($C$5:$DC$5,DG$5,$C67:$DC67) -> 0 | DH67: =SUMIF($C$5:$DC$5,DH$5,$C67:$DC67) -> 0 | DI67: =SUMIF($C$5:$DC$5,DI$5,$C67:$DC67) -> 0 | DJ67: =SUMIF($C$5:$DC$5,DJ$5,$C67:$DC67) -> 0 | DK67: =SUMIF($C$5:$DC$5,DK$5,$C67:$DC67) -> 0 | DL67: =SUMIF($C$5:$DC$5,DL$5,$C67:$DC67) -> 0 | DM67: =SUMIF($C$5:$DC$5,DM$5,$C67:$DC67) -> 0 | ... EE67: =SUMIF($C$5:$DC$5,EE$5,$C67:$DC67) -> 0
B68: % of revenue | C68: =C67/'Income Statement'!C$11 -> #DIV/0! | D68: =D67/'Income Statement'!D$11 -> #DIV/0! | E68: =E67/'Income Statement'!E$11 -> #DIV/0! | F68: =F67/'Income Statement'!F$11 -> #DIV/0! | G68: =G67/'Income Statement'!G$11 -> #DIV/0! | H68: =H67/'Income Statement'!H$11 -> #DIV/0! | I68: =I67/'Income Statement'!I$11 -> #DIV/0! | J68: =J67/'Income Statement'!J$11 -> #DIV/0! | ... BD68: =BD67/'Income Statement'!BD$11 -> #DIV/0! | BE68: =BE67/'Income Statement'!BE11 -> #DIV/0! | BF68: =BF67/'Income Statement'!BF11 -> #DIV/0! | BG68: =BG67/'Income Statement'!BG$11 -> #DIV/0! | BH68: =BH67/'Income Statement'!BH$11 -> #DIV/0! | BI68: =BI67/'Income Statement'!BI$11 -> #DIV/0! | BJ68: =BJ67/'Income Statement'!BJ$11 -> #DIV/0! | BK68: =BK67/'Income Statement'!BK$11 -> 0 | BL68: =BL67/'Income Statement'!BL$11 -> 0 | BM68: =BM67/'Income Statement'!BM$11 -> 0 | BN68: =BN67/'Income Statement'!BN$11 -> 0 | ... BP68: =BP67/'Income Statement'!BP$11 -> 0 | BQ68: =BM68 -> 0 | BR68: =BN68 -> 0 | BS68: =BO68 -> 0 | BT68: =BP68 -> 0 | BU68: =BQ68 -> 0 | BV68: =BR68 -> 0 | BW68: =BS68 -> 0 | BX68: =BT68 -> 0 | ... DB68: =CX68 -> 0 | DE68: % of revenue | DG68: =DG67/'Balance Sheet'!DG$72 -> #DIV/0! | DH68: =DH67/'Balance Sheet'!DH$72 -> #DIV/0! | DI68: =DI67/'Balance Sheet'!DI$72 -> #DIV/0! | DJ68: =DJ67/'Balance Sheet'!DJ$72 -> #DIV/0! | DK68: =DK67/'Balance Sheet'!DK$72 -> #DIV/0! | DL68: =DL67/'Balance Sheet'!DL$72 -> #DIV/0! | DM68: =DM67/'Balance Sheet'!DM$72 -> #DIV/0! | DN68: =DN67/'Balance Sheet'!DN$72 -> #DIV/0! | ... EE68: =EE67/'Balance Sheet'!EE$72 -> 0
B69: SG&A Expenses | BK69: =-BK24 -> 4.0907364 | BL69: =-BL24 -> 2.4430765 | BM69: =-BM24 -> 3.4044525 | BN69: =-BN24 -> 4.5680524 | BO69: =-BO24 -> 3.9740135 | BP69: =-BP24 -> 3.7569652 | BQ69: =-BQ24 -> 3.5100979 | BR69: =-BR24 -> 4.778099 | ... DB69: =-DB24 -> 25.336401 | DE69: SG&A Expenses | DF69: =SUMIF($C$5:$DC$5,DF$5,$C69:$DC69) -> 0 | DG69: =SUMIF($C$5:$DC$5,DG$5,$C69:$DC69) -> 0 | DH69: =SUMIF($C$5:$DC$5,DH$5,$C69:$DC69) -> 0 | DI69: =SUMIF($C$5:$DC$5,DI$5,$C69:$DC69) -> 0 | DJ69: =SUMIF($C$5:$DC$5,DJ$5,$C69:$DC69) -> 0 | DK69: =SUMIF($C$5:$DC$5,DK$5,$C69:$DC69) -> 0 | DL69: =SUMIF($C$5:$DC$5,DL$5,$C69:$DC69) -> 0 | DM69: =SUMIF($C$5:$DC$5,DM$5,$C69:$DC69) -> 0 | ... EE69: =SUMIF($C$5:$DC$5,EE$5,$C69:$DC69) -> 101.00263
B70: % of revenue | C70: =C69/'Income Statement'!C$11 -> #DIV/0! | D70: =D69/'Income Statement'!D$11 -> #DIV/0! | E70: =E69/'Income Statement'!E$11 -> #DIV/0! | F70: =F69/'Income Statement'!F$11 -> #DIV/0! | G70: =G69/'Income Statement'!G$11 -> #DIV/0! | H70: =H69/'Income Statement'!H$11 -> #DIV/0! | I70: =I69/'Income Statement'!I$11 -> #DIV/0! | J70: =J69/'Income Statement'!J$11 -> #DIV/0! | ... DB70: =DB69/'Income Statement'!DB$11 -> 0.07 | DE70: % of revenue | DG70: =DG69/'Balance Sheet'!DG$72 -> #DIV/0! | DH70: =DH69/'Balance Sheet'!DH$72 -> #DIV/0! | DI70: =DI69/'Balance Sheet'!DI$72 -> #DIV/0! | DJ70: =DJ69/'Balance Sheet'!DJ$72 -> #DIV/0! | DK70: =DK69/'Balance Sheet'!DK$72 -> #DIV/0! | DL70: =DL69/'Balance Sheet'!DL$72 -> #DIV/0! | DM70: =DM69/'Balance Sheet'!DM$72 -> #DIV/0! | DN70: =DN69/'Balance Sheet'!DN$72 -> #DIV/0! | ... EE70: =EE69/'Balance Sheet'!EE$72 -> 0.07
B72: Depreciation & Amortization | C72: =-'Cash Flow'!C11 -> 0 | D72: =-'Cash Flow'!D11 -> 0 | E72: =-'Cash Flow'!E11 -> 0 | F72: =-'Cash Flow'!F11 -> 0 | G72: =-'Cash Flow'!G11 -> 0 | H72: =-'Cash Flow'!H11 -> 0 | I72: =-'Cash Flow'!I11 -> 0 | J72: =-'Cash Flow'!J11 -> 0 | ... DB72: =-'Cash Flow'!DB11 -> -26.199345 | DE72: Depreciation & Amortization | DF72: =SUMIF($C$5:$DC$5,DF$5,$C72:$DC72) -> 0 | DG72: =SUMIF($C$5:$DC$5,DG$5,$C72:$DC72) -> 0 | DH72: =SUMIF($C$5:$DC$5,DH$5,$C72:$DC72) -> 0 | DI72: =SUMIF($C$5:$DC$5,DI$5,$C72:$DC72) -> 0 | DJ72: =SUMIF($C$5:$DC$5,DJ$5,$C72:$DC72) -> 0 | DK72: =SUMIF($C$5:$DC$5,DK$5,$C72:$DC72) -> 0 | DL72: =SUMIF($C$5:$DC$5,DL$5,$C72:$DC72) -> 0 | DM72: =SUMIF($C$5:$DC$5,DM$5,$C72:$DC72) -> 0 | ... EE72: =SUMIF($C$5:$DC$5,EE$5,$C72:$DC72) -> -104.79738
B73: Extraordinary Items | C73: =C76-C39 -> 0 | D73: =D76-D39 -> 0 | E73: =E76-E39 -> 0 | F73: =F76-F39 -> 0 | G73: =G76-G39 -> 0 | H73: =H76-H39 -> 0 | I73: =I76-I39 -> 0 | J73: =J76-J39 -> 0 | ... BP73: =BP76-BP39 -> -8.4579566 | BQ73: 0 | BR73: 0 | BS73: 0 | BT73: 0 | BU73: 0 | BV73: 0 | BW73: 0 | BX73: 0 | BY73: 0 | BZ73: 0 | CA73: 0 | CB73: 0 | CC73: 0 | CD73: 0 | CE73: 0 | CF73: 0 | CG73: 0 | CH73: 0 | CI73: 0 | CJ73: 0 | CK73: 0 | CL73: 0 | CM73: 0 | CN73: 0 | CO73: 0 | CP73: 0 | CQ73: 0 | CR73: 0 | CS73: 0 | CT73: 0 | CU73: 0 | CV73: 0 | CW73: 0 | CX73: 0 | CY73: 0 | CZ73: 0 | DA73: 0 | DB73: 0 | DE73: Extraordinary Items | DF73: =SUMIF($C$5:$DC$5,DF$5,$C73:$DC73) -> 0 | DG73: =SUMIF($C$5:$DC$5,DG$5,$C73:$DC73) -> 0 | DH73: =SUMIF($C$5:$DC$5,DH$5,$C73:$DC73) -> 0 | DI73: =SUMIF($C$5:$DC$5,DI$5,$C73:$DC73) -> 0 | DJ73: =SUMIF($C$5:$DC$5,DJ$5,$C73:$DC73) -> 0 | DK73: =SUMIF($C$5:$DC$5,DK$5,$C73:$DC73) -> 0 | DL73: =SUMIF($C$5:$DC$5,DL$5,$C73:$DC73) -> 0 | DM73: =SUMIF($C$5:$DC$5,DM$5,$C73:$DC73) -> 0 | ... EE73: =SUMIF($C$5:$DC$5,EE$5,$C73:$DC73) -> 0
B74: Discontinued Operations | O74: 38 | BM74: 0 | BN74: 0 | BO74: 0 | BP74: 0 | BQ74: 0 | BR74: 0 | BS74: 0 | BT74: 0 | BU74: 0 | BV74: 0 | BW74: 0 | BX74: 0 | BY74: 0 | BZ74: 0 | CA74: 0 | CB74: 0 | CC74: 0 | CD74: 0 | CE74: 0 | CF74: 0 | CG74: 0 | CH74: 0 | CI74: 0 | CJ74: 0 | CK74: 0 | CL74: 0 | CM74: 0 | CN74: 0 | CO74: 0 | CP74: 0 | CQ74: 0 | CR74: 0 | CS74: 0 | CT74: 0 | CU74: 0 | CV74: 0 | CW74: 0 | CX74: 0 | CY74: 0 | CZ74: 0 | DA74: 0 | DB74: 0 | DE74: Discontinued Operations | DF74: =SUMIF($C$5:$DC$5,DF$5,$C74:$DC74) -> 0 | DG74: =SUMIF($C$5:$DC$5,DG$5,$C74:$DC74) -> 0 | DH74: =SUMIF($C$5:$DC$5,DH$5,$C74:$DC74) -> 0 | DI74: =SUMIF($C$5:$DC$5,DI$5,$C74:$DC74) -> 38 | DJ74: =SUMIF($C$5:$DC$5,DJ$5,$C74:$DC74) -> 0 | DK74: =SUMIF($C$5:$DC$5,DK$5,$C74:$DC74) -> 0 | DL74: =SUMIF($C$5:$DC$5,DL$5,$C74:$DC74) -> 0 | DM74: =SUMIF($C$5:$DC$5,DM$5,$C74:$DC74) -> 0 | ... EE74: =SUMIF($C$5:$DC$5,EE$5,$C74:$DC74) -> 0
B76: Net Income GAAP | BQ76: =BQ39+BQ73+BQ74 -> 3.375241 | BR76: =BR39+BR73+BR74 -> 14.535326 | BS76: =BS39+BS73+BS74 -> 19.923692 | BT76: =BT39+BT73+BT74 -> 68.227221 | BU76: =BU39+BU73+BU74 -> 64.224102 | BV76: =BV39+BV73+BV74 -> 62.513217 | BW76: =BW39+BW73+BW74 -> 62.905 | BX76: =BX39+BX73+BX74 -> 71.211 | ... DB76: =DB39+DB73+DB74 -> 70.263786 | DE76: Net Income GAAP | DF76: =SUMIF($C$5:$DC$5,DF$5,$C76:$DC76) -> 0 | DG76: =SUMIF($C$5:$DC$5,DG$5,$C76:$DC76) -> 0 | DH76: =SUMIF($C$5:$DC$5,DH$5,$C76:$DC76) -> 0 | DI76: =SUMIF($C$5:$DC$5,DI$5,$C76:$DC76) -> 0 | DJ76: =SUMIF($C$5:$DC$5,DJ$5,$C76:$DC76) -> 0 | DK76: =SUMIF($C$5:$DC$5,DK$5,$C76:$DC76) -> 0 | DL76: =SUMIF($C$5:$DC$5,DL$5,$C76:$DC76) -> 0 | DM76: =SUMIF($C$5:$DC$5,DM$5,$C76:$DC76) -> 0 | ... EE76: =SUMIF($C$5:$DC$5,EE$5,$C76:$DC76) -> 279.91104
B77: EPS GAAP (Basic) | C77: =C$76/C58 -> #DIV/0! | D77: =D$76/D58 -> #DIV/0! | E77: =E$76/E58 -> #DIV/0! | F77: =F$76/F58 -> #DIV/0! | G77: =G$76/G58 -> #DIV/0! | H77: =H$76/H58 -> #DIV/0! | I77: =I$76/I58 -> #DIV/0! | J77: =J$76/J58 -> #DIV/0! | ... DB77: =DB$76/DB58 -> 0.63944182 | DE77: EPS GAAP (Basic) | DF77: =SUMIF($C$5:$DC$5,DF$5,$C77:$DC77) -> #DIV/0! | DG77: =SUMIF($C$5:$DC$5,DG$5,$C77:$DC77) -> #DIV/0! | DH77: =SUMIF($C$5:$DC$5,DH$5,$C77:$DC77) -> #DIV/0! | DI77: =SUMIF($C$5:$DC$5,DI$5,$C77:$DC77) -> #DIV/0! | DJ77: =SUMIF($C$5:$DC$5,DJ$5,$C77:$DC77) -> #DIV/0! | DK77: =SUMIF($C$5:$DC$5,DK$5,$C77:$DC77) -> #DIV/0! | DL77: =SUMIF($C$5:$DC$5,DL$5,$C77:$DC77) -> #DIV/0! | DM77: =SUMIF($C$5:$DC$5,DM$5,$C77:$DC77) -> #DIV/0! | ... EE77: =SUMIF($C$5:$DC$5,EE$5,$C77:$DC77) -> 2.5473552
A78: x | B78: EPS GAAP (Diluted) | C78: =C$76/C59 -> #DIV/0! | D78: =D$76/D59 -> #DIV/0! | E78: =E$76/E59 -> #DIV/0! | F78: =F$76/F59 -> #DIV/0! | G78: =G$76/G59 -> #DIV/0! | H78: =H$76/H59 -> #DIV/0! | I78: =I$76/I59 -> #DIV/0! | J78: =J$76/J59 -> #DIV/0! | ... DB78: =DB$76/DB59 -> 0.63256257 | DE78: EPS GAAP (Diluted) | DF78: =SUMIF($C$5:$DC$5,DF$5,$C78:$DC78) -> #DIV/0! | DG78: =SUMIF($C$5:$DC$5,DG$5,$C78:$DC78) -> #DIV/0! | DH78: =SUMIF($C$5:$DC$5,DH$5,$C78:$DC78) -> #DIV/0! | DI78: =SUMIF($C$5:$DC$5,DI$5,$C78:$DC78) -> #DIV/0! | DJ78: =SUMIF($C$5:$DC$5,DJ$5,$C78:$DC78) -> #DIV/0! | DK78: =SUMIF($C$5:$DC$5,DK$5,$C78:$DC78) -> #DIV/0! | DL78: =SUMIF($C$5:$DC$5,DL$5,$C78:$DC78) -> #DIV/0! | DM78: =SUMIF($C$5:$DC$5,DM$5,$C78:$DC78) -> #DIV/0! | ... EE78: =SUMIF($C$5:$DC$5,EE$5,$C78:$DC78) -> 2.5199503
B80: Segment EBITDA
B81: Sand Segment | BC81: =Sand!C31 -> 0 | BD81: =Sand!D31 -> 0 | BE81: =Sand!E31 -> 0 | BF81: =Sand!F31 -> 0 | BG81: =Sand!G31 -> 16.097629 | BH81: =Sand!H31 -> 17.035081 | BI81: =Sand!I31 -> 11.216365 | BJ81: =Sand!J31 -> 10.031673 | ... DB81: =Sand!BB31 -> 74.125278
B82: Logistics Segment | BC82: =Logistics!C27 -> 0 | BD82: =Logistics!D27 -> 0 | BE82: =Logistics!E27 -> 0 | BF82: =Logistics!F27 -> 0 | BG82: =Logistics!G27 -> 0 | BH82: =Logistics!H27 -> 0 | BI82: =Logistics!I27 -> 0 | BJ82: =Logistics!J27 -> 0 | ... DB82: =Logistics!BB27 -> -21.683257
B83: Segment Total EBITDA | BC83: =SUM(BC81:BC82) -> 0 | BD83: =SUM(BD81:BD82) -> 0 | BE83: =SUM(BE81:BE82) -> 0 | BF83: =SUM(BF81:BF82) -> 0 | BG83: =SUM(BG81:BG82) -> 16.097629 | BH83: =SUM(BH81:BH82) -> 17.035081 | BI83: =SUM(BI81:BI82) -> 11.216365 | BJ83: =SUM(BJ81:BJ82) -> 10.031673 | ... DB83: =SUM(DB81:DB82) -> 52.44202
B84: Variance (%) | BC84: =IFERROR(BC45/BC83-1,"") | BD84: =IFERROR(BD45/BD83-1,"") | BE84: =IFERROR(BE45/BE83-1,"") | BF84: =IFERROR(BF45/BF83-1,"") | BG84: =IFERROR(BG45/BG83-1,"") -> -1 | BH84: =IFERROR(BH45/BH83-1,"") -> -1 | BI84: =IFERROR(BI45/BI83-1,"") -> -1 | BJ84: =IFERROR(BJ45/BJ83-1,"") -> -1 | ... DB84: =IFERROR(DB45/DB83-1,"") -> 1.2577362
B86: Operating Data
B87: Realized price per ton | BG87: =BG11*1000000/BG88 -> 0 | BH87: =BH11*1000000/BH88 -> 0 | BI87: =BI11*1000000/BI88 -> 0 | BJ87: =BJ11*1000000/BJ88 -> 0 | BK87: =BK11*1000000/BK88 -> 20.186672 | BL87: =BL11*1000000/BL88 -> 24.544612 | BM87: =BM11*1000000/BM88 -> 17.473197 | BN87: =BN11*1000000/BN88 -> 13.217491 | ... BV87: =BV11*1000000/BV88 -> 56.039176 | BW87: =BV87 -> 56.039176 | BX87: =BW87 -> 56.039176 | BY87: =BX87 -> 56.039176 | BZ87: =BY87 -> 56.039176 | CA87: =BZ87 -> 56.039176 | CB87: =CA87 -> 56.039176 | CC87: =CB87 -> 56.039176 | CD87: =CC87 -> 56.039176 | ... DB87: =DA87 -> 56.039176
B88: Sales Volumes (tons) | BG88: 1433062 | BH88: 1435847 | BI88: 1477152 | BJ88: 1487758.5 | BK88: 2116354.1 | BL88: 559714.65 | BM88: 1659230.9 | BN88: 1991258.1 | BO88: 1874591.3 | BP88: 1964958 | BQ88: 1986450.8 | BR88: 2454860.5 | BS88: 2320563.2 | BT88: 2573687.5 | BU88: 2625377 | BV88: 2674279.9 | BW88: =BV88*(1+BW91+BW92) -> 2774198.4 | BX88: =BW88*(1+BX91+BX92) -> 2888026.3 | BY88: =BX88*(1+BY91+BY92) -> 2938804 | BZ88: =BY88*(1+BZ91+BZ92) -> 2796148.7 | CA88: =BZ88*(1+CA91+CA92) -> 2829180.8 | CB88: =CA88*(1+CB91+CB92) -> 2726546.8 | CC88: =CB88*(1+CC91+CC92) -> 2755296.1 | CD88: =CC88*(1+CD91+CD92) -> 2674099.1 | ... DB88: =DA88*(1+DB91+DB92) -> 3296607
B90: US Frac Count (MAJOR BANK Forecast) | BC90: 420 | BD90: 479.15385 | BE90: 464.15385 | BF90: 401.76923 | BG90: 410.61538 | BH90: 405.07692 | BI90: 376.76923 | BJ90: 362.61538 | BK90: 317.69231 | BL90: 88.615385 | BM90: 79.076923 | BN90: 131.85714 | BO90: 157.91667 | BP90: 221.23077 | BQ90: 241.38462 | BR90: 262.5 | BS90: 268 | BT90: 283.26509 | BU90: 280.75859 | BV90: 277.95855 | BW90: 286.95405 | BX90: 297.29327 | BY90: 301.03386 | BZ90: 284.91592 | CA90: 286.85717 | CB90: 275.01659 | CC90: 276.54134 | CD90: 267.00912 | CE90: 276.15623 | CF90: 280.26731 | CG90: 284.63191 | CH90: 274.91825 | CI90: 284.45538 | CJ90: 288.90095 | CK90: 293.28613 | CL90: 283.16436 | CM90: 293.86173 | CN90: 298.37562 | CO90: 302.74023 | CP90: 292.15254 | CQ90: 293.86173 | CR90: 298.37562 | CS90: 302.74023 | CT90: 292.15254 | CU90: 293.86173 | CV90: 298.37562 | CW90: 302.74023 | CX90: 292.15254 | CY90: 293.86173 | CZ90: 298.37562 | DA90: 302.74023 | DB90: 292.15254
B91: Change (%) | BD91: =BD90/BC90-1 -> 0.14084249 | BE91: =BE90/BD90-1 -> -0.031305185 | BF91: =BF90/BE90-1 -> -0.13440504 | BG91: =BG90/BF90-1 -> 0.022017997 | BH91: =BH90/BG90-1 -> -0.013488198 | BI91: =BI90/BH90-1 -> -0.069882264 | BJ91: =BJ90/BI90-1 -> -0.037566354 | BK91: =BK90/BJ90-1 -> -0.1238863 | ... DB91: =DB90/DA90-1 -> -0.034972846
B92: Market Share Growth | BD92: 0 | BE92: 0 | BF92: 0 | BG92: 0 | BH92: 0 | BI92: 0 | BJ92: 0 | BK92: 0 | BL92: 0 | BM92: 0 | BN92: 0 | BO92: 0 | BP92: 0 | BQ92: 0 | BR92: 0 | BS92: 0 | BT92: 0.005 | BU92: 0.005 | BV92: 0.005 | BW92: 0.005 | BX92: 0.005 | BY92: 0.005 | BZ92: 0.005 | CA92: 0.005 | CB92: 0.005 | CC92: 0.005 | CD92: 0.005 | CE92: 0.005 | CF92: 0.005 | CG92: 0.005 | CH92: 0.005 | CI92: 0.005 | CJ92: 0.005 | CK92: 0.005 | CL92: 0.005 | CM92: 0.005 | CN92: 0.005 | CO92: 0.005 | CP92: 0.005 | CQ92: 0.005 | CR92: 0.005 | CS92: 0.005 | CT92: 0.005 | CU92: 0.005 | CV92: 0.005 | CW92: 0.005 | CX92: 0.005 | CY92: 0.005 | CZ92: 0.005 | DA92: 0.005 | DB92: 0.005
B94: Assets (10K) | BN94: 458.317 | BO94: =BN94-BO95+BO96 -> 465.72347 | BP94: =BO94-BP95+BP96 -> 478.92082 | BQ94: =BP94-BQ95+BQ96 -> 492.12788 | BR94: =BQ94-BR95+BR96 -> 505.67889 | BS94: 461.09 | BT94: 470.82171 | BU94: 507.21506 | BV94: =BU94-BU95+BU96 -> 550.69858 | BW94: =BV94-BV95+BV96 -> 593.63638 | BX94: =BW94-BW95+BW96 -> 663.09538 | BY94: =BX94-BX95+BX96 -> 758.42338 | BZ94: =BY94-BY95+BY96 -> 867.50238 | CA94: =BZ94-BZ95+BZ96 -> 998.92038 | CB94: =CA94-CA95+CA96 -> 1111.5814 | CC94: =CB94-CB95+CB96 -> 1252.3984 | ... DB94: =DA94-DA95+DA96 -> 2628.0846
B95: Depreciation (10K) | BK95: =BK27 -> -5.6177018 | BL95: =BL27 -> -4.7066194 | BM95: =BM27 -> -5.4692377 | BN95: =BN27 -> -5.7231352 | BO95: =BO27 -> -5.6814658 | BP95: =BP27 -> -6.1653538 | BQ95: =BQ27 -> -6.1750633 | BR95: =BR27 -> -6.5190106 | ... CC95: =CC27 -> -26.069 | CD95: =+CC95*1.005 -> -26.199345 | CE95: =+CD95 -> -26.199345 | CF95: =+CE95 -> -26.199345 | CG95: =+CF95 -> -26.199345 | CH95: =+CG95 -> -26.199345 | CI95: =+CH95 -> -26.199345 | CJ95: =+CI95 -> -26.199345 | CK95: =+CJ95 -> -26.199345 | CL95: =+CK95 -> -26.199345 | ... DB95: =+DA95 -> -26.199345
B96: Capex (10K) | BK96: =-'Cash Flow'!BK28 -> 2.383 | BL96: =-'Cash Flow'!BL28 -> 2.383 | BM96: =-'Cash Flow'!BM28 -> 2.383 | BN96: =-'Cash Flow'!BN28 -> 2.383 | BO96: =-'Cash Flow'!BO28 -> 1.725 | BP96: =-'Cash Flow'!BP28 -> 7.032 | BQ96: =-'Cash Flow'!BQ28 -> 7.032 | BR96: =-'Cash Flow'!BR28 -> 7.032 | ... DB96: =-'Cash Flow'!DB28 -> 18.99375
B101: Key Metrics | DE101: Key Metrics
B103: Line Items | DE103: Line Items
B104: Revenue | C104: =C11 -> 0 | D104: =D11 -> 0 | E104: =E11 -> 0 | F104: =F11 -> 0 | G104: =G11 -> 0 | H104: =H11 -> 0 | I104: =I11 -> 0 | J104: =J11 -> 0 | ... CH104: =CH11 -> 338.64074 | DE104: Revenue | DF104: =DF11 -> 0 | DG104: =DG11 -> 0 | DH104: =DH11 -> 0 | DI104: =DI11 -> 0 | DJ104: =DJ11 -> 0 | DK104: =DK11 -> 0 | DL104: =DL11 -> 0 | DM104: =DM11 -> 0 | ... EE104: =EE11 -> 1442.8948
B105: EBITDA | C105: =C45 -> 0 | D105: =D45 -> 0 | E105: =E45 -> 0 | F105: =F45 -> 0 | G105: =G45 -> 0 | H105: =H45 -> 0 | I105: =I45 -> 0 | J105: =J45 -> 0 | ... CH105: =CH45 -> 94.493062 | DE105: EBITDA | DF105: =DF45 -> 0 | DG105: =DG45 -> 0 | DH105: =DH45 -> 0 | DI105: =DI45 -> 0 | DJ105: =DJ45 -> 0 | DK105: =DK45 -> 0 | DL105: =DL45 -> 0 | DM105: =DM45 -> 0 | ... EE105: =EE45 -> 472.15275
B106: EBIT | C106: =C31 -> 0 | D106: =D31 -> 0 | E106: =E31 -> 0 | F106: =F31 -> 0 | G106: =G31 -> 0 | H106: =H31 -> 0 | I106: =I31 -> 0 | J106: =J31 -> 0 | ... CH106: =CH31 -> 68.293717 | DE106: EBIT | DF106: =DF31 -> 0 | DG106: =DG31 -> 0 | DH106: =DH31 -> 0 | DI106: =DI31 -> 0 | DJ106: =DJ31 -> 0 | DK106: =DK31 -> 0 | DL106: =DL31 -> 0 | DM106: =DM31 -> 0 | ... EE106: =EE31 -> 367.35537
B107: Interest Expense (Net) | C107: =#REF!+C32 -> #REF! | D107: =#REF!+D32 -> #REF! | E107: =#REF!+E32 -> #REF! | F107: =#REF!+F32 -> #REF! | G107: =#REF!+G32 -> #REF! | H107: =#REF!+H32 -> #REF! | I107: =#REF!+I32 -> #REF! | J107: =#REF!+J32 -> #REF! | ... CH107: =#REF!+CH32 -> #REF! | DE107: Interest Expense | DF107: =#REF!+DF32 -> #REF! | DG107: =#REF!+DG32 -> #REF! | DH107: =#REF!+DH32 -> #REF! | DI107: =#REF!+DI32 -> #REF! | DJ107: =#REF!+DJ32 -> #REF! | DK107: =#REF!+DK32 -> #REF! | DL107: =#REF!+DL32 -> #REF! | DM107: =#REF!+DM32 -> #REF! | ... EE107: =#REF!+EE32 -> #REF!
B108: Net Income | C108: =C39 -> 0 | D108: =D39 -> 0 | E108: =E39 -> 0 | F108: =F39 -> 0 | G108: =G39 -> 0 | H108: =H39 -> 0 | I108: =I39 -> 0 | J108: =J39 -> 0 | ... CH108: =CH39 -> 51.377109 | DE108: Net Income | DF108: =DF39 -> 0 | DG108: =DG39 -> 0 | DH108: =DH39 -> 0 | DI108: =DI39 -> 0 | DJ108: =DJ39 -> 0 | DK108: =DK39 -> 0 | DL108: =DL39 -> 0 | DM108: =DM39 -> 0 | ... EE108: =EE39 -> 279.91104
B109: Basic Shares Outstanding | C109: =C58 -> 0 | D109: =D58 -> 0 | E109: =E58 -> 0 | F109: =F58 -> 0 | G109: =G58 -> 0 | H109: =H58 -> 0 | I109: =I58 -> 0 | J109: =J58 -> 0 | ... DB109: =DB58 -> 109.883 | DE109: Basic Shares Outstanding | DF109: =DF58 -> #DIV/0! | DG109: =DG58 -> #DIV/0! | DH109: =DH58 -> #DIV/0! | DI109: =DI58 -> #DIV/0! | DJ109: =DJ58 -> #DIV/0! | DK109: =DK58 -> #DIV/0! | DL109: =DL58 -> #DIV/0! | DM109: =DM58 -> #DIV/0! | ... EE109: =EE58 -> 109.883
B110: Diluted Shares Outstanding | C110: =C59 -> 0 | D110: =D59 -> 0 | E110: =E59 -> 0 | F110: =F59 -> 0 | G110: =G59 -> 0 | H110: =H59 -> 0 | I110: =I59 -> 0 | J110: =J59 -> 0 | ... DB110: =DB59 -> 111.078 | DE110: Diluted Shares Outstanding | DF110: =DF59 -> #DIV/0! | DG110: =DG59 -> #DIV/0! | DH110: =DH59 -> #DIV/0! | DI110: =DI59 -> #DIV/0! | DJ110: =DJ59 -> #DIV/0! | DK110: =DK59 -> #DIV/0! | DL110: =DL59 -> #DIV/0! | DM110: =DM59 -> #DIV/0! | ... EE110: =EE59 -> 111.078
B111: Total Debt | C111: ='Balance Sheet'!C37+'Balance Sheet'!C31 -> 0 | D111: ='Balance Sheet'!D37+'Balance Sheet'!D31 -> 0 | E111: ='Balance Sheet'!E37+'Balance Sheet'!E31 -> 0 | F111: ='Balance Sheet'!F37+'Balance Sheet'!F31 -> 0 | G111: ='Balance Sheet'!G37+'Balance Sheet'!G31 -> 0 | H111: ='Balance Sheet'!H37+'Balance Sheet'!H31 -> 0 | I111: ='Balance Sheet'!I37+'Balance Sheet'!I31 -> 0 | J111: ='Balance Sheet'!J37+'Balance Sheet'!J31 -> 0 | ... CH111: ='Balance Sheet'!CH37+'Balance Sheet'!CH31 -> 435.262 | DE111: Total Debt | DF111: ='Balance Sheet'!DF37+'Balance Sheet'!DF31 -> 0 | DG111: ='Balance Sheet'!DG37+'Balance Sheet'!DG31 -> 0 | DH111: ='Balance Sheet'!DH37+'Balance Sheet'!DH31 -> 0 | DI111: ='Balance Sheet'!DI37+'Balance Sheet'!DI31 -> 0 | DJ111: ='Balance Sheet'!DJ37+'Balance Sheet'!DJ31 -> 0 | DK111: ='Balance Sheet'!DK37+'Balance Sheet'!DK31 -> 0 | DL111: ='Balance Sheet'!DL37+'Balance Sheet'!DL31 -> 0 | DM111: ='Balance Sheet'!DM37+'Balance Sheet'!DM31 -> 0 | ... EE111: ='Balance Sheet'!EE37+'Balance Sheet'!EE31 -> 275.262
B112: Cash | C112: ='Balance Sheet'!C10 -> 0 | D112: ='Balance Sheet'!D10 -> 0 | E112: ='Balance Sheet'!E10 -> 0 | F112: ='Balance Sheet'!F10 -> 0 | G112: ='Balance Sheet'!G10 -> 0 | H112: ='Balance Sheet'!H10 -> 0 | I112: ='Balance Sheet'!I10 -> 0 | J112: ='Balance Sheet'!J10 -> 0 | ... CH112: ='Balance Sheet'!CH10 -> 156.85387 | DE112: Cash | DF112: ='Balance Sheet'!DF10 -> 0 | DG112: ='Balance Sheet'!DG10 -> 0 | DH112: ='Balance Sheet'!DH10 -> 0 | DI112: ='Balance Sheet'!DI10 -> 0 | DJ112: ='Balance Sheet'!DJ10 -> 0 | DK112: ='Balance Sheet'!DK10 -> 0 | DL112: ='Balance Sheet'!DL10 -> 0 | DM112: ='Balance Sheet'!DM10 -> 0 | ... EE112: ='Balance Sheet'!EE10 -> 1200.9385
B113: Net Debt | C113: =C111-C112 -> 0 | D113: =D111-D112 -> 0 | E113: =E111-E112 -> 0 | F113: =F111-F112 -> 0 | G113: =G111-G112 -> 0 | H113: =H111-H112 -> 0 | I113: =I111-I112 -> 0 | J113: =J111-J112 -> 0 | ... CH113: =CH111-CH112 -> 278.40813 | DE113: Net Debt | DF113: =DF111-DF112 -> 0 | DG113: =DG111-DG112 -> 0 | DH113: =DH111-DH112 -> 0 | DI113: =DI111-DI112 -> 0 | DJ113: =DJ111-DJ112 -> 0 | DK113: =DK111-DK112 -> 0 | DL113: =DL111-DL112 -> 0 | DM113: =DM111-DM112 -> 0 | ... EE113: =EE111-EE112 -> -925.67652
B114: Total Assets | C114: ='Balance Sheet'!C25 -> 0 | D114: ='Balance Sheet'!D25 -> 0 | E114: ='Balance Sheet'!E25 -> 0 | F114: ='Balance Sheet'!F25 -> 0 | G114: ='Balance Sheet'!G25 -> 0 | H114: ='Balance Sheet'!H25 -> 0 | I114: ='Balance Sheet'!I25 -> 0 | J114: ='Balance Sheet'!J25 -> 0 | ... CH114: ='Balance Sheet'!CH25 -> 2122.2441 | DE114: Total Assets | DF114: ='Balance Sheet'!DF25 -> 0 | DG114: ='Balance Sheet'!DG25 -> 0 | DH114: ='Balance Sheet'!DH25 -> 0 | DI114: ='Balance Sheet'!DI25 -> 0 | DJ114: ='Balance Sheet'!DJ25 -> 0 | DK114: ='Balance Sheet'!DK25 -> 0 | DL114: ='Balance Sheet'!DL25 -> 0 | DM114: ='Balance Sheet'!DM25 -> 0 | ... EE114: ='Balance Sheet'!EE25 -> 3178.2344
B115: Equity | C115: ='Balance Sheet'!C49 -> 0 | D115: ='Balance Sheet'!D49 -> 0 | E115: ='Balance Sheet'!E49 -> 0 | F115: ='Balance Sheet'!F49 -> 0 | G115: ='Balance Sheet'!G49 -> 0 | H115: ='Balance Sheet'!H49 -> 0 | I115: ='Balance Sheet'!I49 -> 0 | J115: ='Balance Sheet'!J49 -> 0 | ... CH115: ='Balance Sheet'!CH49 -> 1118.5068 | DE115: Equity | DF115: ='Balance Sheet'!DF49 -> 0 | DG115: ='Balance Sheet'!DG49 -> 0 | DH115: ='Balance Sheet'!DH49 -> 0 | DI115: ='Balance Sheet'!DI49 -> 0 | DJ115: ='Balance Sheet'!DJ49 -> 0 | DK115: ='Balance Sheet'!DK49 -> 0 | DL115: ='Balance Sheet'!DL49 -> 0 | DM115: ='Balance Sheet'!DM49 -> 0 | ... EE115: ='Balance Sheet'!EE49 -> 1901.3853
B117: Interest Rate | C117: =-C107*4/C111 -> #REF! | D117: =-D107*4/D111 -> #REF! | E117: =-E107*4/E111 -> #REF! | F117: =-F107*4/F111 -> #REF! | G117: =-G107*4/G111 -> #REF! | H117: =-H107*4/H111 -> #REF! | I117: =-I107*4/I111 -> #REF! | J117: =-J107*4/J111 -> #REF! | ... CH117: =-CH107*4/CH111 -> #REF! | DE117: Interest Rate | DF117: =-DF107/DF111 -> #REF! | DG117: =-DG107/DG111 -> #REF! | DH117: =-DH107/DH111 -> #REF! | DI117: =-DI107/DI111 -> #REF! | DJ117: =-DJ107/DJ111 -> #REF! | DK117: =-DK107/DK111 -> #REF! | DL117: =-DL107/DL111 -> #REF! | DM117: =-DM107/DM111 -> #REF! | ... EE117: =-EE107/EE111 -> #REF!
B119: Leverage | DE119: Leverage
B120: Debt/Capital | C120: =C111/(C111+C115) -> #DIV/0! | D120: =D111/(D111+D115) -> #DIV/0! | E120: =E111/(E111+E115) -> #DIV/0! | F120: =F111/(F111+F115) -> #DIV/0! | G120: =G111/(G111+G115) -> #DIV/0! | H120: =H111/(H111+H115) -> #DIV/0! | I120: =I111/(I111+I115) -> #DIV/0! | J120: =J111/(J111+J115) -> #DIV/0! | ... CH120: =CH111/(CH111+CH115) -> 0.28013306 | DE120: Debt/Capital | DF120: =DF111/(DF111+DF115) -> #DIV/0! | DG120: =DG111/(DG111+DG115) -> #DIV/0! | DH120: =DH111/(DH111+DH115) -> #DIV/0! | DI120: =DI111/(DI111+DI115) -> #DIV/0! | DJ120: =DJ111/(DJ111+DJ115) -> #DIV/0! | DK120: =DK111/(DK111+DK115) -> #DIV/0! | DL120: =DL111/(DL111+DL115) -> #DIV/0! | DM120: =DM111/(DM111+DM115) -> #DIV/0! | ... EE120: =EE111/(EE111+EE115) -> 0.12646146
B121: Net Debt/Capital | C121: =C113/(C111+C115) -> #DIV/0! | D121: =D113/(D111+D115) -> #DIV/0! | E121: =E113/(E111+E115) -> #DIV/0! | F121: =F113/(F111+F115) -> #DIV/0! | G121: =G113/(G111+G115) -> #DIV/0! | H121: =H113/(H111+H115) -> #DIV/0! | I121: =I113/(I111+I115) -> #DIV/0! | J121: =J113/(J111+J115) -> #DIV/0! | ... CH121: =CH113/(CH111+CH115) -> 0.17918247 | DE121: Net Debt/Capital | DF121: =DF113/(DF111+DF115) -> #DIV/0! | DG121: =DG113/(DG111+DG115) -> #DIV/0! | DH121: =DH113/(DH111+DH115) -> #DIV/0! | DI121: =DI113/(DI111+DI115) -> #DIV/0! | DJ121: =DJ113/(DJ111+DJ115) -> #DIV/0! | DK121: =DK113/(DK111+DK115) -> #DIV/0! | DL121: =DL113/(DL111+DL115) -> #DIV/0! | DM121: =DM113/(DM111+DM115) -> #DIV/0! | ... EE121: =EE113/(EE111+EE115) -> -0.4252763
B122: Net Debt/EBITDA | C122: =C113/(C105*4) -> #DIV/0! | D122: =D113/(D105*4) -> #DIV/0! | E122: =E113/(E105*4) -> #DIV/0! | F122: =F113/(F105*4) -> #DIV/0! | G122: =G113/(G105*4) -> #DIV/0! | H122: =H113/(H105*4) -> #DIV/0! | I122: =I113/(I105*4) -> #DIV/0! | J122: =J113/(J105*4) -> #DIV/0! | ... CH122: =CH113/(CH105*4) -> 0.73658353 | DE122: Net Debt/EBITDA | DF122: =DF113/(DF105) -> #DIV/0! | DG122: =DG113/(DG105) -> #DIV/0! | DH122: =DH113/(DH105) -> #DIV/0! | DI122: =DI113/(DI105) -> #DIV/0! | DJ122: =DJ113/(DJ105) -> #DIV/0! | DK122: =DK113/(DK105) -> #DIV/0! | DL122: =DL113/(DL105) -> #DIV/0! | DM122: =DM113/(DM105) -> #DIV/0! | ... EE122: =EE113/(EE105) -> -1.9605446
B124: Interest Coverage | DE124: Interest Coverage
B125: EBIT/Interest | C125: =C106/-C107 -> #REF! | D125: =D106/-D107 -> #REF! | E125: =E106/-E107 -> #REF! | F125: =F106/-F107 -> #REF! | G125: =G106/-G107 -> #REF! | H125: =H106/-H107 -> #REF! | I125: =I106/-I107 -> #REF! | J125: =J106/-J107 -> #REF! | ... CH125: =CH106/-CH107 -> #REF! | DE125: EBIT/Interest | DF125: =DF106/-DF107 -> #REF! | DG125: =DG106/-DG107 -> #REF! | DH125: =DH106/-DH107 -> #REF! | DI125: =DI106/-DI107 -> #REF! | DJ125: =DJ106/-DJ107 -> #REF! | DK125: =DK106/-DK107 -> #REF! | DL125: =DL106/-DL107 -> #REF! | DM125: =DM106/-DM107 -> #REF! | ... EE125: =EE106/-EE107 -> #REF!
B126: EBITDA/Interest | C126: =C105/-C107 -> #REF! | D126: =D105/-D107 -> #REF! | E126: =E105/-E107 -> #REF! | F126: =F105/-F107 -> #REF! | G126: =G105/-G107 -> #REF! | H126: =H105/-H107 -> #REF! | I126: =I105/-I107 -> #REF! | J126: =J105/-J107 -> #REF! | ... CH126: =CH105/-CH107 -> #REF! | DE126: EBITDA/Interest | DF126: =DF105/-DF107 -> #REF! | DG126: =DG105/-DG107 -> #REF! | DH126: =DH105/-DH107 -> #REF! | DI126: =DI105/-DI107 -> #REF! | DJ126: =DJ105/-DJ107 -> #REF! | DK126: =DK105/-DK107 -> #REF! | DL126: =DL105/-DL107 -> #REF! | DM126: =DM105/-DM107 -> #REF! | ... EE126: =EE105/-EE107 -> #REF!
B128: Book Value per Share | C128: ='Balance Sheet'!C48/C109 -> #DIV/0! | D128: ='Balance Sheet'!D48/D109 -> #DIV/0! | E128: ='Balance Sheet'!E48/E109 -> #DIV/0! | F128: ='Balance Sheet'!F48/F109 -> #DIV/0! | G128: ='Balance Sheet'!G48/G109 -> #DIV/0! | H128: ='Balance Sheet'!H48/H109 -> #DIV/0! | I128: ='Balance Sheet'!I48/I109 -> #DIV/0! | J128: ='Balance Sheet'!J48/J109 -> #DIV/0! | ... CH128: ='Balance Sheet'!CH48/CH109 -> 10.17907 | DE128: Book Value per Share | DF128: ='Balance Sheet'!DF48/DF109 -> #DIV/0! | DG128: ='Balance Sheet'!DG48/DG109 -> #DIV/0! | DH128: ='Balance Sheet'!DH48/DH109 -> #DIV/0! | DI128: ='Balance Sheet'!DI48/DI109 -> #DIV/0! | DJ128: ='Balance Sheet'!DJ48/DJ109 -> #DIV/0! | DK128: ='Balance Sheet'!DK48/DK109 -> #DIV/0! | DL128: ='Balance Sheet'!DL48/DL109 -> #DIV/0! | DM128: ='Balance Sheet'!DM48/DM109 -> #DIV/0! | ... EE128: ='Balance Sheet'!EE48/EE109 -> 17.303726
B130: Return Metrics | DE130: Return Metrics
...

Sheet Balance Sheet
A2: x | B2: Atlas Energy Solutions Limited
B3: Balance Sheet
B4: (US$ Millions)
C5: =VALUE(LEFT(C6,4)) -> 2005 | D5: =VALUE(LEFT(C6,4)) -> 2005 | E5: =VALUE(LEFT(C6,4)) -> 2005 | F5: =VALUE(LEFT(C6,4)) -> 2005 | G5: =VALUE(LEFT(G6,4)) -> 2006 | H5: =VALUE(LEFT(G6,4)) -> 2006 | I5: =VALUE(LEFT(G6,4)) -> 2006 | J5: =VALUE(LEFT(G6,4)) -> 2006 | K5: =VALUE(LEFT(K6,4)) -> 2007 | L5: =VALUE(LEFT(K6,4)) -> 2007 | M5: =VALUE(LEFT(K6,4)) -> 2007 | N5: =VALUE(LEFT(K6,4)) -> 2007 | O5: =VALUE(LEFT(O6,4)) -> 2008 | P5: =VALUE(LEFT(O6,4)) -> 2008 | Q5: =VALUE(LEFT(O6,4)) -> 2008 | R5: =VALUE(LEFT(O6,4)) -> 2008 | S5: =VALUE(LEFT(S6,4)) -> 2009 | T5: =VALUE(LEFT(S6,4)) -> 2009 | U5: =VALUE(LEFT(S6,4)) -> 2009 | V5: =VALUE(LEFT(S6,4)) -> 2009 | W5: =VALUE(LEFT(W6,4)) -> 2010 | X5: =VALUE(LEFT(W6,4)) -> 2010 | Y5: =VALUE(LEFT(W6,4)) -> 2010 | Z5: =VALUE(LEFT(W6,4)) -> 2010 | AA5: =VALUE(LEFT(AA6,4)) -> 2011 | AB5: =VALUE(LEFT(AA6,4)) -> 2011 | AC5: =VALUE(LEFT(AA6,4)) -> 2011 | AD5: =VALUE(LEFT(AA6,4)) -> 2011 | AE5: =VALUE(LEFT(AE6,4)) -> 2012 | AF5: =VALUE(LEFT(AE6,4)) -> 2012 | AG5: =VALUE(LEFT(AE6,4)) -> 2012 | AH5: =VALUE(LEFT(AE6,4)) -> 2012 | AI5: =VALUE(LEFT(AI6,4)) -> 2013 | AJ5: =VALUE(LEFT(AI6,4)) -> 2013 | AK5: =VALUE(LEFT(AI6,4)) -> 2013 | AL5: =VALUE(LEFT(AI6,4)) -> 2013 | AM5: =VALUE(LEFT(AM6,4)) -> 2014 | AN5: =VALUE(LEFT(AM6,4)) -> 2014 | AO5: =VALUE(LEFT(AM6,4)) -> 2014 | AP5: =VALUE(LEFT(AM6,4)) -> 2014 | AQ5: =VALUE(LEFT(AQ6,4)) -> 2015 | AR5: =VALUE(LEFT(AQ6,4)) -> 2015 | AS5: =VALUE(LEFT(AQ6,4)) -> 2015 | AT5: =VALUE(LEFT(AQ6,4)) -> 2015 | AU5: =VALUE(LEFT(AU6,4)) -> 2016 | AV5: =VALUE(LEFT(AU6,4)) -> 2016 | AW5: =VALUE(LEFT(AU6,4)) -> 2016 | AX5: =VALUE(LEFT(AU6,4)) -> 2016 | AY5: =VALUE(LEFT(AY6,4)) -> 2017 | AZ5: =VALUE(LEFT(AY6,4)) -> 2017 | BA5: =VALUE(LEFT(AY6,4)) -> 2017 | BB5: =VALUE(LEFT(AY6,4)) -> 2017 | BC5: =VALUE(LEFT(BC6,4)) -> 2018 | BD5: =VALUE(LEFT(BC6,4)) -> 2018 | BE5: =VALUE(LEFT(BC6,4)) -> 2018 | BF5: =VALUE(LEFT(BC6,4)) -> 2018 | BG5: =VALUE(LEFT(BG6,4)) -> 2019 | BH5: =VALUE(LEFT(BG6,4)) -> 2019 | BI5: =VALUE(LEFT(BG6,4)) -> 2019 | BJ5: =VALUE(LEFT(BG6,4)) -> 2019 | BK5: =VALUE(LEFT(BK6,4)) -> 2020 | BL5: =VALUE(LEFT(BK6,4)) -> 2020 | BM5: =VALUE(LEFT(BK6,4)) -> 2020 | BN5: =VALUE(LEFT(BK6,4)) -> 2020 | BO5: =VALUE(LEFT(BO6,4)) -> 2021 | BP5: =VALUE(LEFT(BO6,4)) -> 2021 | BQ5: =VALUE(LEFT(BO6,4)) -> 2021 | BR5: =VALUE(LEFT(BO6,4)) -> 2021 | BS5: =VALUE(LEFT(BS6,4)) -> 2022 | BT5: =VALUE(LEFT(BS6,4)) -> 2022 | BU5: =VALUE(LEFT(BS6,4)) -> 2022 | BV5: =VALUE(LEFT(BS6,4)) -> 2022 | BW5: =VALUE(LEFT(BW6,4)) -> 2023 | BX5: =VALUE(LEFT(BW6,4)) -> 2023 | BY5: =VALUE(LEFT(BW6,4)) -> 2023 | BZ5: =VALUE(LEFT(BW6,4)) -> 2023 | CA5: =VALUE(LEFT(CA6,4)) -> 2024 | CB5: =VALUE(LEFT(CA6,4)) -> 2024 | CC5: =VALUE(LEFT(CA6,4)) -> 2024 | CD5: =VALUE(LEFT(CA6,4)) -> 2024 | CE5: =VALUE(LEFT(CE6,4)) -> 2025 | CF5: =VALUE(LEFT(CE6,4)) -> 2025 | CG5: =VALUE(LEFT(CE6,4)) -> 2025 | CH5: =VALUE(LEFT(CE6,4)) -> 2025 | CI5: =VALUE(LEFT(CI6,4)) -> 2026 | CJ5: =VALUE(LEFT(CI6,4)) -> 2026 | CK5: =VALUE(LEFT(CI6,4)) -> 2026 | CL5: =VALUE(LEFT(CI6,4)) -> 2026 | CM5: =VALUE(LEFT(CM6,4)) -> 2027 | CN5: =VALUE(LEFT(CM6,4)) -> 2027 | CO5: =VALUE(LEFT(CM6,4)) -> 2027 | CP5: =VALUE(LEFT(CM6,4)) -> 2027 | CQ5: =VALUE(LEFT(CQ6,4)) -> 2028 | CR5: =VALUE(LEFT(CQ6,4)) -> 2028 | CS5: =VALUE(LEFT(CQ6,4)) -> 2028 | CT5: =VALUE(LEFT(CQ6,4)) -> 2028 | CU5: =VALUE(LEFT(CU6,4)) -> 2029 | CV5: =VALUE(LEFT(CU6,4)) -> 2029 | CW5: =VALUE(LEFT(CU6,4)) -> 2029 | CX5: =VALUE(LEFT(CU6,4)) -> 2029 | CY5: =VALUE(LEFT(CY6,4)) -> 2030 | CZ5: =VALUE(LEFT(CY6,4)) -> 2030 | DA5: =VALUE(LEFT(CY6,4)) -> 2030 | DB5: =VALUE(LEFT(CY6,4)) -> 2030 | DF5: =VALUE(LEFT(DF7,4)) -> 2005 | DG5: =VALUE(LEFT(DG7,4)) -> 2006 | DH5: =VALUE(LEFT(DH7,4)) -> 2007 | DI5: =VALUE(LEFT(DI7,4)) -> 2008 | DJ5: =VALUE(LEFT(DJ7,4)) -> 2009 | DK5: =VALUE(LEFT(DK7,4)) -> 2010 | DL5: =VALUE(LEFT(DL7,4)) -> 2011 | DM5: =VALUE(LEFT(DM7,4)) -> 2012 | ... EE5: =VALUE(LEFT(EE7,4)) -> 2030
C6: 2005 | G6: 2006 | K6: 2007 | O6: 2008 | S6: 2009 | W6: 2010 | AA6: 2011 | AE6: 2012 | AI6: 2013 | AM6: 2014 | AQ6: 2015 | AU6: 2016 | AY6: 2017 | BC6: 2018 | BG6: =BC6+1 -> 2019 | BK6: =BG6+1 -> 2020 | BO6: =BK6+1 -> 2021 | BS6: =BO6+1 -> 2022 | BW6: =BS6+1 -> 2023 | CA6: =BW6+1 -> 2024 | CE6: =CA6+1 -> 2025 | CI6: =CE6+1 -> 2026 | CM6: =CI6+1 -> 2027 | CQ6: =CM6+1 -> 2028 | CU6: =CQ6+1 -> 2029 | CY6: =CU6+1 -> 2030 | DE6: Balance Sheet (Full Year ending Dec 31)
C7: ="1Q"&RIGHT(C6,2) -> 1Q05 | D7: ="2Q"&RIGHT(C6,2) -> 2Q05 | E7: ="3Q"&RIGHT(C6,2) -> 3Q05 | F7: ="4Q"&RIGHT(C6,2) -> 4Q05 | G7: ="1Q"&RIGHT(G6,2) -> 1Q06 | H7: ="2Q"&RIGHT(G6,2) -> 2Q06 | I7: ="3Q"&RIGHT(G6,2) -> 3Q06 | J7: ="4Q"&RIGHT(G6,2) -> 4Q06 | K7: ="1Q"&RIGHT(K6,2) -> 1Q07 | L7: ="2Q"&RIGHT(K6,2) -> 2Q07 | M7: ="3Q"&RIGHT(K6,2) -> 3Q07 | N7: ="4Q"&RIGHT(K6,2) -> 4Q07 | O7: ="1Q"&RIGHT(O6,2) -> 1Q08 | P7: ="2Q"&RIGHT(O6,2) -> 2Q08 | Q7: ="3Q"&RIGHT(O6,2) -> 3Q08 | R7: ="4Q"&RIGHT(O6,2) -> 4Q08 | S7: ="1Q"&RIGHT(S6,2) -> 1Q09 | T7: ="2Q"&RIGHT(S6,2) -> 2Q09 | U7: ="3Q"&RIGHT(S6,2) -> 3Q09 | V7: ="4Q"&RIGHT(S6,2) -> 4Q09 | W7: ="1Q"&RIGHT(W6,2) -> 1Q10 | X7: ="2Q"&RIGHT(W6,2) -> 2Q10 | Y7: ="3Q"&RIGHT(W6,2) -> 3Q10 | Z7: ="4Q"&RIGHT(W6,2) -> 4Q10 | AA7: ="1Q"&RIGHT(AA6,2) -> 1Q11 | AB7: ="2Q"&RIGHT(AA6,2) -> 2Q11 | AC7: ="3Q"&RIGHT(AA6,2) -> 3Q11 | AD7: ="4Q"&RIGHT(AA6,2) -> 4Q11 | AE7: ="1Q"&RIGHT(AE6,2) -> 1Q12 | AF7: ="2Q"&RIGHT(AE6,2) -> 2Q12 | AG7: ="3Q"&RIGHT(AE6,2) -> 3Q12 | AH7: ="4Q"&RIGHT(AE6,2) -> 4Q12 | AI7: ="1Q"&RIGHT(AI6,2) -> 1Q13 | AJ7: ="2Q"&RIGHT(AI6,2) -> 2Q13 | AK7: ="3Q"&RIGHT(AI6,2) -> 3Q13 | AL7: ="4Q"&RIGHT(AI6,2) -> 4Q13 | AM7: ="1Q"&RIGHT(AM6,2) -> 1Q14 | AN7: ="2Q"&RIGHT(AM6,2) -> 2Q14 | AO7: ="3Q"&RIGHT(AM6,2) -> 3Q14 | AP7: ="4Q"&RIGHT(AM6,2) -> 4Q14 | AQ7: ="1Q"&RIGHT(AQ6,2) -> 1Q15 | AR7: ="2Q"&RIGHT(AQ6,2) -> 2Q15 | AS7: ="3Q"&RIGHT(AQ6,2) -> 3Q15 | AT7: ="4Q"&RIGHT(AQ6,2) -> 4Q15 | AU7: ="1Q"&RIGHT(AU6,2) -> 1Q16 | AV7: ="2Q"&RIGHT(AU6,2) -> 2Q16 | AW7: ="3Q"&RIGHT(AU6,2) -> 3Q16 | AX7: ="4Q"&RIGHT(AU6,2) -> 4Q16 | AY7: ="1Q"&RIGHT(AY6,2) -> 1Q17 | AZ7: ="2Q"&RIGHT(AY6,2) -> 2Q17 | BA7: ="3Q"&RIGHT(AY6,2) -> 3Q17 | BB7: ="4Q"&RIGHT(AY6,2) -> 4Q17 | BC7: ="1Q"&RIGHT(BC6,2) -> 1Q18 | BD7: ="2Q"&RIGHT(BC6,2) -> 2Q18 | BE7: ="3Q"&RIGHT(BC6,2) -> 3Q18 | BF7: ="4Q"&RIGHT(BC6,2) -> 4Q18 | BG7: ="1Q"&RIGHT(BG6,2) -> 1Q19 | BH7: ="2Q"&RIGHT(BG6,2) -> 2Q19 | BI7: ="3Q"&RIGHT(BG6,2) -> 3Q19 | BJ7: ="4Q"&RIGHT(BG6,2) -> 4Q19 | BK7: ="1Q"&RIGHT(BK6,2) -> 1Q20 | BL7: ="2Q"&RIGHT(BK6,2) -> 2Q20 | BM7: ="3Q"&RIGHT(BK6,2) -> 3Q20 | BN7: ="4Q"&RIGHT(BK6,2) -> 4Q20 | BO7: ="1Q"&RIGHT(BO6,2) -> 1Q21 | BP7: ="2Q"&RIGHT(BO6,2) -> 2Q21 | BQ7: ="3Q"&RIGHT(BO6,2) -> 3Q21 | BR7: ="4Q"&RIGHT(BO6,2) -> 4Q21 | BS7: ="1Q"&RIGHT(BS6,2) -> 1Q22 | BT7: ="2Q"&RIGHT(BS6,2) -> 2Q22 | BU7: ="3Q"&RIGHT(BS6,2) -> 3Q22 | BV7: ="4Q"&RIGHT(BS6,2) -> 4Q22 | BW7: ="1Q"&RIGHT(BW6,2) -> 1Q23 | BX7: ="2Q"&RIGHT(BW6,2) -> 2Q23 | BY7: ="3Q"&RIGHT(BW6,2) -> 3Q23 | BZ7: ="4Q"&RIGHT(BW6,2) -> 4Q23 | CA7: ="1Q"&RIGHT(CA6,2) -> 1Q24 | CB7: ="2Q"&RIGHT(CA6,2) -> 2Q24 | CC7: ="3Q"&RIGHT(CA6,2) -> 3Q24 | CD7: ="4Q"&RIGHT(CA6,2) -> 4Q24 | CE7: ="1Q"&RIGHT(CE6,2) -> 1Q25 | CF7: ="2Q"&RIGHT(CE6,2) -> 2Q25 | CG7: ="3Q"&RIGHT(CE6,2) -> 3Q25 | CH7: ="4Q"&RIGHT(CE6,2) -> 4Q25 | CI7: ="1Q"&RIGHT(CI6,2) -> 1Q26 | CJ7: ="2Q"&RIGHT(CI6,2) -> 2Q26 | CK7: ="3Q"&RIGHT(CI6,2) -> 3Q26 | CL7: ="4Q"&RIGHT(CI6,2) -> 4Q26 | CM7: ="1Q"&RIGHT(CM6,2) -> 1Q27 | CN7: ="2Q"&RIGHT(CM6,2) -> 2Q27 | CO7: ="3Q"&RIGHT(CM6,2) -> 3Q27 | CP7: ="4Q"&RIGHT(CM6,2) -> 4Q27 | CQ7: ="1Q"&RIGHT(CQ6,2) -> 1Q28 | CR7: ="2Q"&RIGHT(CQ6,2) -> 2Q28 | CS7: ="3Q"&RIGHT(CQ6,2) -> 3Q28 | CT7: ="4Q"&RIGHT(CQ6,2) -> 4Q28 | CU7: ="1Q"&RIGHT(CU6,2) -> 1Q29 | CV7: ="2Q"&RIGHT(CU6,2) -> 2Q29 | CW7: ="3Q"&RIGHT(CU6,2) -> 3Q29 | CX7: ="4Q"&RIGHT(CU6,2) -> 4Q29 | CY7: ="1Q"&RIGHT(CY6,2) -> 1Q30 | CZ7: ="2Q"&RIGHT(CY6,2) -> 2Q30 | DA7: ="3Q"&RIGHT(CY6,2) -> 3Q30 | DB7: ="4Q"&RIGHT(CY6,2) -> 4Q30 | DE7: (US$ Millions) | DF7: 2005 | DG7: =DF7+1 -> 2006 | DH7: =DG7+1 -> 2007 | DI7: =DH7+1 -> 2008 | DJ7: =DI7+1 -> 2009 | DK7: =DJ7+1 -> 2010 | DL7: =DK7+1 -> 2011 | DM7: =DL7+1 -> 2012 | DN7: =DM7+1 -> 2013 | ... DR7: =DQ7+1 -> 2017 | DS7: 2018 | DT7: =DS7+1 -> 2019 | DU7: =DT7+1 -> 2020 | DV7: =DU7+1 -> 2021 | DW7: =DV7+1 -> 2022 | DX7: =DW7+1 -> 2023 | DY7: =DX7+1 -> 2024 | DZ7: =DY7+1 -> 2025 | EA7: =DZ7+1 -> 2026 | ... EE7: =ED7+1 -> 2030
A8: x
B9: Current Assets | DE9: Current Assets
B10: Cash | BS10: 53.83638 | BT10: 69.009332 | BU10: 90.719619 | BV10: 82.010041 | BW10: 352.656 | BX10: 341.674 | BY10: 264.538 | BZ10: 210.174 | CA10: 187.12 | CB10: 104.723 | CC10: 78.637 | CD10: =CC10+'Cash Flow'!CD48 -> 52.35294 | CE10: =CD10+'Cash Flow'!CE48 -> 19.25834 | CF10: =CE10+'Cash Flow'!CF48 -> 21.833885 | CG10: =CF10+'Cash Flow'!CG48 -> 95.915836 | CH10: =CG10+'Cash Flow'!CH48 -> 156.85387 | CI10: =CH10+'Cash Flow'!CI48 -> 178.48512 | CJ10: =CI10+'Cash Flow'!CJ48 -> 224.43662 | CK10: =CJ10+'Cash Flow'!CK48 -> 257.27183 | ... DB10: =DA10+'Cash Flow'!DB48 -> 1200.9385 | DE10: Cash | DF10: =INDEX($C10:$DC10,MATCH(DF$5,$C$6:$DC$6,0)+3) -> 0 | DG10: =INDEX($C10:$DC10,MATCH(DG$5,$C$6:$DC$6,0)+3) -> 0 | DH10: =INDEX($C10:$DC10,MATCH(DH$5,$C$6:$DC$6,0)+3) -> 0 | DI10: =INDEX($C10:$DC10,MATCH(DI$5,$C$6:$DC$6,0)+3) -> 0 | DJ10: =INDEX($C10:$DC10,MATCH(DJ$5,$C$6:$DC$6,0)+3) -> 0 | DK10: =INDEX($C10:$DC10,MATCH(DK$5,$C$6:$DC$6,0)+3) -> 0 | DL10: =INDEX($C10:$DC10,MATCH(DL$5,$C$6:$DC$6,0)+3) -> 0 | DM10: =INDEX($C10:$DC10,MATCH(DM$5,$C$6:$DC$6,0)+3) -> 0 | ... DT10: =INDEX($C10:$DC10,MATCH(DT$5,$C$6:$DC$6,0)+3) -> 0 | DU10: 36.072472 | DV10: 40.400985 | DW10: =INDEX($C10:$DC10,MATCH(DW$5,$C$6:$DC$6,0)+3) -> 82.010041 | DX10: =INDEX($C10:$DC10,MATCH(DX$5,$C$6:$DC$6,0)+3) -> 210.174 | DY10: =INDEX($C10:$DC10,MATCH(DY$5,$C$6:$DC$6,0)+3) -> 52.35294 | DZ10: =INDEX($C10:$DC10,MATCH(DZ$5,$C$6:$DC$6,0)+3) -> 156.85387 | EA10: =INDEX($C10:$DC10,MATCH(EA$5,$C$6:$DC$6,0)+3) -> 324.39944 | EB10: =INDEX($C10:$DC10,MATCH(EB$5,$C$6:$DC$6,0)+3) -> 520.10409 | EC10: =INDEX($C10:$DC10,MATCH(EC$5,$C$6:$DC$6,0)+3) -> 203.92197 | ED10: =INDEX($C10:$DC10,MATCH(ED$5,$C$6:$DC$6,0)+3) -> 969.69755 | EE10: =INDEX($C10:$DC10,MATCH(EE$5,$C$6:$DC$6,0)+3) -> 1200.9385
B11: Short-term investments | BS11: 0 | BT11: 0 | BU11: 0 | BV11: 0 | BW11: 0 | BX11: 0 | BY11: 0 | BZ11: 0 | CA11: 0 | CB11: 0 | CC11: 0 | CD11: =CC11 -> 0 | CE11: =CD11 -> 0 | CF11: =CE11 -> 0 | CG11: =CF11 -> 0 | CH11: =CG11 -> 0 | CI11: =CH11 -> 0 | CJ11: =CI11 -> 0 | CK11: =CJ11 -> 0 | ... DB11: =DA11 -> 0 | DE11: Short-term investments | DF11: =INDEX($C11:$DC11,MATCH(DF$5,$C$6:$DC$6,0)+3) -> 0 | DG11: =INDEX($C11:$DC11,MATCH(DG$5,$C$6:$DC$6,0)+3) -> 0 | DH11: =INDEX($C11:$DC11,MATCH(DH$5,$C$6:$DC$6,0)+3) -> 0 | DI11: =INDEX($C11:$DC11,MATCH(DI$5,$C$6:$DC$6,0)+3) -> 0 | DJ11: =INDEX($C11:$DC11,MATCH(DJ$5,$C$6:$DC$6,0)+3) -> 0 | DK11: =INDEX($C11:$DC11,MATCH(DK$5,$C$6:$DC$6,0)+3) -> 0 | DL11: =INDEX($C11:$DC11,MATCH(DL$5,$C$6:$DC$6,0)+3) -> 0 | DM11: =INDEX($C11:$DC11,MATCH(DM$5,$C$6:$DC$6,0)+3) -> 0 | ... EE11: =INDEX($C11:$DC11,MATCH(EE$5,$C$6:$DC$6,0)+3) -> 0
B12: Accounts Receivable | BS12: 33.146973 | BT12: 74.028675 | BU12: 72.611938 | BV12: 73.341285 | BW12: 95.112 | BX12: 85.94 | BY12: 102.234 | BZ12: 71.17 | CA12: 185.758 | CB12: 197.072 | CC12: 179.924 | CD12: ='Balance Sheet'!CD72*'Balance Sheet'!CD76/90 -> 164.46769 | CE12: ='Balance Sheet'!CE72*'Balance Sheet'!CE76/90 -> 181.44167 | CF12: ='Balance Sheet'!CF72*'Balance Sheet'!CF76/90 -> 209.46416 | CG12: ='Balance Sheet'!CG72*'Balance Sheet'!CG76/90 -> 160.13428 | CH12: ='Balance Sheet'!CH72*'Balance Sheet'!CH76/90 -> 136.64848 | CI12: ='Balance Sheet'!CI72*'Balance Sheet'!CI76/90 -> 167.51074 | CJ12: ='Balance Sheet'!CJ72*'Balance Sheet'!CJ76/90 -> 176.7973 | CK12: ='Balance Sheet'!CK72*'Balance Sheet'!CK76/90 -> 201.39191 | ... DB12: ='Balance Sheet'!DB72*'Balance Sheet'!DB76/90 -> 268.15094 | DE12: Accounts Receivable | DF12: =INDEX($C12:$DC12,MATCH(DF$5,$C$6:$DC$6,0)+3) -> 0 | DG12: =INDEX($C12:$DC12,MATCH(DG$5,$C$6:$DC$6,0)+3) -> 0 | DH12: =INDEX($C12:$DC12,MATCH(DH$5,$C$6:$DC$6,0)+3) -> 0 | DI12: =INDEX($C12:$DC12,MATCH(DI$5,$C$6:$DC$6,0)+3) -> 0 | DJ12: =INDEX($C12:$DC12,MATCH(DJ$5,$C$6:$DC$6,0)+3) -> 0 | DK12: =INDEX($C12:$DC12,MATCH(DK$5,$C$6:$DC$6,0)+3) -> 0 | DL12: =INDEX($C12:$DC12,MATCH(DL$5,$C$6:$DC$6,0)+3) -> 0 | DM12: =INDEX($C12:$DC12,MATCH(DM$5,$C$6:$DC$6,0)+3) -> 0 | ... DT12: =INDEX($C12:$DC12,MATCH(DT$5,$C$6:$DC$6,0)+3) -> 0 | DU12: 11.508702 | DV12: 29.41804 | DW12: =INDEX($C12:$DC12,MATCH(DW$5,$C$6:$DC$6,0)+3) -> 73.341285 | DX12: =INDEX($C12:$DC12,MATCH(DX$5,$C$6:$DC$6,0)+3) -> 71.17 | DY12: =INDEX($C12:$DC12,MATCH(DY$5,$C$6:$DC$6,0)+3) -> 164.46769 | DZ12: =INDEX($C12:$DC12,MATCH(DZ$5,$C$6:$DC$6,0)+3) -> 136.64848 | EA12: =INDEX($C12:$DC12,MATCH(EA$5,$C$6:$DC$6,0)+3) -> 203.08112 | EB12: =INDEX($C12:$DC12,MATCH(EB$5,$C$6:$DC$6,0)+3) -> 210.68777 | EC12: =INDEX($C12:$DC12,MATCH(EC$5,$C$6:$DC$6,0)+3) -> 225.4263 | ED12: =INDEX($C12:$DC12,MATCH(ED$5,$C$6:$DC$6,0)+3) -> 255.83355 | EE12: =INDEX($C12:$DC12,MATCH(EE$5,$C$6:$DC$6,0)+3) -> 268.15094
B13: Inventories | BS13: 12.860898 | BT13: 14.44792 | BU13: 16.394109 | BV13: 23.380277 | BW13: 22.886 | BX13: 26.654 | BY13: 34.752 | BZ13: 37.342 | CA13: 52.619 | CB13: 63.361 | CC13: 57.952 | CD13: ='Balance Sheet'!CD77*'Balance Sheet'!CD74/90 -> 48.033726 | CE13: ='Balance Sheet'!CE77*'Balance Sheet'!CE74/90 -> 52.723156 | CF13: ='Balance Sheet'!CF77*'Balance Sheet'!CF74/90 -> 56.666909 | CG13: ='Balance Sheet'!CG77*'Balance Sheet'!CG74/90 -> 54.290084 | CH13: ='Balance Sheet'!CH77*'Balance Sheet'!CH74/90 -> 49.972685 | CI13: ='Balance Sheet'!CI77*'Balance Sheet'!CI74/90 -> 49.175037 | CJ13: ='Balance Sheet'!CJ77*'Balance Sheet'!CJ74/90 -> 52.178083 | CK13: ='Balance Sheet'!CK77*'Balance Sheet'!CK74/90 -> 52.692541 | ... DB13: ='Balance Sheet'!DB77*'Balance Sheet'!DB74/90 -> 53.600957 | DE13: Inventories | DF13: =INDEX($C13:$DC13,MATCH(DF$5,$C$6:$DC$6,0)+3) -> 0 | DG13: =INDEX($C13:$DC13,MATCH(DG$5,$C$6:$DC$6,0)+3) -> 0 | DH13: =INDEX($C13:$DC13,MATCH(DH$5,$C$6:$DC$6,0)+3) -> 0 | DI13: =INDEX($C13:$DC13,MATCH(DI$5,$C$6:$DC$6,0)+3) -> 0 | DJ13: =INDEX($C13:$DC13,MATCH(DJ$5,$C$6:$DC$6,0)+3) -> 0 | DK13: =INDEX($C13:$DC13,MATCH(DK$5,$C$6:$DC$6,0)+3) -> 0 | DL13: =INDEX($C13:$DC13,MATCH(DL$5,$C$6:$DC$6,0)+3) -> 0 | DM13: =INDEX($C13:$DC13,MATCH(DM$5,$C$6:$DC$6,0)+3) -> 0 | ... DT13: =INDEX($C13:$DC13,MATCH(DT$5,$C$6:$DC$6,0)+3) -> 0 | DU13: 11.058387 | DV13: 14.359091 | DW13: =INDEX($C13:$DC13,MATCH(DW$5,$C$6:$DC$6,0)+3) -> 23.380277 | DX13: =INDEX($C13:$DC13,MATCH(DX$5,$C$6:$DC$6,0)+3) -> 37.342 | DY13: =INDEX($C13:$DC13,MATCH(DY$5,$C$6:$DC$6,0)+3) -> 48.033726 | DZ13: =INDEX($C13:$DC13,MATCH(DZ$5,$C$6:$DC$6,0)+3) -> 49.972685 | EA13: =INDEX($C13:$DC13,MATCH(EA$5,$C$6:$DC$6,0)+3) -> 50.148797 | EB13: =INDEX($C13:$DC13,MATCH(EB$5,$C$6:$DC$6,0)+3) -> 55.397488 | EC13: =INDEX($C13:$DC13,MATCH(EC$5,$C$6:$DC$6,0)+3) -> 0 | ED13: =INDEX($C13:$DC13,MATCH(ED$5,$C$6:$DC$6,0)+3) -> 54.201905 | EE13: =INDEX($C13:$DC13,MATCH(EE$5,$C$6:$DC$6,0)+3) -> 53.600957
B14: Other Current Assets | BS14: 0 | BT14: 0 | BU14: 0 | BV14: 0 | BW14: 0 | BX14: 0 | BY14: 0 | BZ14: 0 | CA14: 0 | CB14: 0 | CC14: 0 | CD14: =CC14 -> 0 | CE14: =CD14 -> 0 | CF14: =CE14 -> 0 | CG14: =CF14 -> 0 | CH14: =CG14 -> 0 | CI14: =CH14 -> 0 | CJ14: =CI14 -> 0 | CK14: =CJ14 -> 0 | ... DB14: =DA14 -> 0 | DE14: Other Current Assets | DF14: =INDEX($C14:$DC14,MATCH(DF$5,$C$6:$DC$6,0)+3) -> 0 | DG14: =INDEX($C14:$DC14,MATCH(DG$5,$C$6:$DC$6,0)+3) -> 0 | DH14: =INDEX($C14:$DC14,MATCH(DH$5,$C$6:$DC$6,0)+3) -> 0 | DI14: =INDEX($C14:$DC14,MATCH(DI$5,$C$6:$DC$6,0)+3) -> 0 | DJ14: =INDEX($C14:$DC14,MATCH(DJ$5,$C$6:$DC$6,0)+3) -> 0 | DK14: =INDEX($C14:$DC14,MATCH(DK$5,$C$6:$DC$6,0)+3) -> 0 | DL14: =INDEX($C14:$DC14,MATCH(DL$5,$C$6:$DC$6,0)+3) -> 0 | DM14: =INDEX($C14:$DC14,MATCH(DM$5,$C$6:$DC$6,0)+3) -> 0 | ... EE14: =INDEX($C14:$DC14,MATCH(EE$5,$C$6:$DC$6,0)+3) -> 0
B15: Total Current Assets | C15: =SUM(C10:C14) -> 0 | D15: =SUM(D10:D14) -> 0 | E15: =SUM(E10:E14) -> 0 | F15: =SUM(F10:F14) -> 0 | G15: =SUM(G10:G14) -> 0 | H15: =SUM(H10:H14) -> 0 | I15: =SUM(I10:I14) -> 0 | J15: =SUM(J10:J14) -> 0 | ... DB15: =SUM(DB10:DB14) -> 1522.6904 | DE15: Total Current Assets | DF15: =INDEX($C15:$DC15,MATCH(DF$5,$C$6:$DC$6,0)+3) -> 0 | DG15: =INDEX($C15:$DC15,MATCH(DG$5,$C$6:$DC$6,0)+3) -> 0 | DH15: =INDEX($C15:$DC15,MATCH(DH$5,$C$6:$DC$6,0)+3) -> 0 | DI15: =INDEX($C15:$DC15,MATCH(DI$5,$C$6:$DC$6,0)+3) -> 0 | DJ15: =INDEX($C15:$DC15,MATCH(DJ$5,$C$6:$DC$6,0)+3) -> 0 | DK15: =INDEX($C15:$DC15,MATCH(DK$5,$C$6:$DC$6,0)+3) -> 0 | DL15: =INDEX($C15:$DC15,MATCH(DL$5,$C$6:$DC$6,0)+3) -> 0 | DM15: =INDEX($C15:$DC15,MATCH(DM$5,$C$6:$DC$6,0)+3) -> 0 | ... DT15: =INDEX($C15:$DC15,MATCH(DT$5,$C$6:$DC$6,0)+3) -> 0 | DU15: =SUM(DU10:DU13) -> 58.63956 | DV15: =SUM(DV10:DV13) -> 84.178116 | DW15: =INDEX($C15:$DC15,MATCH(DW$5,$C$6:$DC$6,0)+3) -> 178.7316 | DX15: =INDEX($C15:$DC15,MATCH(DX$5,$C$6:$DC$6,0)+3) -> 318.686 | DY15: =INDEX($C15:$DC15,MATCH(DY$5,$C$6:$DC$6,0)+3) -> 264.85436 | DZ15: =INDEX($C15:$DC15,MATCH(DZ$5,$C$6:$DC$6,0)+3) -> 343.47504 | EA15: =INDEX($C15:$DC15,MATCH(EA$5,$C$6:$DC$6,0)+3) -> 577.62935 | EB15: =INDEX($C15:$DC15,MATCH(EB$5,$C$6:$DC$6,0)+3) -> 786.18934 | EC15: =INDEX($C15:$DC15,MATCH(EC$5,$C$6:$DC$6,0)+3) -> 429.34826 | ED15: =INDEX($C15:$DC15,MATCH(ED$5,$C$6:$DC$6,0)+3) -> 1279.733 | EE15: =INDEX($C15:$DC15,MATCH(EE$5,$C$6:$DC$6,0)+3) -> 1522.6904
B17: Long-Term Assets | DE17: Long-Term Assets
B18: Investments | BS18: 0 | BT18: 0 | BU18: =BT18-'Cash Flow'!BU30-'Cash Flow'!BU32 -> 0 | BV18: 0 | BW18: 0 | BX18: 0 | BY18: 0 | BZ18: 0 | CA18: 0 | CB18: 0 | CC18: 0 | CD18: =CC18-'Cash Flow'!CD30-'Cash Flow'!CD32 -> 0 | CE18: =CD18-'Cash Flow'!CE30-'Cash Flow'!CE32 -> 0 | CF18: =CE18-'Cash Flow'!CF30-'Cash Flow'!CF32 -> 0 | CG18: =CF18-'Cash Flow'!CG30-'Cash Flow'!CG32 -> 0 | CH18: =CG18-'Cash Flow'!CH30-'Cash Flow'!CH32 -> 0 | CI18: =CH18-'Cash Flow'!CI30-'Cash Flow'!CI32 -> 0 | CJ18: =CI18-'Cash Flow'!CJ30-'Cash Flow'!CJ32 -> 0 | CK18: =CJ18-'Cash Flow'!CK30-'Cash Flow'!CK32 -> 0 | ... DB18: =DA18-'Cash Flow'!DB30-'Cash Flow'!DB32 -> 0 | DE18: Investments | DF18: =INDEX($C18:$DC18,MATCH(DF$5,$C$6:$DC$6,0)+3) -> 0 | DG18: =INDEX($C18:$DC18,MATCH(DG$5,$C$6:$DC$6,0)+3) -> 0 | DH18: =INDEX($C18:$DC18,MATCH(DH$5,$C$6:$DC$6,0)+3) -> 0 | DI18: =INDEX($C18:$DC18,MATCH(DI$5,$C$6:$DC$6,0)+3) -> 0 | DJ18: =INDEX($C18:$DC18,MATCH(DJ$5,$C$6:$DC$6,0)+3) -> 0 | DK18: =INDEX($C18:$DC18,MATCH(DK$5,$C$6:$DC$6,0)+3) -> 0 | DL18: =INDEX($C18:$DC18,MATCH(DL$5,$C$6:$DC$6,0)+3) -> 0 | DM18: =INDEX($C18:$DC18,MATCH(DM$5,$C$6:$DC$6,0)+3) -> 0 | ... EE18: =INDEX($C18:$DC18,MATCH(EE$5,$C$6:$DC$6,0)+3) -> 0
B19: Property, Plant, & Equipment (Net) | BS19: 461.02157 | BT19: 470.82171 | BU19: 507.21506 | BV19: 541.5241 | BW19: 601.964 | BX19: 700.018 | BY19: 828.997 | BZ19: 934.66 | CA19: 1287.505 | CB19: 1403.417 | CC19: 1449.54 | CD19: =CC19-'Cash Flow'!CD28-'Cash Flow'!CD11-'Cash Flow'!CD29 -> 1482.9219 | CE19: =CD19-'Cash Flow'!CE28-'Cash Flow'!CE11-'Cash Flow'!CE29 -> 1498.4131 | CF19: =CE19-'Cash Flow'!CF28-'Cash Flow'!CF11-'Cash Flow'!CF29 -> 1512.4902 | CG19: =CF19-'Cash Flow'!CG28-'Cash Flow'!CG11-'Cash Flow'!CG29 -> 1538.5038 | CH19: =CG19-'Cash Flow'!CH28-'Cash Flow'!CH11-'Cash Flow'!CH29 -> 1571.3321 | CI19: =CH19-'Cash Flow'!CI28-'Cash Flow'!CI11-'Cash Flow'!CI29 -> 1578.282 | CJ19: =CI19-'Cash Flow'!CJ28-'Cash Flow'!CJ11-'Cash Flow'!CJ29 -> 1577.8077 | CK19: =CJ19-'Cash Flow'!CK28-'Cash Flow'!CK11-'Cash Flow'!CK29 -> 1570.6021 | ... DB19: =DA19-'Cash Flow'!DB28-'Cash Flow'!DB11-'Cash Flow'!DB29 -> 1448.107 | DE19: Property, Plant, & Equipment (Net) | DF19: =INDEX($C19:$DC19,MATCH(DF$5,$C$6:$DC$6,0)+3) -> 0 | DG19: =INDEX($C19:$DC19,MATCH(DG$5,$C$6:$DC$6,0)+3) -> 0 | DH19: =INDEX($C19:$DC19,MATCH(DH$5,$C$6:$DC$6,0)+3) -> 0 | DI19: =INDEX($C19:$DC19,MATCH(DI$5,$C$6:$DC$6,0)+3) -> 0 | DJ19: =INDEX($C19:$DC19,MATCH(DJ$5,$C$6:$DC$6,0)+3) -> 0 | DK19: =INDEX($C19:$DC19,MATCH(DK$5,$C$6:$DC$6,0)+3) -> 0 | DL19: =INDEX($C19:$DC19,MATCH(DL$5,$C$6:$DC$6,0)+3) -> 0 | DM19: =INDEX($C19:$DC19,MATCH(DM$5,$C$6:$DC$6,0)+3) -> 0 | ... DT19: =INDEX($C19:$DC19,MATCH(DT$5,$C$6:$DC$6,0)+3) -> 0 | DU19: 461.08988 | DV19: 458.31674 | DW19: =INDEX($C19:$DC19,MATCH(DW$5,$C$6:$DC$6,0)+3) -> 541.5241 | DX19: =INDEX($C19:$DC19,MATCH(DX$5,$C$6:$DC$6,0)+3) -> 934.66 | DY19: =INDEX($C19:$DC19,MATCH(DY$5,$C$6:$DC$6,0)+3) -> 1482.9219 | DZ19: =INDEX($C19:$DC19,MATCH(DZ$5,$C$6:$DC$6,0)+3) -> 1571.3321 | EA19: =INDEX($C19:$DC19,MATCH(EA$5,$C$6:$DC$6,0)+3) -> 1563.3965 | EB19: =INDEX($C19:$DC19,MATCH(EB$5,$C$6:$DC$6,0)+3) -> 1534.5742 | EC19: =INDEX($C19:$DC19,MATCH(EC$5,$C$6:$DC$6,0)+3) -> 1505.7518 | ED19: =INDEX($C19:$DC19,MATCH(ED$5,$C$6:$DC$6,0)+3) -> 1476.9294 | EE19: =INDEX($C19:$DC19,MATCH(EE$5,$C$6:$DC$6,0)+3) -> 1448.107
B20: Goodwill | BS20: 0 | BT20: =BS20 -> 0 | BU20: 0 | BV20: 0 | BW20: 0 | BX20: 0 | BY20: 0 | BZ20: 0 | CA20: 91.171 | CB20: 75.219 | CC20: 75.219 | CD20: =CC20 -> 75.219 | CE20: =CD20 -> 75.219 | CF20: =CE20 -> 75.219 | CG20: =CF20 -> 75.219 | CH20: =CG20 -> 75.219 | CI20: =CH20 -> 75.219 | CJ20: =CI20 -> 75.219 | CK20: =CJ20 -> 75.219 | ... DB20: =DA20 -> 75.219 | DE20: Goodwill | DF20: =INDEX($C20:$DC20,MATCH(DF$5,$C$6:$DC$6,0)+3) -> 0 | DG20: =INDEX($C20:$DC20,MATCH(DG$5,$C$6:$DC$6,0)+3) -> 0 | DH20: =INDEX($C20:$DC20,MATCH(DH$5,$C$6:$DC$6,0)+3) -> 0 | DI20: =INDEX($C20:$DC20,MATCH(DI$5,$C$6:$DC$6,0)+3) -> 0 | DJ20: =INDEX($C20:$DC20,MATCH(DJ$5,$C$6:$DC$6,0)+3) -> 0 | DK20: =INDEX($C20:$DC20,MATCH(DK$5,$C$6:$DC$6,0)+3) -> 0 | DL20: =INDEX($C20:$DC20,MATCH(DL$5,$C$6:$DC$6,0)+3) -> 0 | DM20: =INDEX($C20:$DC20,MATCH(DM$5,$C$6:$DC$6,0)+3) -> 0 | ... EE20: =INDEX($C20:$DC20,MATCH(EE$5,$C$6:$DC$6,0)+3) -> 75.219
B21: Intangible Assets | BS21: 0 | BT21: =BS21 -> 0 | BU21: 0 | BV21: 0 | BW21: 0 | BX21: 0 | BY21: 0 | BZ21: 0 | CA21: 112.462 | CB21: 112.422 | CC21: 109.281 | CD21: =CC21 -> 109.281 | CE21: =CD21 -> 109.281 | CF21: =CE21 -> 109.281 | CG21: =CF21 -> 109.281 | CH21: =CG21 -> 109.281 | CI21: =CH21 -> 109.281 | CJ21: =CI21 -> 109.281 | CK21: =CJ21 -> 109.281 | ... DB21: =DA21 -> 109.281 | DE21: Intangible Assets | DF21: =INDEX($C21:$DC21,MATCH(DF$5,$C$6:$DC$6,0)+3) -> 0 | DG21: =INDEX($C21:$DC21,MATCH(DG$5,$C$6:$DC$6,0)+3) -> 0 | DH21: =INDEX($C21:$DC21,MATCH(DH$5,$C$6:$DC$6,0)+3) -> 0 | DI21: =INDEX($C21:$DC21,MATCH(DI$5,$C$6:$DC$6,0)+3) -> 0 | DJ21: =INDEX($C21:$DC21,MATCH(DJ$5,$C$6:$DC$6,0)+3) -> 0 | DK21: =INDEX($C21:$DC21,MATCH(DK$5,$C$6:$DC$6,0)+3) -> 0 | DL21: =INDEX($C21:$DC21,MATCH(DL$5,$C$6:$DC$6,0)+3) -> 0 | DM21: =INDEX($C21:$DC21,MATCH(DM$5,$C$6:$DC$6,0)+3) -> 0 | ... EE21: =INDEX($C21:$DC21,MATCH(EE$5,$C$6:$DC$6,0)+3) -> 109.281
